Workbook
Name lis_act: [1]listas!$L$11:$L$30
Name lis_act: listas!$L$11:$L$30
Name lis_act2: [1]listas!$Q$11:$Q$27
Name lis_act2: listas!$Q$11:$Q$27
Name lis_dat: [1]datos!$A$10:$A$129
Name lis_dat: datos!$A$10:$A$129
Name lis_ma: listas!$B$12:$B$95
Name lis_rub: [1]listas!$J$11:$J$23
Name lis_rub: listas!$J$11:$J$23
Name ran: listas!$J$79
Name ran_act: [1]listas!$L$11:$N$30
Name ran_act: listas!$L$11:$N$30
Name ran_act2: [1]listas!$Q$11:$V$27
Name ran_act2: listas!$Q$11:$V$27
Name ran_dat: [1]datos!$A$1:$NP$300
Name ran_dat: datos!$A$1:$NP$300
Name ran_expo: #REF!
Name ran_idma: [1]listas!$C$12:$D$143
Name ran_idma: listas!$C$12:$D$143
Name ran_impo: #REF!
Name ran_ma: [1]listas!$B$12:$G$143
Name ran_ma: listas!$B$12:$G$143

Sheet Guia
G1: Datos de…
B2: Bases de Datos | G2: 45778 | H2: 45809 | I2: 45839 | J2: 45870 | K2: 45901 | L2: 45931 | M2: 45962 | N2: 45992 | O2: 46023 | P2: 46054 | Q2: 46082 | R2: 46113 | S2: 46143 | T2: 46174 | U2: 46204 | V2: 46235 | W2: 46266
A3: https://x.com/DatosAlfa | B3: 0 Precios MCBA | C3: https://www.mercadocentral.gob.ar/informaci%C3%B3n/precios-mayoristas | D3: Excel para obtener los precios promedios mensuales de hortalizas y frutas | Z3: 45992 | AA3: 46023 | AB3: 46054 | AC3: 46082 | AD3: 46113 | AE3: 46143 | AF3: 46174 | AG3: 46204
B4: Precios Pollo | C4: https://www.catedraavicola.com.ar/cotizaciones/ | D4: Excel para obtener los precios promedios mensuales de huevos y pollo | Y4: Algodón
B5: CONI_comercio_exterior | C5: https://comex.indec.gob.ar/#/database | D5: Excel para obtener datos de exportacion e importacion | Y5: Arroz
Y6: Aves
B7: Variables Macro | D7: Fuente | E7: Link | F7: Tipo de dato | Y7: Bovinos
B8: Dólar BNA | D8: Banco Nacion | E8: https://www.bna.com.ar/Personas | F8: Promedio mensual compra-venta | Y8: Cítricos Dulces
B9: Inflacion | D9: INDEC | E9: https://www.indec.gob.ar/indec/web/Nivel4-Tema-3-5-31 | F9: Indice IPC | Y9: Forestal
B10: Salario Peon Rural | D10: CNTA | E10: http://trabajoagrarioweb.trabajo.gob.ar/Consultas/Consulta.asp | F10: Salario mensual | Y10: Granos
B11: Insumos | Y11: Hortalizas
B12: Precio Gasoil | D12: Margenes | E12: https://www.margenes.com/ | F12: Precio de 100 lt de gasoil en dolares | Y12: Leche | Z12: 3
B13: Urea | D13: Margenes | E13: https://www.margenes.com/ | F13: Precio Urea Granulada por tonelada en dolares | Y13: Mandioca | Z13: Denis
B14: Glifosato | D14: Margenes | E14: https://www.margenes.com/ | F14: Precio Glifosato 54% por litro en dolares | Y14: Maní | Z14: Gaich
B15: Flete | D15: Margenes | E15: https://www.margenes.com/ | F15: Precio por flete de 300 km por tonelada de grano en dolares | Y15: Miel
Y16: Ovino
B17: Precio al Productor | D17: Fuente | E17: Link | F17: Tipo de dato | Y17: Papa | Z17: Mario
B18: Algodón | C18: C 1/2 | D18: SAGyP | E18: https://www.magyp.gob.ar/sitio/areas/ss_mercados_agropecuarios/areas/regionales/index.php | F18: Precio promedio mensual al mercado interno. Grado C 1/2 | Y18: Peras y Manzanas | Z18: Riskin, secretario de fruticultuta RN
C19: D 1/2 | D19: SAGyP | E19: https://www.magyp.gob.ar/sitio/areas/ss_mercados_agropecuarios/areas/regionales/index.php | F19: Precio promedio mensual al mercado interno. Grado D 1/2 | Y19: Porcinos
B20: Arroz | D20: SAGyP | E20: https://www.magyp.gob.ar/sitio/areas/ss_mercados_agropecuarios/areas/regionales/index.php | F20: Precio de arroz cascara Largo Fino | Y20: Tabaco
B21: Granos | C21: Cebada | D21: BCBB | E21: https://www.bcp.org.ar/cotizaciones.asp | F21: Precio promedio en puerto de Bahia Blanca | Y21: Vino y Mosto
C22: Girasol | D22: BCR | E22: https://www.cac.bcr.com.ar/es/precios-de-pizarra/consultas | F22: Precio pizarra promedio mensual | Y22: Yerba Mate | Z22: Denis
C23: Maíz | D23: Matba Rofex | E23: https://cem.matbarofex.com.ar/ | F23: Precio promedio mensual - MAI Dolar MATBA.Cuando arranque la siembra tomar Posicion de ABRIL de la campaña. Mientras tanto Tomar futuro del mes mas cercano
C24: Soja | D24: Matba Rofex | E24: https://cem.matbarofex.com.ar/ | F24: Precio promedio mensual - SOJ Dolar MATBA.Cuando arranque la siembra tomar Posicion de MAYO de la campaña. Mientras tanto Tomar futuro del mes mas cercano
C25: Sorgo | D25: SAGyP | E25: https://dinem.magyp.gob.ar/dinem_fob.WP_ConsProdf.aspx | F25: Precio mensual. Sorgo granífero, Los Demás, A granel con hasta un 15 % embolsado
C26: Trigo | D26: Matba Rofex | E26: https://cem.matbarofex.com.ar/ | F26: Precio promedio mensual - TRI Dolar MATBA.Cuando arranque la siembra tomar Posicion de ENERO de la campaña. Mientras tanto Tomar futuro del mes mas cercano
B27: Mani | D27: BCCBA | E27: https://bccba.org.ar/ | F27: Precio pizarra disponible Mani Runner
B28: Yerba Mate | C28: Hoja Verde | D28: PARTICULAR | E28: - | F28: Precio promedio mensual entre Coop y Sector Privado
C29: Canchada | D29: PARTICULAR | E29: - | F29: Precio promedio mensual entre Coop y Sector Privado
B30: Vino | C30: Tinto | D30: BCM | E30: https://bolsamza.com.ar/estadisticas-de-uvas-del-mercado-vitivinicola/ | F30: Precio promedio gral. variedad TINTO
C31: Blanco | D31: BCM | E31: https://bolsamza.com.ar/estadisticas-de-uvas-del-mercado-vitivinicola/ | F31: Precio promedio gral. variedad BLANCO
C32: Rosado | D32: BCM | E32: https://bolsamza.com.ar/estadisticas-de-uvas-del-mercado-vitivinicola/ | F32: Precio promedio gral. variedad ROSADO
B33: Mosto | D33: BCM | E33: https://bolsamza.com.ar/estadisticas-de-uvas-del-mercado-vitivinicola/ | F33: Precio promedio mosto SULFITADO
B34: Manzanas | D34: MCBA | E34: https://www.mercadocentral.gob.ar/informaci%C3%B3n/precios-mayoristas | F34: Precio promedio tipo RED DELICIUS. (MO - Modal)
B35: Peras | D35: MCBA | E35: https://www.mercadocentral.gob.ar/informaci%C3%B3n/precios-mayoristas | F35: Precio promedio especial. (MO - Modal)
B36: Limon | D36: MCBA | E36: https://www.mercadocentral.gob.ar/informaci%C3%B3n/precios-mayoristas | F36: Precio Eureka. (MO - Modal)
B37: Citricos Dulces | C37: Mandarina | D37: MCBA | E37: https://www.mercadocentral.gob.ar/informaci%C3%B3n/precios-mayoristas | F37: Precio promedio especial. (MO - Modal)
C38: Naranja | D38: MCBA | E38: https://www.mercadocentral.gob.ar/informaci%C3%B3n/precios-mayoristas | F38: Precio tipo Valencia. (MO - Modal)
C39: Pomelo | D39: MCBA | E39: https://www.mercadocentral.gob.ar/informaci%C3%B3n/precios-mayoristas | F39: Precio promedio especial. (MO - Modal)
B40: Hortalizas | C40: Papa | D40: MCBA | E40: https://www.mercadocentral.gob.ar/informaci%C3%B3n/precios-mayoristas | F40: Precio promedio tipo SPUNTA. (MO - Modal)
C41: Mandioca | D41: MCBA | E41: https://www.mercadocentral.gob.ar/informaci%C3%B3n/precios-mayoristas | F41: Precio promedio especial. (MO - Modal)
C42: Cebolla | D42: MCBA | E42: https://www.mercadocentral.gob.ar/informaci%C3%B3n/precios-mayoristas | F42: Precio promedio especial. (MO - Modal)
C43: Tomate | D43: MCBA | E43: https://www.mercadocentral.gob.ar/informaci%C3%B3n/precios-mayoristas | F43: PrecioRedondo. (MO - Modal)
C44: Zanahoria | D44: MCBA | E44: https://www.mercadocentral.gob.ar/informaci%C3%B3n/precios-mayoristas | F44: Precio promedio especial. (MO - Modal)
C45: Zapallo | D45: MCBA | E45: https://www.mercadocentral.gob.ar/informaci%C3%B3n/precios-mayoristas | F45: Precio promedio tipo ANQUITO. (MO - Modal)
B46: Forestacion | C46: Pino 25-30 pf | D46: Instituto Forestal Misiones | E46: https://infopro.misiones.gob.ar/index.php/category/precios-materia-prima/ | F46: Precio Pino Resinoso, trozas podadas de 25 - 29,9 cm | L46: 45931
C47: Pino +16 pf | D47: INTA Concordia | E47: https://drive.google.com/drive/folders/1Gl3471K-NMJGDsoWq2Y00Eix3W-1qWhM | F47: Precio Pino +16 cm en punta fina. Monte en pie. Madera para aserradero | G47: 45717 | I47: 45839 | L47: 45931 | Q47: 46082
C48: Euca 25-30 pf | D48: Instituto Forestal Misiones | E48: https://infopro.misiones.gob.ar/index.php/category/precios-materia-prima/ | F48: Precio Eucalipto, trozas podadas de 25 - 29,9 cm | L48: 45931
C49: Euca +18 pf | D49: INTA Concordia | E49: https://drive.google.com/drive/folders/1Gl3471K-NMJGDsoWq2Y00Eix3W-1qWhM | F49: Precio Eucalipto +18 cm en punta fina. Monte en pie. Madera para aserradero | G49: 45717 | I49: 45839 | L49: 45931 | Q49: 46082
B50: Tabaco | C50: Virginia B1F | D50: Camara del tabaco - Salta | E50: https://www.ctsalta.com.ar/category/precios/ | F50: Precio de campaña tabaco Virginia B1F - Acopio | G50: 45717 | P50: 25/26
D51: SAGyP | E51: https://www.magyp.gob.ar/sitio/areas/tabaco/normativa/precios/index.php | F51: Precio FET Virginia | G51: 45717 | Q51: 46082
B52: Bovino | C52: Novillito | D52: MAG (Liniers) | E52: https://www.mercadoagroganadero.com.ar/dll/hacienda1.dll/haciinfo000502 | F52: Precio promedio de la categoria
C53: Ternero | D53: ROSGAN | E53: https://www.rosgan.com.ar/indices | F53: Precio indice terneros Rosgan
B54: Leche | D54: SAGyP - SIGLeA | E54: https://www.magyp.gob.ar/sitio/areas/ss_lecheria/mercado_futuro/ | F54: Precio al productor Nacional
B55: Aves | C55: Pollo | D55: Catedra Avicola | E55: https://www.catedraavicola.com.ar/cotizaciones/ | F55: Precio promedio mayorista pollo parrillero eviserado. Capital Federal y CABA
C56: Huevos | D56: Catedra Avicola | E56: https://www.catedraavicola.com.ar/cotizaciones/ | F56: Precio promedio de la docena de huevos de color y blanco. Buenos Aires
B57: Porcino | D57: SAGyP | E57: https://www.magyp.gob.ar/sitio/areas/porcinos/informes/ | F57: Precio promedio Capon General. Informes de precios porcinos
B58: Ovinos | C58: Cordero | D58: SIPAN | E58: https://sipan.inta.gob.ar/economia/informes/?Y=MjAyNg== | F58: Precio de Cordero Pesado mayor a 12kg Patagonia Norte A (Rio Negro y Patagones)
C59: Lana | D59: SAGyP - PROLANA | E59: https://www.magyp.gob.ar/sitio/areas/prolana/calculadora/ | F59: Patagónicas 28 micrones. 55% de rinde al peine
B60: Miel | D60: INTA Manfredi | E60: https://repositorio.inta.gob.ar/handle/20.500.12123/225 | F60: Precio promedio ponderado region pampeana - Exportacion | G60: -
D61: PROAPI | E61: https://public.tableau.com/views/Miel-PreciosZonales-vs2/Panel_Evolucion?:language=es-ES&:display_count=n&:origin=viz_share_link&:showVizHome=no | F61: Precio promedio de referencia. Interno
B63: Area/Stock | D63: Fuente | E63: Link | F63: Tipo de dato
B64: Algodón | D64: SAGyP | E64: https://www.magyp.gob.ar/sitio/areas/estimaciones/ | F64: Superficie a implantar (ha) | G64: 24/25 | K64: 25-26
B65: Arroz | D65: SAGyP | E65: https://www.magyp.gob.ar/sitio/areas/estimaciones/ | F65: Superficie a implantar (ha) | G65: 24/25 | K65: 25-26
B66: Granos | C66: Cebada | D66: SAGyP | E66: https://www.magyp.gob.ar/sitio/areas/estimaciones/ | F66: Superficie a implantar (ha) | G66: 25/26 | S66: 26-27
C67: Girasol | D67: SAGyP | E67: https://www.magyp.gob.ar/sitio/areas/estimaciones/ | F67: Superficie a implantar (ha) | G67: 24/25 | J67: 25-26
C68: Maiz | D68: BCBA | E68: https://www.bolsadecereales.com/pas | F68: Superficie sembrada (ha) | G68: 24/25 | J68: 25/26 | U68: 26-27
C69: Soja | D69: SAGyP | E69: https://www.magyp.gob.ar/sitio/areas/estimaciones/ | F69: Superficie a implantar (ha) | G69: 24/25 | J69: 25-26
C70: Sorgo | D70: SAGyP | E70: https://www.magyp.gob.ar/sitio/areas/estimaciones/ | F70: Superficie a implantar (ha) | G70: 24/25 | J70: 25-26
C71: Trigo | D71: SAGyP | E71: https://www.magyp.gob.ar/sitio/areas/estimaciones/ | F71: Superficie a implantar (ha) | G71: 25/26 | S71: 26-27
B72: Mani | D72: CAM | E72: https://camaradelmani.org.ar/estadisticas/ | F72: Superficie sembrada (ha) camapaña actual | G72: 45689 | K72: 25-26
B73: Yerba Mate | D73: INYM | E73: https://inym.org.ar/descargar/publicaciones/estadisticas/superficie-cultivada-por-departamento.html | F73: Superficie CULTIVADA (ha) | G73: 2024 | L73: 2025
B74: Vitivinicultura | D74: INV - SAGyP | E74: https://www.argentina.gob.ar/inv/principales-datos-vitivinicolas | F74: Superficie (ha). Dato anual | G74: 2024 | O74: 2025
B75: Bovinos | D75: SAGyP - SENASA | E75: https://www.magyp.gob.ar/sitio/areas/bovinos/informacion_interes/informes/index.php | F75: Stock de cabezas al 31 de diciembre | G75: 2024 | O75: 46387
B76: Porcinos | D76: SAGyP - SENASA | E76: https://www.magyp.gob.ar/sitio/areas/porcinos/estadistica/ | F76: Stock de cabezas al 31 de marzo | G76: 45717 | R76: 2026
B77: Ovinos | D77: SAGyP - SENASA | E77: https://www.magyp.gob.ar/sitio/areas/d_ovinos/estadistica/existencias/index.php | F77: Stock de cabezas al 31 de marzo | G77: 45717 | Q77: 2026
B78: Leche | D78: SENASA | E78: https://qliksensebycores.senasa.gob.ar/hub/stream/aaec8d41-5201-43ab-809f-3063750dfafd | F78: Stock total de bovinos en tambo | G78: - | H78: 45809 | I78: 45839 | J78: 45870 | K78: 45901 | L78: 45931 | M78: 45962 | N78: 45992 | O78: 46023 | P78: 46054 | Q78: 46082 | R78: 46113 | S78: 46143 | T78: 46174 | U78: 46204
B79: Aves | D79: SAGyP - RENAVI | E79: https://www.magyp.gob.ar/sitio/areas/aves/renavi/ | F79: Existencias de Reproductoras pesadas Totales
B80: Miel | D80: RENAPA | F80: Dato colmenas del 2019 | G80: 43831 | I80: 2025
B81: Citricos Dulces | D81: Federcitrus | E81: https://www.federcitrus.org/estadisticas/ | F81: Superficie plantada (ha). Sumatoria Naranja, Mandarina y Pomelo | G81: 44927 | K81: 2024
B82: Forestal
B83: Hortalizas | C83: Cebolla | D83: FAO | E83: https://www.fao.org/faostat/es/#data/QCL | F83: Dato area cosechada - cebollas y chalotes, secos (excepto deshidratados) | G83: 2024 | N83: 2024
A84: https://www.argentina.gob.ar/agricultura/subsecretaria-agricultura/informes-sectoriales-de-hortalizas#:~:text=Nuestro%20pa%C3%ADs%20produce%20unas%207,distribuidas%20en%20todo%20el%20pa%C3%ADs. | C84: Tomate | D84: FAO | E84: https://www.fao.org/faostat/es/#data/QCL | F84: Dato area cosechada - tomates, frescos | G84: 2024 | N84: 2024
C85: Zanahoria | D85: FAO | E85: https://www.fao.org/faostat/es/#data/QCL | F85: Dato area cosechada - zanahorias y nabos | G85: 2024 | N85: 2024
C86: Zapallo | D86: FAO | E86: https://www.fao.org/faostat/es/#data/QCL | F86: Dato area cosechada - calabazas, zapayo, calabaza confitera | G86: 2024 | N86: 2024
B87: Mandioca | D87: FAO | E87: https://www.fao.org/faostat/es/#data/QCL | F87: Dato area cosechada - Yuca, freca | G87: 2024 | N87: 2024
B88: Papa | D88: FAO | E88: https://fenapp.org.ar/la-superficie-sembrada-de-papa-en-el-sudeste-bonaerense-aumento-un-97/ | F88: Dato area cosehcada - papas, patatas | G88: 2024 | N88: 2024
B89: Peras | D89: FAO | E89: https://www.fao.org/faostat/es/#data/QCL | F89: Dato area cosechada - peras | G89: 2024 | N89: 2024
B90: Manzanas | D90: FAO | E90: https://www.fao.org/faostat/es/#data/QCL | F90: Dato area cosechada - manzanas | G90: 2024 | N90: 2024
B91: Tabaco | D91: SAGYP | E91: https://www.magyp.gob.ar/sitio/areas/tabaco/produccion_mercados/interno/index.php | F91: produccion campaña | G91: 24-25
B93: Produccion | D93: Fuente | E93: Link | F93: Tipo de dato
B94: Algodón | D94: SAGyP | E94: https://www.magyp.gob.ar/sitio/areas/estimaciones/ | F94: Volumen de produccion campaña actual | G94: 24/25 | R94: 25/26
B95: Arroz | D95: SAGyP | E95: https://www.magyp.gob.ar/sitio/areas/estimaciones/ | F95: Volumen de produccion campaña actual | G95: 24/25 | R95: 25/26
B96: Granos | C96: Cebada | D96: Bolsa de Cereales Bs As | E96: https://www.bolsadecereales.com/ | F96: Volumen de produccion campaña actual | G96: 24/25 | K96: 25-26 | V96: 26-27
C97: Girasol | D97: Bolsa de Cereales Bs As | E97: https://www.bolsadecereales.com/ | F97: Volumen de produccion campaña actual | G97: 24/25 | K97: 25-26 | V97: 26-27
C98: Maíz | D98: Bolsa de Cereales Bs As | E98: https://www.bolsadecereales.com/ | F98: Volumen de produccion campaña actual | G98: 24/25 | K98: 25-26 | V98: 26-27
C99: Soja | D99: Bolsa de Cereales Bs As | E99: https://www.bolsadecereales.com/ | F99: Volumen de produccion campaña actual | G99: 24/25 | K99: 25-26 | V99: 26-27
C100: Sorgo | D100: Bolsa de Cereales Bs As | E100: https://www.bolsadecereales.com/ | F100: Volumen de produccion campaña actual | G100: 24/25 | K100: 25-26 | V100: 26-27
C101: Trigo | D101: Bolsa de Cereales Bs As | E101: https://www.bolsadecereales.com/ | F101: Volumen de produccion campaña actual | G101: 24/25 | K101: 25-26 | V101: 26-27
B102: Mani | D102: CAM | E102: https://camaradelmani.org.ar/2025/04/16/tabla-de-oferta-y-demanda-2025/ | F102: Volumen de produccion campaña actual | G102: 24/25 | K102: 25-26 | V102: 26-27
...

Sheet Comex
A1: Ene -Ago | B1: Expo | AG1: Impo | BM1: =A1 -> Ene -Ago | BN1: Expo | CG1: total | CH1: total s/ granos | CI1: Impo | DB1: total | DC1: total s/ granos | DE1: EXPORTACIONES GRAFICO | DX1: IMPORTACIONES GRAFICO
B2: Algodón | C2: Arroz | D2: Cebada | E2: Girasol | F2: Maíz | G2: Maní | H2: Soja | I2: Sorgo | J2: Trigo | K2: Papa | L2: Mandioca | M2: Cebolla | N2: Tomate | O2: Zanahoria | P2: Zapallo | Q2: Vitícola | R2: Manzana | S2: Pera | T2: Limón | U2: Mandarina | V2: Naranja | W2: Pomelo | X2: Forestal | Y2: Tabaco | Z2: Yerba Mate | AA2: Apícola | AB2: Aviar | AC2: Bovinos | AD2: Lechería | AE2: Ovinos | AF2: Porcinos | AG2: Algodón | AH2: Arroz | AI2: Cebada | AJ2: Girasol | AK2: Maíz | AL2: Maní | AM2: Soja | AN2: Sorgo | AO2: Trigo | AP2: Papa | AQ2: Mandioca | AR2: Cebolla | AS2: Tomate | AT2: Zanahoria | AU2: Zapallo | AV2: Vitícola | AW2: Manzana | AX2: Pera | AY2: Limón | AZ2: Mandarina | BA2: Naranja | BB2: Pomelo | BC2: Forestal | BD2: Tabaco | BE2: Yerba Mate | BF2: Apícola | BG2: Aviar | BH2: Bovinos | BI2: Lechería | BJ2: Ovinos | BK2: Porcinos | BN2: Algodón | BO2: Arroz | BP2: Granos | BQ2: Mani | BR2: Papa | BS2: Mandioca | BT2: Hortalizas | BU2: Vitivinicola | BV2: Peras y Manzanas | BW2: Citricos Dulces | BX2: Forestal | BY2: Tabaco | BZ2: Yerba Mate | CA2: Apícola | CB2: Aviar | CC2: Bovinos | CD2: Lechería | CE2: Ovinos | CF2: Porcinos | CI2: Algodón | CJ2: Arroz | CK2: Granos | CL2: Mani | CM2: Papa | CN2: Mandioca | CO2: Hortalizas | CP2: Vitivinicola | CQ2: Peras y Manzanas | CR2: Citricos Dulces | CS2: Forestal | CT2: Tabaco | CU2: Yerba Mate | CV2: Apícola | CW2: Aviar | CX2: Bovinos | CY2: Lechería | CZ2: Ovinos | DA2: Porcinos | DE2: Bovinos | DF2: Lechería | DG2: Aviar | DH2: Ovinos | DI2: Porcinos | DJ2: Vitivinicola | DK2: Yerba Mate | DL2: Algodón | DM2: Peras y Manzanas | DN2: Citricos Dulces | DO2: Forestal | DP2: Tabaco | DQ2: Apícola | DR2: Arroz | DS2: Mani | DT2: Papa | DU2: Hortalizas | DV2: Mandioca | DX2: Bovinos | DY2: Lechería | DZ2: Aviar | EA2: Ovinos | EB2: Porcinos | EC2: Vitivinicola | ED2: Yerba Mate | EE2: Algodón | EF2: Peras y Manzanas | EG2: Citricos Dulces | EH2: Forestal | EI2: Tabaco | EJ2: Apícola | EK2: Arroz | EL2: Mani | EM2: Papa | EN2: Hortalizas | EO2: Mandioca
A3: 2016 | B3: =SUM(datos!JF10:JF17) -> 54.409827 | C3: =SUM(datos!JG10:JG17) -> 149.46794 | D3: =SUM(datos!JH10:JH17) -> 640.51608 | E3: =SUM(datos!JI10:JI17) -> 626.62949 | F3: =SUM(datos!JJ10:JJ17) -> 3033.8296 | G3: =SUM(datos!JK10:JK17) -> 604.07055 | H3: =SUM(datos!JL10:JL17) -> 12368.025 | I3: =SUM(datos!JM10:JM17) -> 57.116446 | ... BK3: =SUM(datos!LO10:LO17) -> 44.470737 | BM3: 2016 | BN3: =B3 -> 54.409827 | BO3: =C3 -> 149.46794 | BP3: =SUM(D3:F3,H3:J3) -> 18209.237 | BQ3: =G3 -> 604.07055 | BR3: =K3 -> 145.68574 | BS3: =L3 -> 0 | BT3: =SUM(M3:P3) -> 28.489358 | BU3: =Q3 -> 648.49007 | BV3: =SUM(R3:S3) -> 341.38826 | BW3: =SUM(T3:W3) -> 513.85055 | BX3: =X3 -> 129.4643 | BY3: =Y3 -> 232.85714 | BZ3: =Z3 -> 42.311108 | CA3: =AA3 -> 123.20439 | CB3: =AB3 -> 179.52155 | CC3: =AC3 -> 1287.3146 | CD3: =AD3 -> 387.09514 | CE3: =AE3 -> 156.29588 | CF3: =AF3 -> 7.0322254 | CG3: =SUM(BN3:CF3) -> 23240.186 | CH3: =CG3-BP3 -> 5030.9486 | CI3: =AG3 -> 86.194496 | CJ3: =AH3 -> 4.0060256 | CK3: =SUM(AI3:AK3,AM3:AO3) -> 245.28067 | CL3: =AL3 -> 0.12216077 | CM3: =AP3 -> 17.887523 | CN3: =AQ3 -> 0.83185262 | CO3: =SUM(AR3:AU3) -> 27.856347 | CP3: =AV3 -> 2.7151343 | CQ3: =SUM(AW3:AX3) -> 4.4321264 | CR3: =SUM(AY3:BB3) -> 9.8060333 | CS3: =BC3 -> 154.22261 | CT3: =BD3 -> 34.735092 | CU3: =BE3 -> 0.50848095 | CV3: =BF3 -> 0.01478013 | CW3: =BG3 -> 28.210152 | CX3: =BH3 -> 29.801982 | CY3: =BI3 -> 9.2453238 | CZ3: =BJ3 -> 5.3927472 | DA3: =BK3 -> 44.470737 | DB3: =SUM(CI3:DA3) -> 705.73428 | DC3: =DB3-CK3 -> 460.45361 | DD3: 2016 | DE3: =CC3 -> 1287.3146 | DF3: =CD3 -> 387.09514 | DG3: =CB3 -> 179.52155 | DH3: =CE3 -> 156.29588 | DI3: =CF3 -> 7.0322254 | DJ3: =BU3 -> 648.49007 | DK3: =BZ3 -> 42.311108 | DL3: =BN3 -> 54.409827 | DM3: =BV3 -> 341.38826 | DN3: =BW3 -> 513.85055 | DO3: =BX3 -> 129.4643 | DP3: =BY3 -> 232.85714 | DQ3: =CA3 -> 123.20439 | DR3: =BO3 -> 149.46794 | DS3: =BQ3 -> 604.07055 | DT3: =BR3 -> 145.68574 | DU3: =BT3 -> 28.489358 | DV3: =BS3 -> 0 | DX3: =CX3 -> 29.801982 | DY3: =CY3 -> 9.2453238 | DZ3: =CW3 -> 28.210152 | EA3: =CZ3 -> 5.3927472 | EB3: =DA3 -> 44.470737 | EC3: =CP3 -> 2.7151343 | ED3: =CU3 -> 0.50848095 | EE3: =CI3 -> 86.194496 | EF3: =CQ3 -> 4.4321264 | EG3: =CR3 -> 9.8060333 | EH3: =CS3 -> 154.22261 | EI3: =CT3 -> 34.735092 | EJ3: =CV3 -> 0.01478013 | EK3: =CJ3 -> 4.0060256 | EL3: =CL3 -> 0.12216077 | EM3: =CM3 -> 17.887523 | EN3: =CO3 -> 27.856347 | EO3: =CN3 -> 0.83185262
A4: 2017 | B4: =SUM(datos!JF22:JF29) -> 49.565386 | C4: =SUM(datos!JG22:JG29) -> 126.87513 | D4: =SUM(datos!JH22:JH29) -> 523.9634 | E4: =SUM(datos!JI22:JI29) -> 571.33697 | F4: =SUM(datos!JJ22:JJ29) -> 2727.6092 | G4: =SUM(datos!JK22:JK29) -> 560.18411 | H4: =SUM(datos!JL22:JL29) -> 11308.755 | I4: =SUM(datos!JM22:JM29) -> 43.107363 | ... BK4: =SUM(datos!LO22:LO29) -> 80.561475 | BM4: 2017 | BN4: =B4 -> 49.565386 | BO4: =C4 -> 126.87513 | BP4: =SUM(D4:F4,H4:J4) -> 16925.388 | BQ4: =G4 -> 560.18411 | BR4: =K4 -> 125.01639 | BS4: =L4 -> 0.001664 | BT4: =SUM(M4:P4) -> 16.598591 | BU4: =Q4 -> 614.54182 | BV4: =SUM(R4:S4) -> 328.57696 | BW4: =SUM(T4:W4) -> 415.40884 | BX4: =X4 -> 158.43166 | BY4: =Y4 -> 214.27715 | BZ4: =Z4 -> 55.553768 | CA4: =AA4 -> 134.11465 | CB4: =AB4 -> 213.07472 | CC4: =AC4 -> 1475.5046 | CD4: =AD4 -> 357.27884 | CE4: =AE4 -> 144.58608 | CF4: =AF4 -> 12.538792 | CG4: =SUM(BN4:CF4) -> 21927.517 | CH4: =CG4-BP4 -> 5002.1291 | CI4: =AG4 -> 66.504423 | CJ4: =AH4 -> 3.7127877 | CK4: =SUM(AI4:AK4,AM4:AO4) -> 575.26323 | CL4: =AL4 -> 0.67187738 | CM4: =AP4 -> 23.607516 | CN4: =AQ4 -> 4.4833476 | CO4: =SUM(AR4:AU4) -> 32.063187 | CP4: =AV4 -> 50.990598 | CQ4: =SUM(AW4:AX4) -> 10.98331 | CR4: =SUM(AY4:BB4) -> 11.5585 | CS4: =BC4 -> 152.61877 | CT4: =BD4 -> 34.655634 | CU4: =BE4 -> 0.68021238 | CV4: =BF4 -> 0.22386681 | CW4: =BG4 -> 22.281796 | CX4: =BH4 -> 28.894064 | CY4: =BI4 -> 19.88767 | CZ4: =BJ4 -> 2.3918065 | DA4: =BK4 -> 80.561475 | DB4: =SUM(CI4:DA4) -> 1122.0341 | DC4: =DB4-CK4 -> 546.77084 | DD4: 2017 | DE4: =CC4 -> 1475.5046 | DF4: =CD4 -> 357.27884 | DG4: =CB4 -> 213.07472 | DH4: =CE4 -> 144.58608 | DI4: =CF4 -> 12.538792 | DJ4: =BU4 -> 614.54182 | DK4: =BZ4 -> 55.553768 | DL4: =BN4 -> 49.565386 | DM4: =BV4 -> 328.57696 | DN4: =BW4 -> 415.40884 | DO4: =BX4 -> 158.43166 | DP4: =BY4 -> 214.27715 | DQ4: =CA4 -> 134.11465 | DR4: =BO4 -> 126.87513 | DS4: =BQ4 -> 560.18411 | DT4: =BR4 -> 125.01639 | DU4: =BT4 -> 16.598591 | DV4: =BS4 -> 0.001664 | DX4: =CX4 -> 28.894064 | DY4: =CY4 -> 19.88767 | DZ4: =CW4 -> 22.281796 | EA4: =CZ4 -> 2.3918065 | EB4: =DA4 -> 80.561475 | EC4: =CP4 -> 50.990598 | ED4: =CU4 -> 0.68021238 | EE4: =CI4 -> 66.504423 | EF4: =CQ4 -> 10.98331 | EG4: =CR4 -> 11.5585 | EH4: =CS4 -> 152.61877 | EI4: =CT4 -> 34.655634 | EJ4: =CV4 -> 0.22386681 | EK4: =CJ4 -> 3.7127877 | EL4: =CL4 -> 0.67187738 | EM4: =CM4 -> 23.607516 | EN4: =CO4 -> 32.063187 | EO4: =CN4 -> 4.4833476
A5: 2018 | B5: =SUM(datos!JF34:JF41) -> 66.392231 | C5: =SUM(datos!JG34:JG41) -> 123.09376 | D5: =SUM(datos!JH34:JH41) -> 540.71463 | E5: =SUM(datos!JI34:JI41) -> 580.10943 | F5: =SUM(datos!JJ34:JJ41) -> 3130.3466 | G5: =SUM(datos!JK34:JK41) -> 463.90971 | H5: =SUM(datos!JL34:JL41) -> 9076.2721 | I5: =SUM(datos!JM34:JM41) -> 27.122047 | ... BK5: =SUM(datos!LO34:LO41) -> 76.963965 | BM5: 2018 | BN5: =B5 -> 66.392231 | BO5: =C5 -> 123.09376 | BP5: =SUM(D5:F5,H5:J5) -> 15169.646 | BQ5: =G5 -> 463.90971 | BR5: =K5 -> 112.84753 | BS5: =L5 -> 0 | BT5: =SUM(M5:P5) -> 31.018285 | BU5: =Q5 -> 638.19389 | BV5: =SUM(R5:S5) -> 361.95987 | BW5: =SUM(T5:W5) -> 433.10917 | BX5: =X5 -> 50.234011 | BY5: =Y5 -> 191.74422 | BZ5: =Z5 -> 69.072689 | CA5: =AA5 -> 125.53562 | CB5: =AB5 -> 203.3206 | CC5: =AC5 -> 1949.4436 | CD5: =AD5 -> 462.15821 | CE5: =AE5 -> 196.13031 | CF5: =AF5 -> 14.424982 | CG5: =SUM(BN5:CF5) -> 20662.235 | CH5: =CG5-BP5 -> 5492.5887 | CI5: =AG5 -> 68.738869 | CJ5: =AH5 -> 3.2527584 | CK5: =SUM(AI5:AK5,AM5:AO5) -> 1646.5089 | CL5: =AL5 -> 0.20511525 | CM5: =AP5 -> 34.349134 | CN5: =AQ5 -> 4.1272484 | CO5: =SUM(AR5:AU5) -> 25.513629 | CP5: =AV5 -> 7.0511017 | CQ5: =SUM(AW5:AX5) -> 6.5012361 | CR5: =SUM(AY5:BB5) -> 9.34071 | CS5: =BC5 -> 167.11321 | CT5: =BD5 -> 19.971598 | CU5: =BE5 -> 0.40205221 | CV5: =BF5 -> 0 | CW5: =BG5 -> 19.208996 | CX5: =BH5 -> 24.279341 | CY5: =BI5 -> 14.199746 | CZ5: =BJ5 -> 0.7725766 | DA5: =BK5 -> 76.963965 | DB5: =SUM(CI5:DA5) -> 2128.5002 | DC5: =DB5-CK5 -> 481.99129 | DD5: 2018 | DE5: =CC5 -> 1949.4436 | DF5: =CD5 -> 462.15821 | DG5: =CB5 -> 203.3206 | DH5: =CE5 -> 196.13031 | DI5: =CF5 -> 14.424982 | DJ5: =BU5 -> 638.19389 | DK5: =BZ5 -> 69.072689 | DL5: =BN5 -> 66.392231 | DM5: =BV5 -> 361.95987 | DN5: =BW5 -> 433.10917 | DO5: =BX5 -> 50.234011 | DP5: =BY5 -> 191.74422 | DQ5: =CA5 -> 125.53562 | DR5: =BO5 -> 123.09376 | DS5: =BQ5 -> 463.90971 | DT5: =BR5 -> 112.84753 | DU5: =BT5 -> 31.018285 | DV5: =BS5 -> 0 | DX5: =CX5 -> 24.279341 | DY5: =CY5 -> 14.199746 | DZ5: =CW5 -> 19.208996 | EA5: =CZ5 -> 0.7725766 | EB5: =DA5 -> 76.963965 | EC5: =CP5 -> 7.0511017 | ED5: =CU5 -> 0.40205221 | EE5: =CI5 -> 68.738869 | EF5: =CQ5 -> 6.5012361 | EG5: =CR5 -> 9.34071 | EH5: =CS5 -> 167.11321 | EI5: =CT5 -> 19.971598 | EJ5: =CV5 -> 0 | EK5: =CJ5 -> 3.2527584 | EL5: =CL5 -> 0.20511525 | EM5: =CM5 -> 34.349134 | EN5: =CO5 -> 25.513629 | EO5: =CN5 -> 4.1272484
A6: 2019 | B6: =SUM(datos!JF46:JF53) -> 77.070064 | C6: =SUM(datos!JG46:JG53) -> 109.70648 | D6: =SUM(datos!JH46:JH53) -> 740.64458 | E6: =SUM(datos!JI46:JI53) -> 735.96175 | F6: =SUM(datos!JJ46:JJ53) -> 4187.1008 | G6: =SUM(datos!JK46:JK53) -> 489.30623 | H6: =SUM(datos!JL46:JL53) -> 10207.492 | I6: =SUM(datos!JM46:JM53) -> 34.7978 | ... BK6: =SUM(datos!LO46:LO53) -> 67.506336 | BM6: 2019 | BN6: =B6 -> 77.070064 | BO6: =C6 -> 109.70648 | BP6: =SUM(D6:F6,H6:J6) -> 17848.046 | BQ6: =G6 -> 489.30623 | BR6: =K6 -> 147.41111 | BS6: =L6 -> 0 | BT6: =SUM(M6:P6) -> 39.338341 | BU6: =Q6 -> 631.23457 | BV6: =SUM(R6:S6) -> 288.84739 | BW6: =SUM(T6:W6) -> 319.7925 | BX6: =X6 -> 30.672148 | BY6: =Y6 -> 152.46961 | BZ6: =Z6 -> 58.250138 | CA6: =AA6 -> 104.95143 | CB6: =AB6 -> 272.49848 | CC6: =AC6 -> 2345.5506 | CD6: =AD6 -> 394.36482 | CE6: =AE6 -> 175.64853 | CF6: =AF6 -> 13.156129 | CG6: =SUM(BN6:CF6) -> 23498.315 | CH6: =CG6-BP6 -> 5650.2686 | CI6: =AG6 -> 51.377997 | CJ6: =AH6 -> 2.5394806 | CK6: =SUM(AI6:AK6,AM6:AO6) -> 1521.8325 | CL6: =AL6 -> 0.1844853 | CM6: =AP6 -> 14.437343 | CN6: =AQ6 -> 1.6483422 | CO6: =SUM(AR6:AU6) -> 14.380355 | CP6: =AV6 -> 5.6318893 | CQ6: =SUM(AW6:AX6) -> 3.4126421 | CR6: =SUM(AY6:BB6) -> 4.8034722 | CS6: =BC6 -> 154.6279 | CT6: =BD6 -> 34.935696 | CU6: =BE6 -> 0.74095648 | CV6: =BF6 -> 0.33565781 | CW6: =BG6 -> 18.455583 | CX6: =BH6 -> 46.287423 | CY6: =BI6 -> 18.368854 | CZ6: =BJ6 -> 0.88820652 | DA6: =BK6 -> 67.506336 | DB6: =SUM(CI6:DA6) -> 1962.3951 | DC6: =DB6-CK6 -> 440.56262 | DD6: 2019 | DE6: =CC6 -> 2345.5506 | DF6: =CD6 -> 394.36482 | DG6: =CB6 -> 272.49848 | DH6: =CE6 -> 175.64853 | DI6: =CF6 -> 13.156129 | DJ6: =BU6 -> 631.23457 | DK6: =BZ6 -> 58.250138 | DL6: =BN6 -> 77.070064 | DM6: =BV6 -> 288.84739 | DN6: =BW6 -> 319.7925 | DO6: =BX6 -> 30.672148 | DP6: =BY6 -> 152.46961 | DQ6: =CA6 -> 104.95143 | DR6: =BO6 -> 109.70648 | DS6: =BQ6 -> 489.30623 | DT6: =BR6 -> 147.41111 | DU6: =BT6 -> 39.338341 | DV6: =BS6 -> 0 | DX6: =CX6 -> 46.287423 | DY6: =CY6 -> 18.368854 | DZ6: =CW6 -> 18.455583 | EA6: =CZ6 -> 0.88820652 | EB6: =DA6 -> 67.506336 | EC6: =CP6 -> 5.6318893 | ED6: =CU6 -> 0.74095648 | EE6: =CI6 -> 51.377997 | EF6: =CQ6 -> 3.4126421 | EG6: =CR6 -> 4.8034722 | EH6: =CS6 -> 154.6279 | EI6: =CT6 -> 34.935696 | EJ6: =CV6 -> 0.33565781 | EK6: =CJ6 -> 2.5394806 | EL6: =CL6 -> 0.1844853 | EM6: =CM6 -> 14.437343 | EN6: =CO6 -> 14.380355 | EO6: =CN6 -> 1.6483422
A7: 2020 | B7: =SUM(datos!JF58:JF65) -> 78.485275 | C7: =SUM(datos!JG58:JG65) -> 132.04623 | D7: =SUM(datos!JH58:JH65) -> 713.75236 | E7: =SUM(datos!JI58:JI65) -> 940.32054 | F7: =SUM(datos!JJ58:JJ65) -> 5037.628 | G7: =SUM(datos!JK58:JK65) -> 776.62292 | H7: =SUM(datos!JL58:JL65) -> 14095.232 | I7: =SUM(datos!JM58:JM65) -> 182.12939 | ... BK7: =SUM(datos!LO58:LO65) -> 39.814807 | BM7: 2020 | BN7: =B7 -> 78.485275 | BO7: =C7 -> 132.04623 | BP7: =SUM(D7:F7,H7:J7) -> 23141.08 | BQ7: =G7 -> 776.62292 | BR7: =K7 -> 129.07161 | BS7: =L7 -> 0.0025 | BT7: =SUM(M7:P7) -> 44.521935 | BU7: =Q7 -> 630.37704 | BV7: =SUM(R7:S7) -> 325.7942 | BW7: =SUM(T7:W7) -> 364.08946 | BX7: =X7 -> 130.45437 | BY7: =Y7 -> 199.67913 | BZ7: =Z7 -> 73.211228 | CA7: =AA7 -> 145.55567 | CB7: =AB7 -> 326.81322 | CC7: =AC7 -> 2365.1168 | CD7: =AD7 -> 783.60926 | CE7: =AE7 -> 137.43048 | CF7: =AF7 -> 52.660321 | CG7: =SUM(BN7:CF7) -> 29836.621 | CH7: =CG7-BP7 -> 6695.5416 | CI7: =AG7 -> 32.559056 | CJ7: =AH7 -> 3.2971293 | CK7: =SUM(AI7:AK7,AM7:AO7) -> 1460.4608 | CL7: =AL7 -> 0.28117517 | CM7: =AP7 -> 13.71036 | CN7: =AQ7 -> 1.6076478 | CO7: =SUM(AR7:AU7) -> 28.404996 | CP7: =AV7 -> 5.1813193 | CQ7: =SUM(AW7:AX7) -> 2.5358095 | CR7: =SUM(AY7:BB7) -> 2.028996 | CS7: =BC7 -> 124.15329 | CT7: =BD7 -> 35.706773 | CU7: =BE7 -> 26.540224 | CV7: =BF7 -> 0.00861474 | CW7: =BG7 -> 18.628267 | CX7: =BH7 -> 41.053205 | CY7: =BI7 -> 7.49556 | CZ7: =BJ7 -> 1.7585355 | DA7: =BK7 -> 39.814807 | DB7: =SUM(CI7:DA7) -> 1845.2266 | DC7: =DB7-CK7 -> 384.76576 | DD7: 2020 | DE7: =CC7 -> 2365.1168 | DF7: =CD7 -> 783.60926 | DG7: =CB7 -> 326.81322 | DH7: =CE7 -> 137.43048 | DI7: =CF7 -> 52.660321 | DJ7: =BU7 -> 630.37704 | DK7: =BZ7 -> 73.211228 | DL7: =BN7 -> 78.485275 | DM7: =BV7 -> 325.7942 | DN7: =BW7 -> 364.08946 | DO7: =BX7 -> 130.45437 | DP7: =BY7 -> 199.67913 | DQ7: =CA7 -> 145.55567 | DR7: =BO7 -> 132.04623 | DS7: =BQ7 -> 776.62292 | DT7: =BR7 -> 129.07161 | DU7: =BT7 -> 44.521935 | DV7: =BS7 -> 0.0025 | DX7: =CX7 -> 41.053205 | DY7: =CY7 -> 7.49556 | DZ7: =CW7 -> 18.628267 | EA7: =CZ7 -> 1.7585355 | EB7: =DA7 -> 39.814807 | EC7: =CP7 -> 5.1813193 | ED7: =CU7 -> 26.540224 | EE7: =CI7 -> 32.559056 | EF7: =CQ7 -> 2.5358095 | EG7: =CR7 -> 2.028996 | EH7: =CS7 -> 124.15329 | EI7: =CT7 -> 35.706773 | EJ7: =CV7 -> 0.00861474 | EK7: =CJ7 -> 3.2971293 | EL7: =CL7 -> 0.28117517 | EM7: =CM7 -> 13.71036 | EN7: =CO7 -> 28.404996 | EO7: =CN7 -> 1.6076478
A8: 2021 | B8: =SUM(datos!JF70:JF77) -> 111.61179 | C8: =SUM(datos!JG70:JG77) -> 186.74919 | D8: =SUM(datos!JH70:JH77) -> 893.53495 | E8: =SUM(datos!JI70:JI77) -> 2236.1217 | F8: =SUM(datos!JJ70:JJ77) -> 6898.0969 | G8: =SUM(datos!JK70:JK77) -> 783.51957 | H8: =SUM(datos!JL70:JL77) -> 23783.826 | I8: =SUM(datos!JM70:JM77) -> 353.81834 | ... BK8: =SUM(datos!LO70:LO77) -> 67.972382 | BM8: 2021 | BN8: =B8 -> 111.61179 | BO8: =C8 -> 186.74919 | BP8: =SUM(D8:F8,H8:J8) -> 37026.775 | BQ8: =G8 -> 783.51957 | BR8: =K8 -> 184.49823 | BS8: =L8 -> 0 | BT8: =SUM(M8:P8) -> 37.52872 | BU8: =Q8 -> 655.50522 | BV8: =SUM(R8:S8) -> 316.41513 | BW8: =SUM(T8:W8) -> 311.97407 | BX8: =X8 -> 247.29755 | BY8: =Y8 -> 175.73344 | BZ8: =Z8 -> 75.825863 | CA8: =AA8 -> 185.25047 | CB8: =AB8 -> 295.41043 | CC8: =AC8 -> 2487.5807 | CD8: =AD8 -> 950.31028 | CE8: =AE8 -> 197.83466 | CF8: =AF8 -> 57.222602 | CG8: =SUM(BN8:CF8) -> 44287.043 | CH8: =CG8-BP8 -> 7260.2679 | CI8: =AG8 -> 54.607067 | CJ8: =AH8 -> 1.2123001 | CK8: =SUM(AI8:AK8,AM8:AO8) -> 2102.7844 | CL8: =AL8 -> 0.36556502 | CM8: =AP8 -> 7.1906577 | CN8: =AQ8 -> 2.275207 | CO8: =SUM(AR8:AU8) -> 15.809762 | CP8: =AV8 -> 10.011797 | CQ8: =SUM(AW8:AX8) -> 5.6128368 | CR8: =SUM(AY8:BB8) -> 12.824672 | CS8: =BC8 -> 146.769 | CT8: =BD8 -> 44.98699 | CU8: =BE8 -> 29.901723 | CV8: =BF8 -> 0.02699808 | CW8: =BG8 -> 20.862892 | CX8: =BH8 -> 50.01804 | CY8: =BI8 -> 11.386333 | CZ8: =BJ8 -> 1.9568038 | DA8: =BK8 -> 67.972382 | DB8: =SUM(CI8:DA8) -> 2586.5754 | DC8: =DB8-CK8 -> 483.79102 | DD8: 2021 | DE8: =CC8 -> 2487.5807 | DF8: =CD8 -> 950.31028 | DG8: =CB8 -> 295.41043 | DH8: =CE8 -> 197.83466 | DI8: =CF8 -> 57.222602 | DJ8: =BU8 -> 655.50522 | DK8: =BZ8 -> 75.825863 | DL8: =BN8 -> 111.61179 | DM8: =BV8 -> 316.41513 | DN8: =BW8 -> 311.97407 | DO8: =BX8 -> 247.29755 | DP8: =BY8 -> 175.73344 | DQ8: =CA8 -> 185.25047 | DR8: =BO8 -> 186.74919 | DS8: =BQ8 -> 783.51957 | DT8: =BR8 -> 184.49823 | DU8: =BT8 -> 37.52872 | DV8: =BS8 -> 0 | DX8: =CX8 -> 50.01804 | DY8: =CY8 -> 11.386333 | DZ8: =CW8 -> 20.862892 | EA8: =CZ8 -> 1.9568038 | EB8: =DA8 -> 67.972382 | EC8: =CP8 -> 10.011797 | ED8: =CU8 -> 29.901723 | EE8: =CI8 -> 54.607067 | EF8: =CQ8 -> 5.6128368 | EG8: =CR8 -> 12.824672 | EH8: =CS8 -> 146.769 | EI8: =CT8 -> 44.98699 | EJ8: =CV8 -> 0.02699808 | EK8: =CJ8 -> 1.2123001 | EL8: =CL8 -> 0.36556502 | EM8: =CM8 -> 7.1906577 | EN8: =CO8 -> 15.809762 | EO8: =CN8 -> 2.275207
A9: 2022 | B9: =SUM(datos!JF82:JF89) -> 168.89631 | C9: =SUM(datos!JG82:JG89) -> 172.08141 | D9: =SUM(datos!JH82:JH89) -> 1663.7725 | E9: =SUM(datos!JI82:JI89) -> 2565.9898 | F9: =SUM(datos!JJ82:JJ89) -> 8034.3728 | G9: =SUM(datos!JK82:JK89) -> 799.96 | H9: =SUM(datos!JL82:JL89) -> 22352.225 | I9: =SUM(datos!JM82:JM89) -> 490.58741 | ... BK9: =SUM(datos!LO82:LO89) -> 82.235693 | BM9: 2022 | BN9: =B9 -> 168.89631 | BO9: =C9 -> 172.08141 | BP9: =SUM(D9:F9,H9:J9) -> 41310.408 | BQ9: =G9 -> 799.96 | BR9: =K9 -> 204.29614 | BS9: =L9 -> 0 | BT9: =SUM(M9:P9) -> 41.92377 | BU9: =Q9 -> 703.96595 | BV9: =SUM(R9:S9) -> 247.16688 | BW9: =SUM(T9:W9) -> 267.88394 | BX9: =X9 -> 261.30502 | BY9: =Y9 -> 247.4236 | BZ9: =Z9 -> 66.943449 | CA9: =AA9 -> 211.22974 | CB9: =AB9 -> 383.06839 | CC9: =AC9 -> 3324.2569 | CD9: =AD9 -> 1244.8464 | CE9: =AE9 -> 191.35108 | CF9: =AF9 -> 10.239835 | CG9: =SUM(BN9:CF9) -> 49857.247 | CH9: =CG9-BP9 -> 8546.8388 | CI9: =AG9 -> 76.141605 | CJ9: =AH9 -> 0.51128799 | CK9: =SUM(AI9:AK9,AM9:AO9) -> 1969.2882 | CL9: =AL9 -> 0.61651101 | CM9: =AP9 -> 5.2106525 | CN9: =AQ9 -> 6.3776566 | CO9: =SUM(AR9:AU9) -> 17.916753 | CP9: =AV9 -> 11.112273 | CQ9: =SUM(AW9:AX9) -> 4.832072 | CR9: =SUM(AY9:BB9) -> 4.5914456 | CS9: =BC9 -> 177.00081 | CT9: =BD9 -> 34.229479 | CU9: =BE9 -> 26.88767 | CV9: =BF9 -> 0.08135102 | CW9: =BG9 -> 37.657641 | CX9: =BH9 -> 64.912821 | CY9: =BI9 -> 25.918449 | CZ9: =BJ9 -> 1.4838373 | DA9: =BK9 -> 82.235693 | DB9: =SUM(CI9:DA9) -> 2547.0062 | DC9: =DB9-CK9 -> 577.718 | DD9: 2022 | DE9: =CC9 -> 3324.2569 | DF9: =CD9 -> 1244.8464 | DG9: =CB9 -> 383.06839 | DH9: =CE9 -> 191.35108 | DI9: =CF9 -> 10.239835 | DJ9: =BU9 -> 703.96595 | DK9: =BZ9 -> 66.943449 | DL9: =BN9 -> 168.89631 | DM9: =BV9 -> 247.16688 | DN9: =BW9 -> 267.88394 | DO9: =BX9 -> 261.30502 | DP9: =BY9 -> 247.4236 | DQ9: =CA9 -> 211.22974 | DR9: =BO9 -> 172.08141 | DS9: =BQ9 -> 799.96 | DT9: =BR9 -> 204.29614 | DU9: =BT9 -> 41.92377 | DV9: =BS9 -> 0 | DX9: =CX9 -> 64.912821 | DY9: =CY9 -> 25.918449 | DZ9: =CW9 -> 37.657641 | EA9: =CZ9 -> 1.4838373 | EB9: =DA9 -> 82.235693 | EC9: =CP9 -> 11.112273 | ED9: =CU9 -> 26.88767 | EE9: =CI9 -> 76.141605 | EF9: =CQ9 -> 4.832072 | EG9: =CR9 -> 4.5914456 | EH9: =CS9 -> 177.00081 | EI9: =CT9 -> 34.229479 | EJ9: =CV9 -> 0.08135102 | EK9: =CJ9 -> 0.51128799 | EL9: =CL9 -> 0.61651101 | EM9: =CM9 -> 5.2106525 | EN9: =CO9 -> 17.916753 | EO9: =CN9 -> 6.3776566
A10: 2023 | B10: =SUM(datos!JF94:JF101) -> 30.558404 | C10: =SUM(datos!JG94:JG101) -> 190.79966 | D10: =SUM(datos!JH94:JH101) -> 1234.4019 | E10: =SUM(datos!JI94:JI101) -> 1386.1841 | F10: =SUM(datos!JJ94:JJ101) -> 5597.6435 | G10: =SUM(datos!JK94:JK101) -> 874.25125 | H10: =SUM(datos!JL94:JL101) -> 16037.112 | I10: =SUM(datos!JM94:JM101) -> 210.19931 | ... BK10: =SUM(datos!LO94:LO101) -> 42.658364 | BM10: 2023 | BN10: =B10 -> 30.558404 | BO10: =C10 -> 190.79966 | BP10: =SUM(D10:F10,H10:J10) -> 25410.021 | BQ10: =G10 -> 874.25125 | BR10: =K10 -> 218.73925 | BS10: =L10 -> 0 | BT10: =SUM(M10:P10) -> 46.856545 | BU10: =Q10 -> 559.61141 | BV10: =SUM(R10:S10) -> 287.54382 | BW10: =SUM(T10:W10) -> 235.95864 | BX10: =X10 -> 199.43735 | BY10: =Y10 -> 361.64912 | BZ10: =Z10 -> 70.790468 | CA10: =AA10 -> 147.42474 | CB10: =AB10 -> 231.61567 | CC10: =AC10 -> 2707.7336 | CD10: =AD10 -> 1009.2699 | CE10: =AE10 -> 145.69417 | CF10: =AF10 -> 13.396281 | CG10: =SUM(BN10:CF10) -> 32741.352 | CH10: =CG10-BP10 -> 7331.3303 | CI10: =AG10 -> 66.517924 | CJ10: =AH10 -> 0.33939125 | CK10: =SUM(AI10:AK10,AM10:AO10) -> 4288.0667 | CL10: =AL10 -> 0.46198871 | CM10: =AP10 -> 10.417919 | CN10: =AQ10 -> 8.0199833 | CO10: =SUM(AR10:AU10) -> 11.989456 | CP10: =AV10 -> 10.452242 | CQ10: =SUM(AW10:AX10) -> 5.9066646 | CR10: =SUM(AY10:BB10) -> 4.9948899 | CS10: =BC10 -> 200.04574 | CT10: =BD10 -> 49.274931 | CU10: =BE10 -> 7.3993995 | CV10: =BF10 -> 0.007038 | CW10: =BG10 -> 30.143111 | CX10: =BH10 -> 35.42977 | CY10: =BI10 -> 18.707808 | CZ10: =BJ10 -> 2.4594297 | DA10: =BK10 -> 42.658364 | DB10: =SUM(CI10:DA10) -> 4793.2928 | DC10: =DB10-CK10 -> 505.22605 | DD10: 2023 | DE10: =CC10 -> 2707.7336 | DF10: =CD10 -> 1009.2699 | DG10: =CB10 -> 231.61567 | DH10: =CE10 -> 145.69417 | DI10: =CF10 -> 13.396281 | DJ10: =BU10 -> 559.61141 | DK10: =BZ10 -> 70.790468 | DL10: =BN10 -> 30.558404 | DM10: =BV10 -> 287.54382 | DN10: =BW10 -> 235.95864 | DO10: =BX10 -> 199.43735 | DP10: =BY10 -> 361.64912 | DQ10: =CA10 -> 147.42474 | DR10: =BO10 -> 190.79966 | DS10: =BQ10 -> 874.25125 | DT10: =BR10 -> 218.73925 | DU10: =BT10 -> 46.856545 | DV10: =BS10 -> 0 | DX10: =CX10 -> 35.42977 | DY10: =CY10 -> 18.707808 | DZ10: =CW10 -> 30.143111 | EA10: =CZ10 -> 2.4594297 | EB10: =DA10 -> 42.658364 | EC10: =CP10 -> 10.452242 | ED10: =CU10 -> 7.3993995 | EE10: =CI10 -> 66.517924 | EF10: =CQ10 -> 5.9066646 | EG10: =CR10 -> 4.9948899 | EH10: =CS10 -> 200.04574 | EI10: =CT10 -> 49.274931 | EJ10: =CV10 -> 0.007038 | EK10: =CJ10 -> 0.33939125 | EL10: =CL10 -> 0.46198871 | EM10: =CM10 -> 10.417919 | EN10: =CO10 -> 11.989456 | EO10: =CN10 -> 8.0199833
A11: 2024 | B11: =SUM(datos!JF106:JF113) -> 132.25708 | C11: =SUM(datos!JG106:JG113) -> 204.61331 | D11: =SUM(datos!JH106:JH113) -> 1148.7857 | E11: =SUM(datos!JI106:JI113) -> 1530.8477 | F11: =SUM(datos!JJ106:JJ113) -> 5862.4109 | G11: =SUM(datos!JK106:JK113) -> 782.83545 | H11: =SUM(datos!JL106:JL113) -> 20031.984 | I11: =SUM(datos!JM106:JM113) -> 198.3859 | ... BK11: =SUM(datos!LO106:LO113) -> 26.138777 | BM11: 2024 | BN11: =B11 -> 132.25708 | BO11: =C11 -> 204.61331 | BP11: =SUM(D11:F11,H11:J11) -> 31324.669 | BQ11: =G11 -> 782.83545 | BR11: =K11 -> 245.60389 | BS11: =L11 -> 0 | BT11: =SUM(M11:P11) -> 59.575991 | BU11: =Q11 -> 626.51545 | BV11: =SUM(R11:S11) -> 313.84715 | BW11: =SUM(T11:W11) -> 239.31977 | BX11: =X11 -> 173.77075 | BY11: =Y11 -> 316.79907 | BZ11: =Z11 -> 75.501361 | CA11: =AA11 -> 139.5084 | CB11: =AB11 -> 233.39715 | CC11: =AC11 -> 2633.1533 | CD11: =AD11 -> 986.76099 | CE11: =AE11 -> 142.75738 | CF11: =AF11 -> 17.962228 | CG11: =SUM(BN11:CF11) -> 38648.848 | CH11: =CG11-BP11 -> 7324.1787 | CI11: =AG11 -> 37.5473 | CJ11: =AH11 -> 2.78077 | CK11: =SUM(AI11:AK11,AM11:AO11) -> 2270.3485 | CL11: =AL11 -> 2.0315312 | CM11: =AP11 -> 11.457533 | CN11: =AQ11 -> 0.92337464 | CO11: =SUM(AR11:AU11) -> 18.734589 | CP11: =AV11 -> 9.0850365 | CQ11: =SUM(AW11:AX11) -> 2.3328176 | CR11: =SUM(AY11:BB11) -> 4.0257754 | CS11: =BC11 -> 110.27094 | CT11: =BD11 -> 33.9591 | CU11: =BE11 -> 14.890542 | CV11: =BF11 -> 0.0525393 | CW11: =BG11 -> 22.650185 | CX11: =BH11 -> 21.836344 | CY11: =BI11 -> 12.885164 | CZ11: =BJ11 -> 2.2231297 | DA11: =BK11 -> 26.138777 | DB11: =SUM(CI11:DA11) -> 2604.174 | DC11: =DB11-CK11 -> 333.82545 | DD11: 2024 | DE11: =CC11 -> 2633.1533 | DF11: =CD11 -> 986.76099 | DG11: =CB11 -> 233.39715 | DH11: =CE11 -> 142.75738 | DI11: =CF11 -> 17.962228 | DJ11: =BU11 -> 626.51545 | DK11: =BZ11 -> 75.501361 | DL11: =BN11 -> 132.25708 | DM11: =BV11 -> 313.84715 | DN11: =BW11 -> 239.31977 | DO11: =BX11 -> 173.77075 | DP11: =BY11 -> 316.79907 | DQ11: =CA11 -> 139.5084 | DR11: =BO11 -> 204.61331 | DS11: =BQ11 -> 782.83545 | DT11: =BR11 -> 245.60389 | DU11: =BT11 -> 59.575991 | DV11: =BS11 -> 0 | DX11: =CX11 -> 21.836344 | DY11: =CY11 -> 12.885164 | DZ11: =CW11 -> 22.650185 | EA11: =CZ11 -> 2.2231297 | EB11: =DA11 -> 26.138777 | EC11: =CP11 -> 9.0850365 | ED11: =CU11 -> 14.890542 | EE11: =CI11 -> 37.5473 | EF11: =CQ11 -> 2.3328176 | EG11: =CR11 -> 4.0257754 | EH11: =CS11 -> 110.27094 | EI11: =CT11 -> 33.9591 | EJ11: =CV11 -> 0.0525393 | EK11: =CJ11 -> 2.78077 | EL11: =CL11 -> 2.0315312 | EM11: =CM11 -> 11.457533 | EN11: =CO11 -> 18.734589 | EO11: =CN11 -> 0.92337464
A12: 2025 | B12: =SUM(datos!JF118:JF125) -> 67.837281 | C12: =SUM(datos!JG118:JG125) -> 325.49616 | D12: =SUM(datos!JH118:JH125) -> 1051.9228 | E12: =SUM(datos!JI118:JI125) -> 1942.0605 | F12: =SUM(datos!JJ118:JJ125) -> 6019.2394 | G12: =SUM(datos!JK118:JK125) -> 864.23814 | H12: =SUM(datos!JL118:JL125) -> 17524.546 | I12: =SUM(datos!JM118:JM125) -> 305.37149 | ... BK12: =SUM(datos!LO118:LO125) -> 117.52479 | BM12: 2025 | BN12: =B12 -> 67.837281 | BO12: =C12 -> 325.49616 | BP12: =SUM(D12:F12,H12:J12) -> 29720.179 | BQ12: =G12 -> 864.23814 | BR12: =K12 -> 249.51668 | BS12: =L12 -> 0 | BT12: =SUM(M12:P12) -> 37.565798 | BU12: =Q12 -> 610.25239 | BV12: =SUM(R12:S12) -> 337.41537 | BW12: =SUM(T12:W12) -> 334.4399 | BX12: =X12 -> 104.92459 | BY12: =Y12 -> 364.61011 | BZ12: =Z12 -> 74.724022 | CA12: =AA12 -> 160.61636 | CB12: =AB12 -> 57.796366 | CC12: =AC12 -> 3062.1674 | CD12: =AD12 -> 1111.746 | CE12: =AE12 -> 166.30928 | CF12: =AF12 -> 17.024898 | CG12: =SUM(BN12:CF12) -> 37666.86 | CH12: =CG12-BP12 -> 7946.6808 | CI12: =AG12 -> 76.923617 | CJ12: =AH12 -> 2.8490507 | CK12: =SUM(AI12:AK12,AM12:AO12) -> 1892.5688 | CL12: =AL12 -> 1.5462054 | CM12: =AP12 -> 7.0975334 | CN12: =AQ12 -> 2.1868104 | CO12: =SUM(AR12:AU12) -> 9.5226502 | CP12: =AV12 -> 24.642074 | CQ12: =SUM(AW12:AX12) -> 4.4398865 | CR12: =SUM(AY12:BB12) -> 17.550539 | CS12: =BC12 -> 120.56186 | CT12: =BD12 -> 34.164904 | CU12: =BE12 -> 17.123049 | CV12: =BF12 -> 0.04522687 | CW12: =BG12 -> 26.151564 | CX12: =BH12 -> 67.500707 | CY12: =BI12 -> 20.243999 | CZ12: =BJ12 -> 1.2200566 | DA12: =BK12 -> 117.52479 | DB12: =SUM(CI12:DA12) -> 2443.8633 | DC12: =DB12-CK12 -> 551.29452 | DD12: 2025 | DE12: =CC12 -> 3062.1674 | DF12: =CD12 -> 1111.746 | DG12: =CB12 -> 57.796366 | DH12: =CE12 -> 166.30928 | DI12: =CF12 -> 17.024898 | DJ12: =BU12 -> 610.25239 | DK12: =BZ12 -> 74.724022 | DL12: =BN12 -> 67.837281 | DM12: =BV12 -> 337.41537 | DN12: =BW12 -> 334.4399 | DO12: =BX12 -> 104.92459 | DP12: =BY12 -> 364.61011 | DQ12: =CA12 -> 160.61636 | DR12: =BO12 -> 325.49616 | DS12: =BQ12 -> 864.23814 | DT12: =BR12 -> 249.51668 | DU12: =BT12 -> 37.565798 | DV12: =BS12 -> 0 | DX12: =CX12 -> 67.500707 | DY12: =CY12 -> 20.243999 | DZ12: =CW12 -> 26.151564 | EA12: =CZ12 -> 1.2200566 | EB12: =DA12 -> 117.52479 | EC12: =CP12 -> 24.642074 | ED12: =CU12 -> 17.123049 | EE12: =CI12 -> 76.923617 | EF12: =CQ12 -> 4.4398865 | EG12: =CR12 -> 17.550539 | EH12: =CS12 -> 120.56186 | EI12: =CT12 -> 34.164904 | EJ12: =CV12 -> 0.04522687 | EK12: =CJ12 -> 2.8490507 | EL12: =CL12 -> 1.5462054 | EM12: =CM12 -> 7.0975334 | EN12: =CO12 -> 9.5226502 | EO12: =CN12 -> 2.1868104
A13: 2026 | B13: =SUM(datos!JF130:JF137) -> 120.8521 | C13: =SUM(datos!JG130:JG137) -> 293.9775 | D13: =SUM(datos!JH130:JH137) -> 1506.6423 | E13: =SUM(datos!JI130:JI137) -> 3878.3831 | F13: =SUM(datos!JJ130:JJ137) -> 6943.3568 | G13: =SUM(datos!JK130:JK137) -> 867.33654 | H13: =SUM(datos!JL130:JL137) -> 17983.647 | I13: =SUM(datos!JM130:JM137) -> 251.89073 | ... BK13: =SUM(datos!LO130:LO137) -> 126.8555 | BM13: 2026 | BN13: =B13 -> 120.8521 | BO13: =C13 -> 293.9775 | BP13: =SUM(D13:F13,H13:J13) -> 34060.531 | BQ13: =G13 -> 867.33654 | BR13: =K13 -> 259.05938 | BS13: =L13 -> 0 | BT13: =SUM(M13:P13) -> 48.080469 | BU13: =Q13 -> 546.33289 | BV13: =SUM(R13:S13) -> 327.94638 | BW13: =SUM(T13:W13) -> 434.84178 | BX13: =X13 -> 134.14277 | BY13: =Y13 -> 402.16041 | BZ13: =Z13 -> 78.965883 | CA13: =AA13 -> 244.39321 | CB13: =AB13 -> 67.080908 | CC13: =AC13 -> 4123.6159 | CD13: =AD13 -> 1202.1987 | CE13: =AE13 -> 271.1013 | CF13: =AF13 -> 26.464585 | CG13: =SUM(BN13:CF13) -> 43509.082 | CH13: =CG13-BP13 -> 9448.5507 | CI13: =AG13 -> 46.811962 | CJ13: =AH13 -> 1.2966958 | CK13: =SUM(AI13:AK13,AM13:AO13) -> 2779.0437 | CL13: =AL13 -> 0.5665194 | CM13: =AP13 -> 17.760967 | CN13: =AQ13 -> 7.1763511 | CO13: =SUM(AR13:AU13) -> 14.367727 | CP13: =AV13 -> 25.265352 | CQ13: =SUM(AW13:AX13) -> 6.1102159 | CR13: =SUM(AY13:BB13) -> 6.7373456 | CS13: =BC13 -> 128.3066 | CT13: =BD13 -> 35.879582 | CU13: =BE13 -> 15.53136 | CV13: =BF13 -> 0.0062559 | CW13: =BG13 -> 29.704679 | CX13: =BH13 -> 123.26888 | CY13: =BI13 -> 21.562201 | CZ13: =BJ13 -> 1.5229212 | DA13: =BK13 -> 126.8555 | DB13: =SUM(CI13:DA13) -> 3387.7748 | DC13: =DB13-CK13 -> 608.73112 | DD13: 2026 | DE13: =CC13 -> 4123.6159 | DF13: =CD13 -> 1202.1987 | DG13: =CB13 -> 67.080908 | DH13: =CE13 -> 271.1013 | DI13: =CF13 -> 26.464585 | DJ13: =BU13 -> 546.33289 | DK13: =BZ13 -> 78.965883 | DL13: =BN13 -> 120.8521 | DM13: =BV13 -> 327.94638 | DN13: =BW13 -> 434.84178 | DO13: =BX13 -> 134.14277 | DP13: =BY13 -> 402.16041 | DQ13: =CA13 -> 244.39321 | DR13: =BO13 -> 293.9775 | DS13: =BQ13 -> 867.33654 | DT13: =BR13 -> 259.05938 | DU13: =BT13 -> 48.080469 | DV13: =BS13 -> 0 | DX13: =CX13 -> 123.26888 | DY13: =CY13 -> 21.562201 | DZ13: =CW13 -> 29.704679 | EA13: =CZ13 -> 1.5229212 | EB13: =DA13 -> 126.8555 | EC13: =CP13 -> 25.265352 | ED13: =CU13 -> 15.53136 | EE13: =CI13 -> 46.811962 | EF13: =CQ13 -> 6.1102159 | EG13: =CR13 -> 6.7373456 | EH13: =CS13 -> 128.3066 | EI13: =CT13 -> 35.879582 | EJ13: =CV13 -> 0.0062559 | EK13: =CJ13 -> 1.2966958 | EL13: =CL13 -> 0.5665194 | EM13: =CM13 -> 17.760967 | EN13: =CO13 -> 14.367727 | EO13: =CN13 -> 7.1763511
CG14: =CG13/CG12-1 -> 0.15510244 | DA14: =DA13/DA12-1 -> 0.079393579
BN15: =BN13/$CH13 -> 0.012790543 | BO15: =BO13/$CH13 -> 0.031113502 | BQ15: =BQ13/$CH13 -> 0.091795723 | BR15: =BR13/$CH13 -> 0.027417896 | BS15: =BS13/$CH13 -> 0 | BT15: =BT13/$CH13 -> 0.0050886607 | BU15: =BU13/$CH13 -> 0.057821872 | BV15: =BV13/$CH13 -> 0.034708644 | BW15: =BW13/$CH13 -> 0.046022061 | BX15: =BX13/$CH13 -> 0.01419718 | ... CF15: =CF13/$CH13 -> 0.0028009147 | CI15: =CI13/$DC13 -> 0.076900886 | CJ15: =CJ13/$DC13 -> 0.0021301618 | CL15: =CL13/$DC13 -> 0.00093065622 | CM15: =CM13/$DC13 -> 0.029177031 | CN15: =CN13/$DC13 -> 0.011789033 | CO15: =CO13/$DC13 -> 0.023602747 | CP15: =CP13/$DC13 -> 0.041504946 | CQ15: =CQ13/$DC13 -> 0.010037627 | CR15: =CR13/$DC13 -> 0.011067852 | CS15: =CS13/$DC13 -> 0.21077714 | ... DA15: =DA13/$DC13 -> 0.20839332
A16: Promedio ultimos 5 años | B16: =AVERAGE(B7:B12) -> 98.274356 | C16: =AVERAGE(C7:C12) -> 201.96433 | D16: =AVERAGE(D7:D12) -> 1117.695 | E16: =AVERAGE(E7:E12) -> 1766.9207 | F16: =AVERAGE(F7:F12) -> 6241.5652 | G16: =AVERAGE(G7:G12) -> 813.57122 | H16: =AVERAGE(H7:H12) -> 18970.821 | I16: =AVERAGE(I7:I12) -> 290.08197 | ... BK16: =AVERAGE(BK7:BK12) -> 62.724135 | BM16: Prom | BN16: =AVERAGE(BN3:BN12) -> 83.708364 | BO16: =AVERAGE(BO3:BO12) -> 172.09293 | BP16: =AVERAGE(BP3:BP12) -> 25608.545 | BQ16: =AVERAGE(BQ3:BQ12) -> 699.88979 | BR16: =AVERAGE(BR3:BR12) -> 176.26866 | BS16: =AVERAGE(BS3:BS12) -> 0.0004164 | BT16: =AVERAGE(BT3:BT12) -> 38.341733 | BU16: =AVERAGE(BU3:BU12) -> 631.86878 | ... CF16: =AVERAGE(CF3:CF12) -> 21.565829 | CG16: =AVERAGE(CG7:CG12) -> 38839.662 | CI16: =AVERAGE(CI3:CI12) -> 61.711235 | CJ16: =AVERAGE(CJ3:CJ12) -> 2.4500982 | CK16: =AVERAGE(CK3:CK12) -> 1797.2403 | CL16: =AVERAGE(CL3:CL12) -> 0.64866151 | CM16: =AVERAGE(CM3:CM12) -> 14.536617 | CN16: =AVERAGE(CN3:CN12) -> 3.2481471 | CO16: =AVERAGE(CO3:CO12) -> 20.219173 | CP16: =AVERAGE(CP3:CP12) -> 13.687346 | ... DA16: =AVERAGE(DA3:DA12) -> 64.584732 | DB16: =AVERAGE(DB7:DB12) -> 2803.3564 | DC16: =AVERAGE(DC7:DC12) -> 472.77014
B17: =B13/B16-1 -> 0.22974194 | C17: =C13/C16-1 -> 0.4555912 | D17: =D13/D16-1 -> 0.34799051 | E17: =E13/E16-1 -> 1.1949955 | F17: =F13/F16-1 -> 0.1124384 | G17: =G13/G16-1 -> 0.066085568 | H17: =H13/H16-1 -> -0.052036428 | I17: =I13/I16-1 -> -0.13165674 | ... BK17: =BK13/BK16-1 -> 1.0224352 | BN17: =BN13/BN16-1 -> 0.44372785 | BO17: =BO13/BO16-1 -> 0.70824858 | BP17: =BP13/BP16-1 -> 0.33004555 | BQ17: =BQ13/BQ16-1 -> 0.2392473 | BR17: =BR13/BR16-1 -> 0.46968488 | BS17: 0 | BT17: =BT13/BT16-1 -> 0.2539983 | BU17: =BU13/BU16-1 -> -0.13536971 | BV17: =BV13/BV16-1 -> 0.041445109 | BW17: =BW13/BW16-1 -> 0.26561029 | BX17: =BX13/BX16-1 -> -0.097284543 | BY17: =BY13/BY16-1 -> 0.63663292 | BZ17: =BZ13/BZ16-1 -> 0.1925065 | CA17: =CA13/CA16-1 -> 0.65422111 | ... CG17: =CG13/CG16-1 -> 0.12022299 | CH17: =CG13/CG12-1 -> 0.15510244 | CI17: =CI13/CI16-1 -> -0.24143534 | CJ17: =CJ13/CJ16-1 -> -0.47075763 | CK17: =CK13/CK16-1 -> 0.54628389 | CL17: =CL13/CL16-1 -> -0.12663325 | CM17: =CM13/CM16-1 -> 0.2218088 | CN17: =CN13/CN16-1 -> 1.2093677 | CO17: =CO13/CO16-1 -> -0.28940085 | CP17: =CP13/CP16-1 -> 0.8458912 | ... DC17: =DC13/DC16-1 -> 0.28758369
A19: 2016 | F19: =D13+E13+F13+H13+I13+J13 -> 34060.531 | BM19: 2016 | BN19: =BN3/$CG3 -> 0.0023411959 | BO19: =BO3/$CG3 -> 0.0064314434 | BP19: =BP3/$CG3 -> 0.78352373 | BQ19: =BQ3/$CG3 -> 0.025992501 | BR19: =BR3/$CG3 -> 0.0062686993 | BS19: =BS3/$CG3 -> 0 | BT19: =BT3/$CG3 -> 0.0012258662 | BU19: =BU3/$CG3 -> 0.027903825 | ... CF19: =CF3/$CG3 -> 0.00030258904 | CI19: =CI3/$DB3 -> 0.12213449 | CJ19: =CJ3/$DB3 -> 0.0056763937 | CK19: =CK3/$DB3 -> 0.34755386 | CL19: =CL3/$DB3 -> 0.0001730974 | CM19: =CM3/$DB3 -> 0.025345975 | CN19: =CN3/$DB3 -> 0.0011787051 | CO19: =CO3/$DB3 -> 0.039471439 | CP19: =CP3/$DB3 -> 0.0038472473 | ... DA19: =DA3/$DB3 -> 0.063013429 | DC19: =CG13/DB13 -> 12.842968
A20: 2017 | D20: =D13/$F19 -> 0.044234257 | E20: =E13/$F19 -> 0.11386737 | F20: =F13/$F19 -> 0.20385345 | H20: =H13/$F19 -> 0.5279908 | I20: =I13/$F19 -> 0.0073953845 | J20: =J13/$F19 -> 0.10265874 | BM20: 2017 | BN20: =BN4/$CG4 -> 0.0022604194 | BO20: =BO4/$CG4 -> 0.0057861147 | BP20: =BP4/$CG4 -> 0.77187891 | BQ20: =BQ4/$CG4 -> 0.025547084 | BR20: =BR4/$CG4 -> 0.0057013473 | BS20: =BS4/$CG4 -> 7.5886385e-08 | BT20: =BT4/$CG4 -> 0.00075697538 | BU20: =BU4/$CG4 -> 0.028026056 | ... CF20: =CF4/$CG4 -> 0.00057182909 | CI20: =CI4/$DB4 -> 0.059271304 | CJ20: =CJ4/$DB4 -> 0.0033089794 | CK20: =CK4/$DB4 -> 0.51269676 | CL20: =CL4/$DB4 -> 0.00059880301 | CM20: =CM4/$DB4 -> 0.021039928 | CN20: =CN4/$DB4 -> 0.0039957321 | CO20: =CO4/$DB4 -> 0.028575948 | CP20: =CP4/$DB4 -> 0.045444786 | ... DA20: =DA4/$DB4 -> 0.071799491 | DC20: =CH13/DC13 -> 15.521715
A21: 2018 | BM21: 2018 | BN21: =BN5/$CG5 -> 0.0032132163 | BO21: =BO5/$CG5 -> 0.005957427 | BP21: =BP5/$CG5 -> 0.73417258 | BQ21: =BQ5/$CG5 -> 0.022452058 | BR21: =BR5/$CG5 -> 0.0054615355 | BS21: =BS5/$CG5 -> 0 | BT21: =BT5/$CG5 -> 0.0015012066 | BU21: =BU5/$CG5 -> 0.030886973 | ... CF21: =CF5/$CG5 -> 0.00069813272 | CI21: =CI5/$DB5 -> 0.032294509 | CJ21: =CJ5/$DB5 -> 0.0015281927 | CK21: =CK5/$DB5 -> 0.77355356 | CL21: =CL5/$DB5 -> 9.6366095e-05 | CM21: =CM5/$DB5 -> 0.016137717 | CN21: =CN5/$DB5 -> 0.0019390407 | CO21: =CO5/$DB5 -> 0.01198667 | CP21: =CP5/$DB5 -> 0.003312709 | ... DA21: =DA5/$DB5 -> 0.036158778
A22: 2019 | BM22: 2019 | BN22: =BN6/$CG6 -> 0.0032798124 | BO22: =BO6/$CG6 -> 0.0046686957 | BP22: =BP6/$CG6 -> 0.7595458 | BQ22: =BQ6/$CG6 -> 0.020823035 | BR22: =BR6/$CG6 -> 0.0062732631 | BS22: =BS6/$CG6 -> 0 | BT22: =BT6/$CG6 -> 0.001674092 | BU22: =BU6/$CG6 -> 0.026862972 | ... CF22: =CF6/$CG6 -> 0.00055987543 | CI22: =CI6/$DB6 -> 0.02618127 | CJ22: =CJ6/$DB6 -> 0.001294072 | CK22: =CK6/$DB6 -> 0.77549749 | CL22: =CL6/$DB6 -> 9.4010274e-05 | CM22: =CM6/$DB6 -> 0.0073570011 | CN22: =CN6/$DB6 -> 0.0008399645 | CO22: =CO6/$DB6 -> 0.0073279611 | CP22: =CP6/$DB6 -> 0.0028699059 | ... DA22: =DA6/$DB6 -> 0.034399972
A23: 2020 | BM23: 2020 | BN23: =BN7/$CG7 -> 0.0026305014 | BO23: =BO7/$CG7 -> 0.0044256429 | BP23: =BP7/$CG7 -> 0.77559317 | BQ23: =BQ7/$CG7 -> 0.026029185 | BR23: =BR7/$CG7 -> 0.004325946 | BS23: =BS7/$CG7 -> 8.3789649e-08 | BT23: =BT7/$CG7 -> 0.0014921909 | BU23: =BU7/$CG7 -> 0.021127628 | ... CF23: =CF7/$CG7 -> 0.0017649559 | CI23: =CI7/$DB7 -> 0.017645018 | CJ23: =CJ7/$DB7 -> 0.0017868425 | CK23: =CK7/$DB7 -> 0.79148048 | CL23: =CL7/$DB7 -> 0.00015237975 | CM23: =CM7/$DB7 -> 0.0074301772 | CN23: =CN7/$DB7 -> 0.00087124685 | CO23: =CO7/$DB7 -> 0.015393771 | CP23: =CP7/$DB7 -> 0.0028079583 | ... DA23: =DA7/$DB7 -> 0.021577192
A24: 2021 | BM24: 2021 | BN24: =BN8/$CG8 -> 0.0025201905 | BO24: =BO8/$CG8 -> 0.0042167906 | BP24: =BP8/$CG8 -> 0.83606339 | BQ24: =BQ8/$CG8 -> 0.017691847 | BR24: =BR8/$CG8 -> 0.004165964 | BS24: =BS8/$CG8 -> 0 | BT24: =BT8/$CG8 -> 0.00084739728 | BU24: =BU8/$CG8 -> 0.014801287 | ... CF24: =CF8/$CG8 -> 0.0012920845 | CI24: =CI8/$DB8 -> 0.021111724 | CJ24: =CJ8/$DB8 -> 0.00046868925 | CK24: =CK8/$DB8 -> 0.81296079 | CL24: =CL8/$DB8 -> 0.00014133167 | CM24: =CM8/$DB8 -> 0.0027799915 | CN24: =CN8/$DB8 -> 0.00087962135 | CO24: =CO8/$DB8 -> 0.006112237 | CP24: =CP8/$DB8 -> 0.0038706766 | ... DA24: =DA8/$DB8 -> 0.02627891
A25: 2022 | BM25: 2022 | BN25: =BN9/$CG9 -> 0.0033875981 | BO25: =BO9/$CG9 -> 0.0034514824 | BP25: =BP9/$CG9 -> 0.82857379 | BQ25: =BQ9/$CG9 -> 0.01604501 | BR25: =BR9/$CG9 -> 0.0040976217 | BS25: =BS9/$CG9 -> 0 | BT25: =BT9/$CG9 -> 0.00084087617 | BU25: =BU9/$CG9 -> 0.014119632 | ... CF25: =CF9/$CG9 -> 0.00020538308 | CI25: =CI9/$DB9 -> 0.02989455 | CJ25: =CJ9/$DB9 -> 0.00020074077 | CK25: =CK9/$DB9 -> 0.77317762 | CL25: =CL9/$DB9 -> 0.00024205321 | CM25: =CM9/$DB9 -> 0.002045795 | CN25: =CN9/$DB9 -> 0.0025039816 | CO25: =CO9/$DB9 -> 0.0070344364 | CP25: =CP9/$DB9 -> 0.0043628764 | ... DA25: =DA9/$DB9 -> 0.032287198
A26: 2023 | BM26: 2023 | BN26: =BN10/$CG10 -> 0.0009333275 | BO26: =BO10/$CG10 -> 0.0058274828 | BP26: =BP10/$CG10 -> 0.77608346 | BQ26: =BQ10/$CG10 -> 0.026701746 | BR26: =BR10/$CG10 -> 0.0066808254 | BS26: =BS10/$CG10 -> 0 | BT26: =BT10/$CG10 -> 0.0014311121 | BU26: =BU10/$CG10 -> 0.017091885 | ... CF26: =CF10/$CG10 -> 0.00040915478 | CI26: =CI10/$DB10 -> 0.013877292 | CJ26: =CJ10/$DB10 -> 7.080545e-05 | CK26: =CK10/$DB10 -> 0.89459729 | CL26: =CL10/$DB10 -> 9.6382327e-05 | CM26: =CM10/$DB10 -> 0.0021734369 | CN26: =CN10/$DB10 -> 0.0016731678 | CO26: =CO10/$DB10 -> 0.0025012986 | CP26: =CP10/$DB10 -> 0.0021805974 | ... DA26: =DA10/$DB10 -> 0.0088995948
A27: 2024 | BM27: 2024 | BN27: =BN11/$CG11 -> 0.0034220186 | BO27: =BO11/$CG11 -> 0.0052941633 | BP27: =BP11/$CG11 -> 0.81049426 | BQ27: =BQ11/$CG11 -> 0.020255078 | BR27: =BR11/$CG11 -> 0.0063547532 | BS27: =BS11/$CG11 -> 0 | BT27: =BT11/$CG11 -> 0.0015414687 | BU27: =BU11/$CG11 -> 0.016210456 | ... CF27: =CF11/$CG11 -> 0.00046475455 | CI27: =CI11/$DB11 -> 0.014418123 | CJ27: =CJ11/$DB11 -> 0.0010678127 | CK27: =CK11/$DB11 -> 0.87181139 | CL27: =CL11/$DB11 -> 0.00078010578 | CM27: =CM11/$DB11 -> 0.0043996804 | CN27: =CN11/$DB11 -> 0.00035457487 | CO27: =CO11/$DB11 -> 0.0071940622 | CP27: =CP11/$DB11 -> 0.0034886442 | ... DA27: =DA11/$DB11 -> 0.010037262
A28: 2025 | BM28: 2025 | BN28: =BN12/$CG12 -> 0.0018009805 | BO28: =BO12/$CG12 -> 0.0086414465 | BP28: =BP12/$CG12 -> 0.78902726 | BQ28: =BQ12/$CG12 -> 0.022944258 | BR28: =BR12/$CG12 -> 0.0066243027 | BS28: =BS12/$CG12 -> 0 | BT28: =BT12/$CG12 -> 0.00099731695 | BU28: =BU12/$CG12 -> 0.016201308 | ... CF28: =CF12/$CG12 -> 0.00045198613 | CI28: =CI12/$DB12 -> 0.031476235 | CJ28: =CJ12/$DB12 -> 0.0011657979 | CK28: =CK12/$DB12 -> 0.77441679 | CL28: =CL12/$DB12 -> 0.00063268897 | CM28: =CM12/$DB12 -> 0.0029042268 | CN28: =CN12/$DB12 -> 0.000894817 | CO28: =CO12/$DB12 -> 0.003896556 | CP28: =CP12/$DB12 -> 0.010083246 | ... DA28: =DA12/$DB12 -> 0.048089755
A29: 2026 | BM29: 2026 | BN29: =BN13/$CG13 -> 0.0027776292 | BO29: =BO13/$CG13 -> 0.0067566927 | BP29: =BP13/$CG13 -> 0.78283728 | BQ29: =BQ13/$CG13 -> 0.019934609 | BR29: =BR13/$CG13 -> 0.0059541449 | BS29: =BS13/$CG13 -> 0 | BT29: =BT13/$CG13 -> 0.0011050674 | BU29: =BU13/$CG13 -> 0.012556755 | ... CF29: =CF13/$CG13 -> 0.00060825426 | CI29: =CI13/$DB13 -> 0.013817909 | CJ29: =CJ13/$DB13 -> 0.00038275736 | CK29: =CK13/$DB13 -> 0.82031535 | CL29: =CL13/$DB13 -> 0.00016722463 | CM29: =CM13/$DB13 -> 0.0052426646 | CN29: =CN13/$DB13 -> 0.0021183082 | CO29: =CO13/$DB13 -> 0.0042410514 | CP29: =CP13/$DB13 -> 0.0074578016 | ... DA29: =DA13/$DB13 -> 0.037445081
BM31: Prom | BN31: =AVERAGE(BN23:BN28) -> 0.0024491028 | BO31: =AVERAGE(BO23:BO28) -> 0.0053095014 | BP31: =AVERAGE(BP23:BP28) -> 0.80263922 | BQ31: =AVERAGE(BQ23:BQ28) -> 0.021611187 | BR31: =AVERAGE(BR23:BR28) -> 0.0053749022 | BS31: =AVERAGE(BS23:BS28) -> 1.3964941e-08 | BT31: =AVERAGE(BT23:BT28) -> 0.001191727 | BU31: =AVERAGE(BU23:BU28) -> 0.016592033 | ... CF31: =AVERAGE(CF23:CF28) -> 0.00076471983 | CI31: =AVERAGE(CI24:CI29) -> 0.020765972 | CJ31: =AVERAGE(CJ24:CJ29) -> 0.0005594339 | CK31: =AVERAGE(CK24:CK29) -> 0.82454654 | CL31: =AVERAGE(CL24:CL29) -> 0.00034329776 | CM31: =AVERAGE(CM24:CM29) -> 0.0032576325 | CN31: =AVERAGE(CN24:CN29) -> 0.0014040785 | CO31: =AVERAGE(CO24:CO29) -> 0.0051632736 | CP31: =AVERAGE(CP24:CP29) -> 0.0052406403 | ... DA31: =AVERAGE(DA24:DA29) -> 0.027172967
BP32: 1 | BQ32: 4 | BU32: 5 | CC32: 2 | CD32: 3
CV33: =CV13*1000000 -> 6255.9 | CX33: =CX13/CX12-1 -> 0.82618652
CE34: =80%+9% -> 0.89
CE35: 1 | CF35: =CE35-CE34 -> 0.11
CE36: =BP13+CC13 -> 38184.147
CE37: =CG13-CE36 -> 5324.9348

Sheet PP
B1: Arroz | D1: Vino | F1: Trigo | H1: Bovino | J1: Porcino | L1: Aviar | N1: Ovino | P1: Yerba | R1: Leche | W1: Papa | AD1: Hortalizas | AK1: Participacion del Productor | AX1: https://fetra.org.ar/tarifas.php?anio=2026
F2: =0.75*1.09 -> 0.8175 | H2: =0.58*0.76 -> 0.4408 | J2: =0.8*0.75 -> 0.6 | L2: 0.7 | N2: =0.54*0.7 -> 0.378 | P2: 0.34 | Q2: 2 | AX2: Actualizaciones
B3: $/kg | D3: $/lt | F3: $/kg | H3: $/kg | J3: $/kg | L3: $/kg | N3: $/kg | P3: $/kg | R3: $/lt | W3: $ Mayorista | X3: Comision | Y3: Gastos | Z3: Flete | AB3: 20 | AD3: $ Mayorista | AE3: Comision | AF3: Gastos | AG3: Flete | AH3: 18 | AX3: FETRA
B4: P.P | C4: P.C | D4: P.P | E4: P.C | F4: P.P | G4: P.C | H4: P.P | I4: P.C | J4: P.P | K4: P.C | L4: P.P | M4: P.C | N4: P.P | O4: P.C | P4: P.P | Q4: P.C | R4: P.P | S4: % GB | T4: precio sol.utiles | V4: P.C | W4: 1 | X4: 0.08 | Z4: % | AB4: P.P | AC4: P.C | AD4: 1 | AE4: 0.08 | AH4: P.P | AI4: P.C | AL4: Arroz | AM4: Vino | AN4: Trigo | AO4: Bovino | AP4: Porcino | AQ4: Aviar | AR4: Ovino | AS4: Yerba | AT4: Leche | AU4: Papa | AV4: Hortalizas | AY4: $/tn/kg | AZ4: %
A5: 42370 | B5: =datos!R10/1000 -> 2.1 | D5: =datos!AI10 -> 3.4258 | F5: =(datos!AD10/1000)/PP!$F$2 -> 2.3743329 | H5: =datos!BK10/$H$2 -> 57.899274 | I5: =datos!NB10 -> 109.1 | J5: =datos!BR10/$J$2 -> 24.45 | K5: =datos!NE10 -> 84.93 | L5: =datos!BO10*$L$2 -> 12.41065 | M5: =datos!NA10 -> 32.66 | N5: =datos!BS10*$N$2 -> 21.924 | P5: =(datos!AG10/1000)/$P$2 -> 12.564706 | R5: =datos!BN10 -> 2.75 | W5: =datos!AV10*W$4 -> 63.8 | X5: =W5*X$4 -> 5.104 | Y5: =Y6/(1+(datos!G11/datos!G10-1)) -> 3.2881411 | AD5: =datos!BB10*AD$4 -> 97.835 | AE5: =AD5*AE$4 -> 7.8268 | AF5: =Y5 -> 3.2881411 | AK5: =A5 -> 42370 | AO5: =H5/I5 -> 0.53069912 | AP5: =J5/K5 -> 0.28788414 | AQ5: =L5/M5 -> 0.37999541 | AX5: Feb-22 - Mar-22 | AY5: 578.25
A6: 42401 | B6: =datos!R11/1000 -> 2.05 | D6: =datos!AI11 -> 3.67 | F6: =(datos!AD11/1000)/PP!$F$2 -> 2.4720931 | H6: =datos!BK11/$H$2 -> 59.947822 | I6: =datos!NB11 -> 104.08 | J6: =datos!BR11/$J$2 -> 24.8 | K6: =datos!NE11 -> 84.97 | L6: =datos!BO11*$L$2 -> 14.372474 | M6: =datos!NA11 -> 33.23 | N6: =datos!BS11*$N$2 -> 21.546 | P6: =(datos!AG11/1000)/$P$2 -> 12.564706 | R6: =datos!BN11 -> 2.806 | W6: =datos!AV11*W$4 -> 60.6 | X6: =W6*X$4 -> 4.848 | Y6: =Y7/(1+(datos!G12/datos!G11-1)) -> 3.4415758 | AD6: =datos!BB11*AD$4 -> 275.947 | AE6: =AD6*AE$4 -> 22.07576 | AF6: =Y6 -> 3.4415758 | AK6: =A6 -> 42401 | AO6: =H6/I6 -> 0.57597831 | AP6: =J6/K6 -> 0.29186772 | AQ6: =L6/M6 -> 0.43251501 | AX6: Abr-22 - May-22 | AY6: 693.9 | AZ6: =AY6/AY5-1 -> 0.2
A7: 42430 | B7: =datos!R12/1000 -> 2.05 | D7: =datos!AI12 -> 4.63 | F7: =(datos!AD12/1000)/PP!$F$2 -> 2.644278 | H7: =datos!BK12/$H$2 -> 61.876134 | I7: =datos!NB12 -> 104.06 | J7: =datos!BR12/$J$2 -> 24.566667 | K7: =datos!NE12 -> 85.26 | L7: =datos!BO12*$L$2 -> 14.941333 | M7: =datos!NA12 -> 36.09 | N7: =datos!BS12*$N$2 -> 21.546 | P7: =(datos!AG12/1000)/$P$2 -> 12.564706 | R7: =datos!BN12 -> 2.89 | W7: =datos!AV12*W$4 -> 63.8 | X7: =W7*X$4 -> 5.104 | Y7: =Y8/(1+(datos!G13/datos!G12-1)) -> 3.5414867 | AD7: =datos!BB12*AD$4 -> 127.895 | AE7: =AD7*AE$4 -> 10.2316 | AF7: =Y7 -> 3.5414867 | AK7: =A7 -> 42430 | AO7: =H7/I7 -> 0.59461978 | AP7: =J7/K7 -> 0.28813824 | AQ7: =L7/M7 -> 0.41400203 | AX7: Jun-22 - Oct-22 | AY7: 802.92 | AZ7: =AY7/AY6-1 -> 0.15711198
A8: 42461 | B8: =datos!R13/1000 -> 2.15 | C8: =datos!MA13 -> 16.21 | D8: =datos!AI13 -> 5.31 | E8: =datos!MP13 -> 17.15 | F8: =(datos!AD13/1000)/PP!$F$2 -> 2.8187279 | G8: =datos!MH13 -> 29.85 | H8: =datos!BK13/$H$2 -> 65.830309 | I8: =datos!NB13 -> 104.5 | J8: =datos!BR13/$J$2 -> 24.35 | K8: =datos!NE13 -> 85.38 | L8: =datos!BO13*$L$2 -> 13.095 | M8: =datos!NA13 -> 34.25 | N8: =datos!BS13*$N$2 -> 22.302 | P8: =(datos!AG13/1000)/$P$2 -> 14.126471 | Q8: =datos!MY13*$Q$2 -> 52.58 | R8: =datos!BN13 -> 3.347 | U8: =T8*S8 -> 0 | V8: =datos!NC13+U8 -> 14.37 | W8: =datos!AV13*W$4 -> 71.2 | X8: =W8*X$4 -> 5.696 | Y8: =Y9/(1+(datos!G14/datos!G13-1)) -> 3.7537975 | AC8: =datos!MJ13 -> 9.26 | AD8: =datos!BB13*AD$4 -> 147.255 | AE8: =AD8*AE$4 -> 11.7804 | AF8: =Y8 -> 3.7537975 | AI8: =AVERAGE(datos!ML13,datos!MM13,datos!MN13,datos!MO13) -> 15.303333 | AK8: =A8 -> 42461 | AL8: =B8/C8 -> 0.13263418 | AM8: =D8/E8 -> 0.30962099 | AN8: =F8/G8 -> 0.094429747 | AO8: =H8/I8 -> 0.62995511 | AP8: =J8/K8 -> 0.2851956 | AQ8: =L8/M8 -> 0.38233577 | AS8: =P8/Q8 -> 0.26866623 | AX8: Nov-22 - Ene-23 | AY8: 1086.65 | AZ8: =AY8/AY7-1 -> 0.35337269
A9: 42491 | B9: =datos!R14/1000 -> 2.5 | C9: =datos!MA14 -> 16.32 | D9: =datos!AI14 -> 6.49 | E9: =datos!MP14 -> 20.61 | F9: =(datos!AD14/1000)/PP!$F$2 -> 3.177648 | G9: =datos!MH14 -> 30.85 | H9: =datos!BK14/$H$2 -> 68.464156 | I9: =datos!NB14 -> 106.67 | J9: =datos!BR14/$J$2 -> 23.616667 | K9: =datos!NE14 -> 84.98 | L9: =datos!BO14*$L$2 -> 13.0165 | M9: =datos!NA14 -> 33.04 | N9: =datos!BS14*$N$2 -> 22.302 | P9: =(datos!AG14/1000)/$P$2 -> 14.126471 | Q9: =datos!MY14*$Q$2 -> 53.2 | R9: =datos!BN14 -> 3.961 | U9: =T9*S9 -> 0 | V9: =datos!NC14+U9 -> 15.65 | W9: =datos!AV14*W$4 -> 79.8 | X9: =W9*X$4 -> 6.384 | Y9: =Y10/(1+(datos!G15/datos!G14-1)) -> 3.8965275 | AC9: =datos!MJ14 -> 9.44 | AD9: =datos!BB14*AD$4 -> 184.615 | AE9: =AD9*AE$4 -> 14.7692 | AF9: =Y9 -> 3.8965275 | AI9: =AVERAGE(datos!ML14,datos!MM14,datos!MN14,datos!MO14) -> 18.266667 | AK9: =A9 -> 42491 | AL9: =B9/C9 -> 0.15318627 | AM9: =D9/E9 -> 0.31489568 | AN9: =F9/G9 -> 0.10300318 | AO9: =H9/I9 -> 0.64183141 | AP9: =J9/K9 -> 0.27790853 | AQ9: =L9/M9 -> 0.39396186 | AS9: =P9/Q9 -> 0.26553516 | AX9: Feb-23 - May-23 | AY9: 1325.71 | AZ9: =AY9/AY8-1 -> 0.21999724
A10: 42522 | B10: =datos!R15/1000 -> 2.75 | C10: =datos!MA15 -> 16.6 | D10: =datos!AI15 -> 7.23 | E10: =datos!MP15 -> 23.2 | F10: =(datos!AD15/1000)/PP!$F$2 -> 3.2982826 | G10: =datos!MH15 -> 32.56 | H10: =datos!BK15/$H$2 -> 70.224592 | I10: =datos!NB15 -> 108.57 | J10: =datos!BR15/$J$2 -> 23.233333 | K10: =datos!NE15 -> 85.36 | L10: =datos!BO15*$L$2 -> 12.733636 | M10: =datos!NA15 -> 33.37 | N10: =datos!BS15*$N$2 -> 22.302 | P10: =(datos!AG15/1000)/$P$2 -> 14.126471 | Q10: =datos!MY15*$Q$2 -> 53.76 | R10: =datos!BN15 -> 4.121 | U10: =T10*S10 -> 0 | V10: =datos!NC15+U10 -> 16.07 | W10: =datos!AV15*W$4 -> 104.8 | X10: =W10*X$4 -> 8.384 | Y10: =Y11/(1+(datos!G16/datos!G15-1)) -> 4.0053591 | AC10: =datos!MJ15 -> 11.06 | AD10: =datos!BB15*AD$4 -> 195.5 | AE10: =AD10*AE$4 -> 15.64 | AF10: =Y10 -> 4.0053591 | AI10: =AVERAGE(datos!ML15,datos!MM15,datos!MN15,datos!MO15) -> 20.433333 | AK10: =A10 -> 42522 | AL10: =B10/C10 -> 0.16566265 | AM10: =D10/E10 -> 0.31163793 | AN10: =F10/G10 -> 0.10129861 | AO10: =H10/I10 -> 0.64681396 | AP10: =J10/K10 -> 0.27218057 | AQ10: =L10/M10 -> 0.38158934 | AS10: =P10/Q10 -> 0.26276917 | AX10: Jun-23 - Ago-23 | AY10: 1723.42 | AZ10: =AY10/AY9-1 -> 0.29999774
A11: 42552 | B11: =datos!R16/1000 -> 2.95 | C11: =datos!MA16 -> 16.81 | D11: =datos!AI16 -> 7.64 | E11: =datos!MP16 -> 25.75 | F11: =(datos!AD16/1000)/PP!$F$2 -> 3.2457093 | G11: =datos!MH16 -> 33.07 | H11: =datos!BK16/$H$2 -> 70.11343 | I11: =datos!NB16 -> 108.43 | J11: =datos!BR16/$J$2 -> 23.016667 | K11: =datos!NE16 -> 85.67 | L11: =datos!BO16*$L$2 -> 13.271667 | M11: =datos!NA16 -> 32.66 | N11: =datos!BS16*$N$2 -> 22.302 | P11: =(datos!AG16/1000)/$P$2 -> 14.126471 | Q11: =datos!MY16*$Q$2 -> 54.58 | R11: =datos!BN16 -> 4.1948463 | U11: =T11*S11 -> 0 | V11: =datos!NC16+U11 -> 16.53 | W11: =datos!AV16*W$4 -> 115.6 | X11: =W11*X$4 -> 9.248 | Y11: =Y12/(1+(datos!G17/datos!G16-1)) -> 4.1034859 | AC11: =datos!MJ16 -> 11.91 | AD11: =datos!BB16*AD$4 -> 225.86 | AE11: =AD11*AE$4 -> 18.0688 | AF11: =Y11 -> 4.1034859 | AI11: =AVERAGE(datos!ML16,datos!MM16,datos!MN16,datos!MO16) -> 23.346667 | AK11: =A11 -> 42552 | AL11: =B11/C11 -> 0.17549078 | AM11: =D11/E11 -> 0.29669903 | AN11: =F11/G11 -> 0.098146636 | AO11: =H11/I11 -> 0.64662391 | AP11: =J11/K11 -> 0.26866659 | AQ11: =L11/M11 -> 0.40635844 | AS11: =P11/Q11 -> 0.25882137 | AX11: Sep-23 - Dic-23 | AY11: 2361.09 | AZ11: =AY11/AY10-1 -> 0.37000267
A12: 42583 | B12: =datos!R17/1000 -> 3.35 | C12: =datos!MA17 -> 17.24 | D12: =datos!AI17 -> 7.69 | E12: =datos!MP17 -> 27.95 | F12: =(datos!AD17/1000)/PP!$F$2 -> 3.0106658 | G12: =datos!MH17 -> 33.96 | H12: =datos!BK17/$H$2 -> 70 | I12: =datos!NB17 -> 108.56 | J12: =datos!BR17/$J$2 -> 24.45 | K12: =datos!NE17 -> 88.81 | L12: =datos!BO17*$L$2 -> 14.91 | M12: =datos!NA17 -> 33.68 | N12: =datos!BS17*$N$2 -> 29.862 | P12: =(datos!AG17/1000)/$P$2 -> 14.126471 | Q12: =datos!MY17*$Q$2 -> 54.68 | R12: =datos!BN17 -> 4.2666879 | U12: =T12*S12 -> 0 | V12: =datos!NC17+U12 -> 16.84 | W12: =datos!AV17*W$4 -> 101.2 | X12: =W12*X$4 -> 8.096 | Y12: =Y13/(1+(datos!G18/datos!G17-1)) -> 4.148089 | AC12: =datos!MJ17 -> 11.67 | AD12: =datos!BB17*AD$4 -> 202.5775 | AE12: =AD12*AE$4 -> 16.2062 | AF12: =Y12 -> 4.148089 | AI12: =AVERAGE(datos!ML17,datos!MM17,datos!MN17,datos!MO17) -> 21.426667 | AK12: =A12 -> 42583 | AL12: =B12/C12 -> 0.19431555 | AM12: =D12/E12 -> 0.27513417 | AN12: =F12/G12 -> 0.088653291 | AO12: =H12/I12 -> 0.64480472 | AP12: =J12/K12 -> 0.27530683 | AQ12: =L12/M12 -> 0.44269596 | AS12: =P12/Q12 -> 0.25834804 | AX12: Ene-24 - Feb-24 | AY12: 4279.47 | AZ12: =AY12/AY11-1 -> 0.81249762
A13: 42614 | B13: =datos!R18/1000 -> 3.55 | C13: =datos!MA18 -> 18.18 | D13: =datos!AI18 -> 8.55 | E13: =datos!MP18 -> 29.03 | F13: =(datos!AD18/1000)/PP!$F$2 -> 2.7243953 | G13: =datos!MH18 -> 34.29 | H13: =datos!BK18/$H$2 -> 70.764519 | I13: =datos!NB18 -> 110.92 | J13: =datos!BR18/$J$2 -> 26.616667 | K13: =datos!NE18 -> 96.21 | L13: =datos!BO18*$L$2 -> 14.160682 | M13: =datos!NA18 -> 34.85 | N13: =datos!BS18*$N$2 -> 30.24 | P13: =(datos!AG18/1000)/$P$2 -> 14.126471 | Q13: =datos!MY18*$Q$2 -> 55.46 | R13: =datos!BN18 -> 4.3778386 | U13: =T13*S13 -> 0 | V13: =datos!NC18+U13 -> 17.03 | W13: =datos!AV18*W$4 -> 112.4 | X13: =W13*X$4 -> 8.992 | Y13: =Y14/(1+(datos!G19/datos!G18-1)) -> 4.1891239 | AC13: =datos!MJ18 -> 11.95 | AD13: =datos!BB18*AD$4 -> 251.7 | AE13: =AD13*AE$4 -> 20.136 | AF13: =Y13 -> 4.1891239 | AI13: =AVERAGE(datos!ML18,datos!MM18,datos!MN18,datos!MO18) -> 25.486667 | AK13: =A13 -> 42614 | AL13: =B13/C13 -> 0.19526953 | AM13: =D13/E13 -> 0.29452291 | AN13: =F13/G13 -> 0.079451599 | AO13: =H13/I13 -> 0.63797799 | AP13: =J13/K13 -> 0.27665177 | AQ13: =L13/M13 -> 0.40633233 | AS13: =P13/Q13 -> 0.25471458 | AX13: Mar-24 - Jun-24 | AY13: 5333.08 | AZ13: =AY13/AY12-1 -> 0.24620105
A14: 42644 | B14: =datos!R19/1000 -> 3.75 | C14: =datos!MA19 -> 18.49 | D14: =datos!AI19 -> 9.65 | E14: =datos!MP19 -> 30.03 | F14: =(datos!AD19/1000)/PP!$F$2 -> 2.7571119 | G14: =datos!MH19 -> 33.94 | H14: =datos!BK19/$H$2 -> 68.346189 | I14: =datos!NB19 -> 112.94 | J14: =datos!BR19/$J$2 -> 28.583333 | K14: =datos!NE19 -> 98.99 | L14: =datos!BO19*$L$2 -> 15.65375 | M14: =datos!NA19 -> 36.68 | N14: =datos!BS19*$N$2 -> 30.24 | P14: =(datos!AG19/1000)/$P$2 -> 15 | Q14: =datos!MY19*$Q$2 -> 56.26 | R14: =datos!BN19 -> 4.428 | U14: =T14*S14 -> 0 | V14: =datos!NC19+U14 -> 17.55 | W14: =datos!AV19*W$4 -> 95.2 | X14: =W14*X$4 -> 7.616 | Y14: =Y15/(1+(datos!G20/datos!G19-1)) -> 4.3015237 | AC14: =datos!MJ19 -> 12.55 | AD14: =datos!BB19*AD$4 -> 206.625 | AE14: =AD14*AE$4 -> 16.53 | AF14: =Y14 -> 4.3015237 | AI14: =AVERAGE(datos!ML19,datos!MM19,datos!MN19,datos!MO19) -> 25.193333 | AK14: =A14 -> 42644 | AL14: =B14/C14 -> 0.20281233 | AM14: =D14/E14 -> 0.32134532 | AN14: =F14/G14 -> 0.081234883 | AO14: =H14/I14 -> 0.60515485 | AP14: =J14/K14 -> 0.28874971 | AQ14: =L14/M14 -> 0.42676527 | AS14: =P14/Q14 -> 0.26661927 | AX14: Jul-24 - Dic-24 | AY14: 6239.7 | AZ14: =AY14/AY13-1 -> 0.16999932
A15: 42675 | B15: =datos!R20/1000 -> 3.625 | C15: =datos!MA20 -> 18.94 | D15: =datos!AI20 -> 10.81 | E15: =datos!MP20 -> 33.28 | F15: =(datos!AD20/1000)/PP!$F$2 -> 2.7749993 | G15: =datos!MH20 -> 33.96 | H15: =datos!BK20/$H$2 -> 65.837114 | I15: =datos!NB20 -> 113.66 | J15: =datos!BR20/$J$2 -> 30.116667 | K15: =datos!NE20 -> 101 | L15: =datos!BO20*$L$2 -> 14.295 | M15: =datos!NA20 -> 35.8 | N15: =datos!BS20*$N$2 -> 26.46 | P15: =(datos!AG20/1000)/$P$2 -> 15 | Q15: =datos!MY20*$Q$2 -> 56.86 | R15: =datos!BN20 -> 4.32 | U15: =T15*S15 -> 0 | V15: =datos!NC20+U15 -> 17.92 | W15: =datos!AV20*W$4 -> 81.8 | X15: =W15*X$4 -> 6.544 | Y15: =Y16/(1+(datos!G21/datos!G20-1)) -> 4.3746728 | AC15: =datos!MJ20 -> 11.78 | AD15: =datos!BB20*AD$4 -> 157.225 | AE15: =AD15*AE$4 -> 12.578 | AF15: =Y15 -> 4.3746728 | AI15: =AVERAGE(datos!ML20,datos!MM20,datos!MN20,datos!MO20) -> 23.096667 | AK15: =A15 -> 42675 | AL15: =B15/C15 -> 0.19139388 | AM15: =D15/E15 -> 0.32481971 | AN15: =F15/G15 -> 0.081713759 | AO15: =H15/I15 -> 0.57924612 | AP15: =J15/K15 -> 0.29818482 | AQ15: =L15/M15 -> 0.39930168 | AS15: =P15/Q15 -> 0.26380584 | AX15: Ene-25 - Ago-25 | AY15: 6988.47 | AZ15: =AY15/AY14-1 -> 0.12000096
A16: 42705 | B16: =datos!R21/1000 -> 3.5 | C16: =datos!MA21 -> 19.46 | D16: =datos!AI21 -> 12.3 | E16: =datos!MP21 -> 35.76 | F16: =(datos!AD21/1000)/PP!$F$2 -> 2.8164061 | G16: =datos!MH21 -> 34.28 | H16: =datos!BK21/$H$2 -> 64.657441 | I16: =datos!NB21 -> 116.82 | J16: =datos!BR21/$J$2 -> 30.866667 | K16: =datos!NE21 -> 105.99 | L16: =datos!BO21*$L$2 -> 15.911 | M16: =datos!NA21 -> 36.7 | N16: =datos!BS21*$N$2 -> 25.704 | P16: =(datos!AG21/1000)/$P$2 -> 15 | Q16: =datos!MY21*$Q$2 -> 56.98 | R16: =datos!BN21 -> 4.68 | U16: =T16*S16 -> 0 | V16: =datos!NC21+U16 -> 18.05 | W16: =datos!AV21*W$4 -> 92.4 | X16: =W16*X$4 -> 7.392 | Y16: =Y17/(1+(datos!G22/datos!G21-1)) -> 4.4460378 | AC16: =datos!MJ21 -> 11.59 | AD16: =datos!BB21*AD$4 -> 129.6 | AE16: =AD16*AE$4 -> 10.368 | AF16: =Y16 -> 4.4460378 | AI16: =AVERAGE(datos!ML21,datos!MM21,datos!MN21,datos!MO21) -> 16.776667 | AK16: =A16 -> 42705 | AL16: =B16/C16 -> 0.17985612 | AM16: =D16/E16 -> 0.34395973 | AN16: =F16/G16 -> 0.082158872 | AO16: =H16/I16 -> 0.55347921 | AP16: =J16/K16 -> 0.29122244 | AQ16: =L16/M16 -> 0.43354223 | AS16: =P16/Q16 -> 0.26325026 | AX16: Sep-25 - Dic-25 | AY16: 8083.56 | AZ16: =AY16/AY15-1 -> 0.15669954
A17: 42736 | B17: =datos!R22/1000 -> 3.65 | C17: =datos!MA22 -> 19.5 | D17: =datos!AI22 -> 11.49 | E17: =datos!MP22 -> 36.63 | F17: =(datos!AD22/1000)/PP!$F$2 -> 3.2106005 | G17: =datos!MH22 -> 34.83 | H17: =datos!BK22/$H$2 -> 63.482305 | I17: =datos!NB22 -> 115.15 | J17: =datos!BR22/$J$2 -> 31.866667 | K17: =datos!NE22 -> 108.67 | L17: =datos!BO22*$L$2 -> 13.607045 | M17: =datos!NA22 -> 34.2 | N17: =datos!BS22*$N$2 -> 26.838 | P17: =(datos!AG22/1000)/$P$2 -> 15 | Q17: =datos!MY22*$Q$2 -> 57.06 | R17: =datos!BN22 -> 4.91 | U17: =T17*S17 -> 0 | V17: =datos!NC22+U17 -> 18.6 | W17: =datos!AV22*W$4 -> 135.98061 | X17: =W17*X$4 -> 10.878448 | Y17: =Y18/(1+(datos!G23/datos!G22-1)) -> 4.5171744 | AC17: =datos!MJ22 -> 12.45 | AD17: =datos!BB22*AD$4 -> 117.47138 | AE17: =AD17*AE$4 -> 9.3977107 | AF17: =Y17 -> 4.5171744 | AI17: =AVERAGE(datos!ML22,datos!MM22,datos!MN22,datos!MO22) -> 16.643333 | AK17: =A17 -> 42736 | AL17: =B17/C17 -> 0.18717949 | AM17: =D17/E17 -> 0.31367731 | AN17: =F17/G17 -> 0.09217917 | AO17: =H17/I17 -> 0.55130095 | AP17: =J17/K17 -> 0.29324254 | AQ17: =L17/M17 -> 0.39786683 | AS17: =P17/Q17 -> 0.26288118 | AX17: Ene-26 - Feb-26 | AY17: 8850.69 | AZ17: =AY17/AY16-1 -> 0.094900019
A18: 42767 | B18: =datos!R23/1000 -> 3.35 | C18: =datos!MA23 -> 19.94 | D18: =datos!AI23 -> 11.86 | E18: =datos!MP23 -> 37.23 | F18: =(datos!AD23/1000)/PP!$F$2 -> 3.2989619 | G18: =datos!MH23 -> 35.6 | H18: =datos!BK23/$H$2 -> 67.161978 | I18: =datos!NB23 -> 114.64 | J18: =datos!BR23/$J$2 -> 31.833333 | K18: =datos!NE23 -> 106.79 | L18: =datos!BO23*$L$2 -> 14.785556 | M18: =datos!NA23 -> 34.6 | N18: =datos!BS23*$N$2 -> 28.35 | P18: =(datos!AG23/1000)/$P$2 -> 15 | Q18: =datos!MY23*$Q$2 -> 57.82 | R18: =datos!BN23 -> 5.02 | U18: =T18*S18 -> 0 | V18: =datos!NC23+U18 -> 18.86 | W18: =datos!AV23*W$4 -> 144.65017 | X18: =W18*X$4 -> 11.572013 | Y18: =Y19/(1+(datos!G24/datos!G23-1)) -> 4.6105412 | AC18: =datos!MJ23 -> 13.67 | AD18: =datos!BB23*AD$4 -> 125.6352 | AE18: =AD18*AE$4 -> 10.050816 | AF18: =Y18 -> 4.6105412 | AI18: =AVERAGE(datos!ML23,datos!MM23,datos!MN23,datos!MO23) -> 16.61 | AK18: =A18 -> 42767 | AL18: =B18/C18 -> 0.16800401 | AM18: =D18/E18 -> 0.3185603 | AN18: =F18/G18 -> 0.09266747 | AO18: =H18/I18 -> 0.58585117 | AP18: =J18/K18 -> 0.29809283 | AQ18: =L18/M18 -> 0.4273282 | AS18: =P18/Q18 -> 0.2594258 | AX18: 46082 | AY18: 10015.44 | AZ18: =AY18/AY17-1 -> 0.13159991
A19: 42795 | B19: =datos!R24/1000 -> 3.65 | C19: =datos!MA24 -> 20.16 | D19: =datos!AI24 -> 11.71 | E19: =datos!MP24 -> 38.56 | F19: =(datos!AD24/1000)/PP!$F$2 -> 3.1838151 | G19: =datos!MH24 -> 37.53 | H19: =datos!BK24/$H$2 -> 72.654265 | I19: =datos!NB24 -> 122.81 | J19: =datos!BR24/$J$2 -> 31.8 | K19: =datos!NE24 -> 108.92 | L19: =datos!BO24*$L$2 -> 17.013182 | M19: =datos!NA24 -> 39.68 | N19: =datos!BS24*$N$2 -> 28.35 | P19: =(datos!AG24/1000)/$P$2 -> 15 | Q19: =datos!MY24*$Q$2 -> 58.88 | R19: =datos!BN24 -> 5.15 | U19: =T19*S19 -> 0 | V19: =datos!NC24+U19 -> 19.13 | W19: =datos!AV24*W$4 -> 134.6803 | X19: =W19*X$4 -> 10.774424 | Y19: =Y20/(1+(datos!G25/datos!G24-1)) -> 4.7172461 | AC19: =datos!MJ24 -> 14 | AD19: =datos!BB24*AD$4 -> 129.15913 | AE19: =AD19*AE$4 -> 10.332731 | AF19: =Y19 -> 4.7172461 | AI19: =AVERAGE(datos!ML24,datos!MM24,datos!MN24,datos!MO24) -> 17.496667 | AK19: =A19 -> 42795 | AL19: =B19/C19 -> 0.18105159 | AM19: =D19/E19 -> 0.30368257 | AN19: =F19/G19 -> 0.084833869 | AO19: =H19/I19 -> 0.59159893 | AP19: =J19/K19 -> 0.2919574 | AQ19: =L19/M19 -> 0.42875962 | AS19: =P19/Q19 -> 0.25475543
A20: 42826 | B20: =datos!R25/1000 -> 3.45 | C20: =datos!MA25 -> 20.22 | D20: =datos!AI25 -> 11.03 | E20: =datos!MP25 -> 38.85 | F20: =(datos!AD25/1000)/PP!$F$2 -> 3.2257613 | G20: =datos!MH25 -> 38.19 | H20: =datos!BK25/$H$2 -> 75.537659 | I20: =datos!NB25 -> 123.99 | J20: =datos!BR25/$J$2 -> 31.883333 | K20: =datos!NE25 -> 110.93 | L20: =datos!BO25*$L$2 -> 14.771944 | M20: =datos!NA25 -> 37.3 | N20: =datos!BS25*$N$2 -> 27.972 | P20: =(datos!AG25/1000)/$P$2 -> 17.682353 | Q20: =datos!MY25*$Q$2 -> 59.62 | R20: =datos!BN25 -> 5.26 | U20: =T20*S20 -> 0 | V20: =datos!NC25+U20 -> 19.98 | W20: =datos!AV25*W$4 -> 146.14783 | X20: =W20*X$4 -> 11.691827 | Y20: =Y21/(1+(datos!G26/datos!G25-1)) -> 4.8461812 | AC20: =datos!MJ25 -> 14.67 | AD20: =datos!BB25*AD$4 -> 151.21372 | AE20: =AD20*AE$4 -> 12.097097 | AF20: =Y20 -> 4.8461812 | AI20: =AVERAGE(datos!ML25,datos!MM25,datos!MN25,datos!MO25) -> 18.156667 | AK20: =A20 -> 42826 | AL20: =B20/C20 -> 0.17062315 | AM20: =D20/E20 -> 0.28391248 | AN20: =F20/G20 -> 0.084466125 | AO20: =H20/I20 -> 0.6092238 | AP20: =J20/K20 -> 0.28741849 | AQ20: =L20/M20 -> 0.39603068 | AS20: =P20/Q20 -> 0.29658425
A21: 42856 | B21: =datos!R26/1000 -> 3.55 | C21: =datos!MA26 -> 20.47 | D21: =datos!AI26 -> 11.21 | E21: =datos!MP26 -> 39.75 | F21: =(datos!AD26/1000)/PP!$F$2 -> 3.1211476 | G21: =datos!MH26 -> 38.24 | H21: =datos!BK26/$H$2 -> 74.267241 | I21: =datos!NB26 -> 125.2 | J21: =datos!BR26/$J$2 -> 31.783333 | K21: =datos!NE26 -> 112.22 | L21: =datos!BO26*$L$2 -> 12.801667 | M21: =datos!NA26 -> 35.75 | N21: =datos!BS26*$N$2 -> 27.972 | P21: =(datos!AG26/1000)/$P$2 -> 17.682353 | Q21: =datos!MY26*$Q$2 -> 60.48 | R21: =datos!BN26 -> 5.41 | U21: =T21*S21 -> 0 | V21: =datos!NC26+U21 -> 20.36 | W21: =datos!AV26*W$4 -> 144.84677 | X21: =W21*X$4 -> 11.587742 | Y21: =Y22/(1+(datos!G27/datos!G26-1)) -> 4.9128717 | AC21: =datos!MJ26 -> 14.78 | AD21: =datos!BB26*AD$4 -> 145.50905 | AE21: =AD21*AE$4 -> 11.640724 | AF21: =Y21 -> 4.9128717 | AI21: =AVERAGE(datos!ML26,datos!MM26,datos!MN26,datos!MO26) -> 17.763333 | AK21: =A21 -> 42856 | AL21: =B21/C21 -> 0.17342452 | AM21: =D21/E21 -> 0.28201258 | AN21: =F21/G21 -> 0.081619969 | AO21: =H21/I21 -> 0.59318883 | AP21: =J21/K21 -> 0.28322343 | AQ21: =L21/M21 -> 0.35808858 | AS21: =P21/Q21 -> 0.29236695
A22: 42887 | B22: =datos!R27/1000 -> 3.7 | C22: =datos!MA27 -> 20.96 | D22: =datos!AI27 -> 12.12 | E22: =datos!MP27 -> 39.84 | F22: =(datos!AD27/1000)/PP!$F$2 -> 3.3165579 | G22: =datos!MH27 -> 38.64 | H22: =datos!BK27/$H$2 -> 76.374773 | I22: =datos!NB27 -> 125.47 | J22: =datos!BR27/$J$2 -> 31.483333 | K22: =datos!NE27 -> 111.16 | L22: =datos!BO27*$L$2 -> 12.345 | M22: =datos!NA27 -> 34.5 | N22: =datos!BS27*$N$2 -> 29.484 | P22: =(datos!AG27/1000)/$P$2 -> 17.682353 | Q22: =datos!MY27*$Q$2 -> 61.46 | R22: =datos!BN27 -> 5.51 | U22: =T22*S22 -> 0 | V22: =datos!NC27+U22 -> 20.96 | W22: =datos!AV27*W$4 -> 131.49971 | X22: =W22*X$4 -> 10.519977 | Y22: =Y23/(1+(datos!G28/datos!G27-1)) -> 4.9706702 | AC22: =datos!MJ27 -> 13.9 | AD22: =datos!BB27*AD$4 -> 152.07216 | AE22: =AD22*AE$4 -> 12.165773 | AF22: =Y22 -> 4.9706702 | AI22: =AVERAGE(datos!ML27,datos!MM27,datos!MN27,datos!MO27) -> 18.17 | AK22: =A22 -> 42887 | AL22: =B22/C22 -> 0.17652672 | AM22: =D22/E22 -> 0.30421687 | AN22: =F22/G22 -> 0.085832245 | AO22: =H22/I22 -> 0.60870944 | AP22: =J22/K22 -> 0.28322538 | AQ22: =L22/M22 -> 0.35782609 | AS22: =P22/Q22 -> 0.28770506
A23: 42917 | B23: =datos!R28/1000 -> 3.7 | C23: =datos!MA28 -> 21.08 | D23: =datos!AI28 -> 11.32 | E23: =datos!MP28 -> 41.25 | F23: =(datos!AD28/1000)/PP!$F$2 -> 3.7306446 | G23: =datos!MH28 -> 39.12 | H23: =datos!BK28/$H$2 -> 76.0549 | I23: =datos!NB28 -> 125.1 | J23: =datos!BR28/$J$2 -> 31 | K23: =datos!NE28 -> 111.4 | L23: =datos!BO28*$L$2 -> 14.585 | M23: =datos!NA28 -> 35.73 | N23: =datos!BS28*$N$2 -> 29.484 | P23: =(datos!AG28/1000)/$P$2 -> 17.682353 | Q23: =datos!MY28*$Q$2 -> 62.66 | R23: =datos!BN28 -> 5.56 | U23: =T23*S23 -> 0 | V23: =datos!NC28+U23 -> 21.53 | W23: =datos!AV28*W$4 -> 147.14768 | X23: =W23*X$4 -> 11.771814 | Y23: =Y24/(1+(datos!G29/datos!G28-1)) -> 5.059591 | AC23: =datos!MJ28 -> 14.48 | AD23: =datos!BB28*AD$4 -> 130.52585 | AE23: =AD23*AE$4 -> 10.442068 | AF23: =Y23 -> 5.059591 | AI23: =AVERAGE(datos!ML28,datos!MM28,datos!MN28,datos!MO28) -> 16.59 | AK23: =A23 -> 42917 | AL23: =B23/C23 -> 0.17552182 | AM23: =D23/E23 -> 0.27442424 | AN23: =F23/G23 -> 0.095364127 | AO23: =H23/I23 -> 0.60795284 | AP23: =J23/K23 -> 0.27827648 | AQ23: =L23/M23 -> 0.40820039 | AS23: =P23/Q23 -> 0.28219523
A24: 42948 | B24: =datos!R29/1000 -> 4.05 | C24: =datos!MA29 -> 21.25 | D24: =datos!AI29 -> 12.02 | E24: =datos!MP29 -> 42.09 | F24: =(datos!AD29/1000)/PP!$F$2 -> 3.605181 | G24: =datos!MH29 -> 39.43 | H24: =datos!BK29/$H$2 -> 78.557169 | I24: =datos!NB29 -> 125.3 | J24: =datos!BR29/$J$2 -> 31.65 | K24: =datos!NE29 -> 109.56 | L24: =datos!BO29*$L$2 -> 15.861364 | M24: =datos!NA29 -> 36.36 | N24: =datos!BS29*$N$2 -> 29.484 | P24: =(datos!AG29/1000)/$P$2 -> 17.682353 | Q24: =datos!MY29*$Q$2 -> 63 | R24: =datos!BN29 -> 5.61 | U24: =T24*S24 -> 0 | V24: =datos!NC29+U24 -> 21.72 | W24: =datos!AV29*W$4 -> 152.35318 | X24: =W24*X$4 -> 12.188255 | Y24: =Y25/(1+(datos!G30/datos!G29-1)) -> 5.1307276 | AC24: =datos!MJ29 -> 14.35 | AD24: =datos!BB29*AD$4 -> 162.29459 | AE24: =AD24*AE$4 -> 12.983567 | AF24: =Y24 -> 5.1307276 | AI24: =AVERAGE(datos!ML29,datos!MM29,datos!MN29,datos!MO29) -> 20.32 | AK24: =A24 -> 42948 | AL24: =B24/C24 -> 0.19058824 | AM24: =D24/E24 -> 0.28557852 | AN24: =F24/G24 -> 0.091432437 | AO24: =H24/I24 -> 0.62695266 | AP24: =J24/K24 -> 0.2888828 | AQ24: =L24/M24 -> 0.43623112 | AS24: =P24/Q24 -> 0.28067227
A25: 42979 | B25: =datos!R30/1000 -> 3.9 | C25: =datos!MA30 -> 21.49 | D25: =datos!AI30 -> 12.45 | E25: =datos!MP30 -> 42.39 | F25: =(datos!AD30/1000)/PP!$F$2 -> 3.5398046 | G25: =datos!MH30 -> 39.71 | H25: =datos!BK30/$H$2 -> 77.969601 | I25: =datos!NB30 -> 128.19 | J25: =datos!BR30/$J$2 -> 32.283333 | K25: =datos!NE30 -> 112.42 | L25: =datos!BO30*$L$2 -> 17.56 | M25: =datos!NA30 -> 38.85 | N25: =datos!BS30*$N$2 -> 29.484 | P25: =(datos!AG30/1000)/$P$2 -> 17.682353 | Q25: =datos!MY30*$Q$2 -> 64.4 | R25: =datos!BN30 -> 5.63 | U25: =T25*S25 -> 0 | V25: =datos!NC30+U25 -> 21.81 | W25: =datos!AV30*W$4 -> 143.45894 | X25: =W25*X$4 -> 11.476715 | Y25: =Y26/(1+(datos!G31/datos!G30-1)) -> 5.2285404 | AC25: =datos!MJ30 -> 14.37 | AD25: =datos!BB30*AD$4 -> 176.57862 | AE25: =AD25*AE$4 -> 14.12629 | AF25: =Y25 -> 5.2285404 | AI25: =AVERAGE(datos!ML30,datos!MM30,datos!MN30,datos!MO30) -> 22.333333 | AK25: =A25 -> 42979 | AL25: =B25/C25 -> 0.18147976 | AM25: =D25/E25 -> 0.29370134 | AN25: =F25/G25 -> 0.08914139 | AO25: =H25/I25 -> 0.60823466 | AP25: =J25/K25 -> 0.28716717 | AQ25: =L25/M25 -> 0.45199485 | AS25: =P25/Q25 -> 0.2745707
A26: 43009 | B26: =datos!R31/1000 -> 4.15 | C26: =datos!MA31 -> 21.74 | D26: =datos!AI31 -> 13.64 | E26: =datos!MP31 -> 43.55 | F26: =(datos!AD31/1000)/PP!$F$2 -> 3.693132 | G26: =datos!MH31 -> 39.89 | H26: =datos!BK31/$H$2 -> 77.030399 | I26: =datos!NB31 -> 128.69 | J26: =datos!BR31/$J$2 -> 33.033333 | K26: =datos!NE31 -> 112.46 | L26: =datos!BO31*$L$2 -> 16.018333 | M26: =datos!NA31 -> 38.84 | N26: =datos!BS31*$N$2 -> 32.886 | P26: =(datos!AG31/1000)/$P$2 -> 18.529412 | Q26: =datos!MY31*$Q$2 -> 65.48 | R26: =datos!BN31 -> 5.66 | U26: =T26*S26 -> 0 | V26: =datos!NC31+U26 -> 21.95 | W26: =datos!AV31*W$4 -> 132.86738 | X26: =W26*X$4 -> 10.629391 | Y26: =Y27/(1+(datos!G32/datos!G31-1)) -> 5.3085691 | AC26: =datos!MJ31 -> 15.34 | AD26: =datos!BB31*AD$4 -> 241.65008 | AE26: =AD26*AE$4 -> 19.332007 | AF26: =Y26 -> 5.3085691 | AI26: =AVERAGE(datos!ML31,datos!MM31,datos!MN31,datos!MO31) -> 24.31 | AK26: =A26 -> 43009 | AL26: =B26/C26 -> 0.19089236 | AM26: =D26/E26 -> 0.31320321 | AN26: =F26/G26 -> 0.092582903 | AO26: =H26/I26 -> 0.59857331 | AP26: =J26/K26 -> 0.29373407 | AQ26: =L26/M26 -> 0.41241847 | AS26: =P26/Q26 -> 0.28297819
A27: 43040 | B27: =datos!R32/1000 -> 4.1 | C27: =datos!MA32 -> 21.74 | D27: =datos!AI32 -> 14 | E27: =datos!MP32 -> 44.18 | F27: =(datos!AD32/1000)/PP!$F$2 -> 3.5836746 | G27: =datos!MH32 -> 40.24 | H27: =datos!BK32/$H$2 -> 76.424682 | I27: =datos!NB32 -> 133.37 | J27: =datos!BR32/$J$2 -> 34.7 | K27: =datos!NE32 -> 118.63 | L27: =datos!BO32*$L$2 -> 15.046667 | M27: =datos!NA32 -> 37.65 | N27: =datos!BS32*$N$2 -> 34.02 | P27: =(datos!AG32/1000)/$P$2 -> 18.529412 | Q27: =datos!MY32*$Q$2 -> 66.24 | R27: =datos!BN32 -> 5.69 | U27: =T27*S27 -> 0 | V27: =datos!NC32+U27 -> 22.63 | W27: =datos!AV32*W$4 -> 194.67296 | X27: =W27*X$4 -> 15.573837 | Y27: =Y28/(1+(datos!G33/datos!G32-1)) -> 5.3797057 | AC27: =datos!MJ32 -> 18.7 | AD27: =datos!BB32*AD$4 -> 216.51692 | AE27: =AD27*AE$4 -> 17.321353 | AF27: =Y27 -> 5.3797057 | AI27: =AVERAGE(datos!ML32,datos!MM32,datos!MN32,datos!MO32) -> 22.403333 | AK27: =A27 -> 43040 | AL27: =B27/C27 -> 0.18859246 | AM27: =D27/E27 -> 0.31688547 | AN27: =F27/G27 -> 0.089057519 | AO27: =H27/I27 -> 0.57302754 | AP27: =J27/K27 -> 0.29250611 | AQ27: =L27/M27 -> 0.39964586 | AS27: =P27/Q27 -> 0.27973146
A28: 43070 | B28: =datos!R33/1000 -> 4.15 | C28: =datos!MA33 -> 22.1 | D28: =datos!AI33 -> 12.61 | E28: =datos!MP33 -> 44.76 | F28: =(datos!AD33/1000)/PP!$F$2 -> 3.6574236 | G28: =datos!MH33 -> 40.55 | H28: =datos!BK33/$H$2 -> 75.510436 | I28: =datos!NB33 -> 135.44 | J28: =datos!BR33/$J$2 -> 35.666667 | K28: =datos!NE33 -> 122.71 | L28: =datos!BO33*$L$2 -> 17.802105 | M28: =datos!NA33 -> 38.88 | N28: =datos!BS33*$N$2 -> 34.02 | P28: =(datos!AG33/1000)/$P$2 -> 18.529412 | Q28: =datos!MY33*$Q$2 -> 68.1 | R28: =datos!BN33 -> 5.71 | U28: =T28*S28 -> 0 | V28: =datos!NC33+U28 -> 22.8 | W28: =datos!AV33*W$4 -> 155.46448 | X28: =W28*X$4 -> 12.437158 | Y28: =Y29/(1+(datos!G34/datos!G33-1)) -> 5.5486551 | AC28: =datos!MJ33 -> 18.65 | AD28: =datos!BB33*AD$4 -> 165.75331 | AE28: =AD28*AE$4 -> 13.260265 | AF28: =Y28 -> 5.5486551 | AI28: =AVERAGE(datos!ML33,datos!MM33,datos!MN33,datos!MO33) -> 19.413333 | AK28: =A28 -> 43070 | AL28: =B28/C28 -> 0.18778281 | AM28: =D28/E28 -> 0.28172475 | AN28: =F28/G28 -> 0.090195402 | AO28: =H28/I28 -> 0.55751946 | AP28: =J28/K28 -> 0.29065819 | AQ28: =L28/M28 -> 0.45787308 | AS28: =P28/Q28 -> 0.27209122
A29: 43101 | B29: =datos!R34/1000 -> 3.95 | C29: =datos!MA34 -> 22.81 | D29: =datos!AI34 -> 12.1 | E29: =datos!MP34 -> 44.97 | F29: =(datos!AD34/1000)/PP!$F$2 -> 3.9406711 | G29: =datos!MH34 -> 41.29 | H29: =datos!BK34/$H$2 -> 75 | I29: =datos!NB34 -> 137.65 | J29: =datos!BR34/$J$2 -> 37.1 | K29: =datos!NE34 -> 126.03 | L29: =datos!BO34*$L$2 -> 18.915909 | M29: =datos!NA34 -> 40.27 | N29: =datos!BS34*$N$2 -> 37.8 | P29: =(datos!AG34/1000)/$P$2 -> 18.529412 | Q29: =datos!MY34*$Q$2 -> 70.28 | R29: =datos!BN34 -> 5.72 | U29: =T29*S29 -> 0 | V29: =datos!NC34+U29 -> 22.98 | W29: =datos!AV34*W$4 -> 163.03891 | X29: =W29*X$4 -> 13.043113 | Y29: =Y30/(1+(datos!G35/datos!G34-1)) -> 5.646468 | AC29: =datos!MJ34 -> 17.64 | AD29: =datos!BB34*AD$4 -> 205.54763 | AE29: =AD29*AE$4 -> 16.443811 | AF29: =Y29 -> 5.646468 | AI29: =AVERAGE(datos!ML34,datos!MM34,datos!MN34,datos!MO34) -> 22.646667 | AK29: =A29 -> 43101 | AL29: =B29/C29 -> 0.17316966 | AM29: =D29/E29 -> 0.26906827 | AN29: =F29/G29 -> 0.095438874 | AO29: =H29/I29 -> 0.54486015 | AP29: =J29/K29 -> 0.29437436 | AQ29: =L29/M29 -> 0.46972707 | AS29: =P29/Q29 -> 0.26365128
A30: 43132 | B30: =datos!R35/1000 -> 4.15 | C30: =datos!MA35 -> 23.22 | D30: =datos!AI35 -> 11.52 | E30: =datos!MP35 -> 45.41 | F30: =(datos!AD35/1000)/PP!$F$2 -> 4.4386692 | G30: =datos!MH35 -> 42.62 | H30: =datos!BK35/$H$2 -> 82.58167 | I30: =datos!NB35 -> 139.77 | J30: =datos!BR35/$J$2 -> 38.583333 | K30: =datos!NE35 -> 124.41 | L30: =datos!BO35*$L$2 -> 22.765556 | M30: =datos!NA35 -> 45.22 | N30: =datos!BS35*$N$2 -> 37.8 | P30: =(datos!AG35/1000)/$P$2 -> 18.529412 | Q30: =datos!MY35*$Q$2 -> 71.32 | R30: =datos!BN35 -> 5.76 | U30: =T30*S30 -> 0 | V30: =datos!NC35+U30 -> 23.08 | W30: =datos!AV35*W$4 -> 144.51035 | X30: =W30*X$4 -> 11.560828 | Y30: =Y31/(1+(datos!G36/datos!G35-1)) -> 5.7842951 | AC30: =datos!MJ35 -> 16.64 | AD30: =datos!BB35*AD$4 -> 145.52417 | AE30: =AD30*AE$4 -> 11.641934 | AF30: =Y30 -> 5.7842951 | AI30: =AVERAGE(datos!ML35,datos!MM35,datos!MN35,datos!MO35) -> 19.56 | AK30: =A30 -> 43132 | AL30: =B30/C30 -> 0.17872524 | AM30: =D30/E30 -> 0.25368861 | AN30: =F30/G30 -> 0.10414522 | AO30: =H30/I30 -> 0.59083973 | AP30: =J30/K30 -> 0.31013048 | AQ30: =L30/M30 -> 0.50343997 | AS30: =P30/Q30 -> 0.25980667
... A64: 44166 | B64: =datos!R69/1000 -> 24.6 | C64: =datos!MA69 -> 81.76 | D64: =datos!AI69 -> 20.3876 | E64: =datos!MP69 -> 75.18 | F64: =(datos!AD69/1000)/PP!$F$2 -> 23.458509 | G64: =datos!MH69 -> 140.13 | H64: =datos!BK69/$H$2 -> 343.4755 | I64: =datos!NB69 -> 560.97 | J64: =datos!BR69/$J$2 -> 164.56667 | K64: =datos!NE69 -> 408.2 | L64: =datos!BO69*$L$2 -> 81.07575 | M64: =datos!NA69 -> 157.42 | N64: =datos!BS69*$N$2 -> 117.18 | P64: =(datos!AG69/1000)/$P$2 -> 71.735294 | Q64: =datos!MY69*$Q$2 -> 285.74 | R64: =datos!BN69 -> 21.36 | U64: =T64*S64 -> 0 | V64: =datos!NC69+U64 -> 57.3 | W64: =datos!AV69*W$4 -> 600.37113 | X64: =W64*X$4 -> 48.029691 | Y64: =Y65/(1+(datos!G70/datos!G69-1)) -> 17.15726 | AC64: =datos!MJ69 -> 61.1 | AD64: =datos!BB69*AD$4 -> 556.94109 | AE64: =AD64*AE$4 -> 44.555287 | AF64: =Y64 -> 17.15726 | AI64: =AVERAGE(datos!ML69,datos!MM69,datos!MN69,datos!MO69) -> 70.04 | AK64: =A64 -> 44166 | AL64: =B64/C64 -> 0.30088063 | AM64: =D64/E64 -> 0.27118383 | AN64: =F64/G64 -> 0.16740533 | AO64: =H64/I64 -> 0.61228853 | AP64: =J64/K64 -> 0.40315205 | AQ64: =L64/M64 -> 0.51502827 | AS64: =P64/Q64 -> 0.25105093
A65: 44197 | B65: =datos!R70/1000 -> 25.5 | C65: =datos!MA70 -> 81.53 | D65: =datos!AI70 -> 22.5093 | E65: =datos!MP70 -> 79.48 | F65: =(datos!AD70/1000)/PP!$F$2 -> 25.861886 | G65: =datos!MH70 -> 145.61 | H65: =datos!BK70/$H$2 -> 350.82804 | I65: =datos!NB70 -> 604.07 | J65: =datos!BR70/$J$2 -> 167.4 | K65: =datos!NE70 -> 413.35 | L65: =datos!BO70*$L$2 -> 83.67275 | M65: =datos!NA70 -> 163.48 | N65: =datos!BS70*$N$2 -> 113.4 | P65: =(datos!AG70/1000)/$P$2 -> 71.735294 | Q65: =datos!MY70*$Q$2 -> 293.58 | R65: =datos!BN70 -> 22.74 | S65: 0.0357 | T65: 334.38 | U65: =T65*S65 -> 11.937366 | V65: =datos!NC70+U65 -> 69.937366 | W65: =datos!AV70*W$4 -> 570.83333 | X65: =W65*X$4 -> 45.666667 | Y65: =Y66/(1+(datos!G71/datos!G70-1)) -> 17.850842 | AC65: =datos!MJ70 -> 59.7 | AD65: =datos!BB70*AD$4 -> 510.95386 | AE65: =AD65*AE$4 -> 40.876309 | AF65: =Y65 -> 17.850842 | AI65: =AVERAGE(datos!ML70,datos!MM70,datos!MN70,datos!MO70) -> 63.983333 | AK65: =A65 -> 44197 | AL65: =B65/C65 -> 0.31276831 | AM65: =D65/E65 -> 0.2832071 | AN65: =F65/G65 -> 0.17761065 | AO65: =H65/I65 -> 0.58077382 | AP65: =J65/K65 -> 0.40498367 | AQ65: =L65/M65 -> 0.51182255 | AS65: =P65/Q65 -> 0.24434667 | AT65: =R65/V65 -> 0.32514808
A66: 44228 | B66: =datos!R71/1000 -> 25.5 | C66: =datos!MA71 -> 81.61 | D66: =datos!AI71 -> 23.1596 | E66: =datos!MP71 -> 86.54 | F66: =(datos!AD71/1000)/PP!$F$2 -> 23.008208 | G66: =datos!MH71 -> 151.12 | H66: =datos!BK71/$H$2 -> 373.30762 | I66: =datos!NB71 -> 594.06 | J66: =datos!BR71/$J$2 -> 200.11667 | K66: =datos!NE71 -> 420.47 | L66: =datos!BO71*$L$2 -> 84.834167 | M66: =datos!NA71 -> 172.75 | N66: =datos!BS71*$N$2 -> 117.18 | P66: =(datos!AG71/1000)/$P$2 -> 71.735294 | Q66: =datos!MY71*$Q$2 -> 311.42 | R66: =datos!BN71 -> 24.2 | S66: 0.0362 | T66: 349.43 | U66: =T66*S66 -> 12.649366 | V66: =datos!NC71+U66 -> 74.699366 | W66: =datos!AV71*W$4 -> 492.98276 | X66: =W66*X$4 -> 39.438621 | Y66: =Y67/(1+(datos!G72/datos!G71-1)) -> 18.48927 | AC66: =datos!MJ71 -> 59.67 | AD66: =datos!BB71*AD$4 -> 546.4942 | AE66: =AD66*AE$4 -> 43.719536 | AF66: =Y66 -> 18.48927 | AI66: =AVERAGE(datos!ML71,datos!MM71,datos!MN71,datos!MO71) -> 69.31 | AK66: =A66 -> 44228 | AL66: =B66/C66 -> 0.31246171 | AM66: =D66/E66 -> 0.26761729 | AN66: =F66/G66 -> 0.15225124 | AO66: =H66/I66 -> 0.62840054 | AP66: =J66/K66 -> 0.47593566 | AQ66: =L66/M66 -> 0.49108056 | AS66: =P66/Q66 -> 0.23034903 | AT66: =R66/V66 -> 0.32396527
A67: 44256 | B67: =datos!R72/1000 -> 25.1 | C67: =datos!MA72 -> 84.36 | D67: =datos!AI72 -> 29.86 | E67: =datos!MP72 -> 91.23 | F67: =(datos!AD72/1000)/PP!$F$2 -> 22.768101 | G67: =datos!MH72 -> 157.27 | H67: =datos!BK72/$H$2 -> 393.44601 | I67: =datos!NB72 -> 615.87 | J67: =datos!BR72/$J$2 -> 200.3 | K67: =datos!NE72 -> 424.23 | L67: =datos!BO72*$L$2 -> 82.9825 | M67: =datos!NA72 -> 173.95 | N67: =datos!BS72*$N$2 -> 113.4 | P67: =(datos!AG72/1000)/$P$2 -> 71.735294 | Q67: =datos!MY72*$Q$2 -> 320.76 | R67: =datos!BN72 -> 26.09 | S67: 0.037 | T67: 370 | U67: =T67*S67 -> 13.69 | V67: =datos!NC72+U67 -> 83.21 | W67: =datos!AV72*W$4 -> 407.06122 | X67: =W67*X$4 -> 32.564898 | Y67: =Y68/(1+(datos!G73/datos!G72-1)) -> 19.378754 | AC67: =datos!MJ72 -> 55.86 | AD67: =datos!BB72*AD$4 -> 601.78767 | AE67: =AD67*AE$4 -> 48.143014 | AF67: =Y67 -> 19.378754 | AI67: =AVERAGE(datos!ML72,datos!MM72,datos!MN72,datos!MO72) -> 76.326667 | AK67: =A67 -> 44256 | AL67: =B67/C67 -> 0.29753438 | AM67: =D67/E67 -> 0.32730461 | AN67: =F67/G67 -> 0.14477078 | AO67: =H67/I67 -> 0.63884587 | AP67: =J67/K67 -> 0.47214954 | AQ67: =L67/M67 -> 0.477048 | AS67: =P67/Q67 -> 0.22364165 | AT67: =R67/V67 -> 0.31354405
A68: 44287 | B68: =datos!R73/1000 -> 24.7 | C68: =datos!MA73 -> 96.38 | D68: =datos!AI73 -> 34.96 | E68: =datos!MP73 -> 107.54 | F68: =(datos!AD73/1000)/PP!$F$2 -> 24.162651 | G68: =datos!MH73 -> 164.72 | H68: =datos!BK73/$H$2 -> 418.58439 | I68: =datos!NB73 -> 636.55 | J68: =datos!BR73/$J$2 -> 200.06667 | K68: =datos!NE73 -> 446.36 | L68: =datos!BO73*$L$2 -> 87.15 | M68: =datos!NA73 -> 174.14 | N68: =datos!BS73*$N$2 -> 113.4 | P68: =(datos!AG73/1000)/$P$2 -> 71.735294 | Q68: =datos!MY73*$Q$2 -> 351.86 | R68: =datos!BN73 -> 28.17 | S68: 0.0377 | T68: 393.93 | U68: =T68*S68 -> 14.851161 | V68: =datos!NC73+U68 -> 91.201161 | W68: =datos!AV73*W$4 -> 411.09524 | X68: =W68*X$4 -> 32.887619 | Y68: =Y69/(1+(datos!G74/datos!G73-1)) -> 20.169464 | AC68: =datos!MJ73 -> 54.35 | AD68: =datos!BB73*AD$4 -> 501.80928 | AE68: =AD68*AE$4 -> 40.144743 | AF68: =Y68 -> 20.169464 | AI68: =AVERAGE(datos!ML73,datos!MM73,datos!MN73,datos!MO73) -> 70.386667 | AK68: =A68 -> 44287 | AL68: =B68/C68 -> 0.25627724 | AM68: =D68/E68 -> 0.32508834 | AN68: =F68/G68 -> 0.14668923 | AO68: =H68/I68 -> 0.6575829 | AP68: =J68/K68 -> 0.44821818 | AQ68: =L68/M68 -> 0.5004594 | AS68: =P68/Q68 -> 0.20387454 | AT68: =R68/V68 -> 0.30887765
A69: 44317 | B69: =datos!R74/1000 -> 25 | C69: =datos!MA74 -> 108.97 | D69: =datos!AI74 -> 37.87 | E69: =datos!MP74 -> 112.41 | F69: =(datos!AD74/1000)/PP!$F$2 -> 25.836033 | G69: =datos!MH74 -> 172.29 | H69: =datos!BK74/$H$2 -> 432.99909 | I69: =datos!NB74 -> 671.4 | J69: =datos!BR74/$J$2 -> 178.08333 | K69: =datos!NE74 -> 463.43 | L69: =datos!BO74*$L$2 -> 88.137 | M69: =datos!NA74 -> 177.13 | N69: =datos!BS74*$N$2 -> 132.3 | P69: =(datos!AG74/1000)/$P$2 -> 87.352941 | Q69: =datos!MY74*$Q$2 -> 368.5 | R69: =datos!BN74 -> 29.77 | S69: 0.0382 | T69: 410.37 | U69: =T69*S69 -> 15.676134 | V69: =datos!NC74+U69 -> 92.886134 | W69: =datos!AV74*W$4 -> 402.075 | X69: =W69*X$4 -> 32.166 | Y69: =Y70/(1+(datos!G75/datos!G74-1)) -> 20.839691 | AC69: =datos!MJ74 -> 55.95 | AD69: =datos!BB74*AD$4 -> 632.6367 | AE69: =AD69*AE$4 -> 50.610936 | AF69: =Y69 -> 20.839691 | AI69: =AVERAGE(datos!ML74,datos!MM74,datos!MN74,datos!MO74) -> 78.77 | AK69: =A69 -> 44317 | AL69: =B69/C69 -> 0.22942094 | AM69: =D69/E69 -> 0.33689174 | AN69: =F69/G69 -> 0.14995666 | AO69: =H69/I69 -> 0.64491971 | AP69: =J69/K69 -> 0.38427235 | AQ69: =L69/M69 -> 0.4975837 | AS69: =P69/Q69 -> 0.23705004 | AT69: =R69/V69 -> 0.32049994
A70: 44348 | B70: =datos!R75/1000 -> 25.5 | C70: =datos!MA75 -> 111.68 | D70: =datos!AI75 -> 37.6177 | E70: =datos!MP75 -> 121.42 | F70: =(datos!AD75/1000)/PP!$F$2 -> 24.6939 | G70: =datos!MH75 -> 182.91 | H70: =datos!BK75/$H$2 -> 435.09755 | I70: =datos!NB75 -> 701.91 | J70: =datos!BR75/$J$2 -> 178.88333 | K70: =datos!NE75 -> 455.11 | L70: =datos!BO75*$L$2 -> 94.15 | M70: =datos!NA75 -> 182.8 | N70: =datos!BS75*$N$2 -> 143.64 | P70: =(datos!AG75/1000)/$P$2 -> 87.352941 | Q70: =datos!MY75*$Q$2 -> 380.06 | R70: =datos!BN75 -> 31.32 | S70: 0.0381 | T70: 432.23 | U70: =T70*S70 -> 16.467963 | V70: =datos!NC75+U70 -> 100.56796 | W70: =datos!AV75*W$4 -> 387.96296 | X70: =W70*X$4 -> 31.037037 | Y70: =Y71/(1+(datos!G76/datos!G75-1)) -> 21.501257 | AC70: =datos!MJ75 -> 53.33 | AD70: =datos!BB75*AD$4 -> 525.02368 | AE70: =AD70*AE$4 -> 42.001895 | AF70: =Y70 -> 21.501257 | AI70: =AVERAGE(datos!ML75,datos!MM75,datos!MN75,datos!MO75) -> 73.103333 | AK70: =A70 -> 44348 | AL70: =B70/C70 -> 0.22833095 | AM70: =D70/E70 -> 0.30981469 | AN70: =F70/G70 -> 0.13500574 | AO70: =H70/I70 -> 0.61987655 | AP70: =J70/K70 -> 0.39305516 | AQ70: =L70/M70 -> 0.51504376 | AS70: =P70/Q70 -> 0.22983987 | AT70: =R70/V70 -> 0.31143119
A71: 44378 | B71: =datos!R76/1000 -> 25.1 | C71: =datos!MA76 -> 111.74 | D71: =datos!AI76 -> 39.52 | E71: =datos!MP76 -> 138.99 | F71: =(datos!AD76/1000)/PP!$F$2 -> 24.545002 | G71: =datos!MH76 -> 185.12 | H71: =datos!BK76/$H$2 -> 416.84664 | I71: =datos!NB76 -> 695.22 | J71: =datos!BR76/$J$2 -> 181.65 | K71: =datos!NE76 -> 455.4 | L71: =datos!BO76*$L$2 -> 92.75 | M71: =datos!NA76 -> 190.07 | N71: =datos!BS76*$N$2 -> 141.75 | P71: =(datos!AG76/1000)/$P$2 -> 87.352941 | Q71: =datos!MY76*$Q$2 -> 406.76 | R71: =datos!BN76 -> 32.15 | S71: 0.0379 | T71: 446.65 | U71: =T71*S71 -> 16.928035 | V71: =datos!NC76+U71 -> 101.84804 | W71: =datos!AV76*W$4 -> 386.88158 | X71: =W71*X$4 -> 30.950526 | Y71: =Y72/(1+(datos!G77/datos!G76-1)) -> 22.145656 | AC71: =datos!MJ76 -> 52.36 | AD71: =datos!BB76*AD$4 -> 745.86577 | AE71: =AD71*AE$4 -> 59.669261 | AF71: =Y71 -> 22.145656 | AI71: =AVERAGE(datos!ML76,datos!MM76,datos!MN76,datos!MO76) -> 91.243333 | AK71: =A71 -> 44378 | AL71: =B71/C71 -> 0.2246286 | AM71: =D71/E71 -> 0.284337 | AN71: =F71/G71 -> 0.13258968 | AO71: =H71/I71 -> 0.59958954 | AP71: =J71/K71 -> 0.39888011 | AQ71: =L71/M71 -> 0.48797811 | AS71: =P71/Q71 -> 0.21475303 | AT71: =R71/V71 -> 0.31566637
A72: 44409 | B72: =datos!R77/1000 -> 25.16 | C72: =datos!MA77 -> 117.36 | D72: =datos!AI77 -> 39.1675 | E72: =datos!MP77 -> 145.95 | F72: =(datos!AD77/1000)/PP!$F$2 -> 27.731512 | G72: =datos!MH77 -> 188.62 | H72: =datos!BK77/$H$2 -> 421.51089 | I72: =datos!NB77 -> 675.43 | J72: =datos!BR77/$J$2 -> 192.03333 | K72: =datos!NE77 -> 460.12 | L72: =datos!BO77*$L$2 -> 95.256 | M72: =datos!NA77 -> 188.8 | N72: =datos!BS77*$N$2 -> 143.64 | O72: =datos!ND77 -> 849 | P72: =(datos!AG77/1000)/$P$2 -> 87.352941 | Q72: =datos!MY77*$Q$2 -> 422.12 | R72: =datos!BN77 -> 32.51 | S72: 0.0375 | T72: 456.42 | U72: =T72*S72 -> 17.11575 | V72: =datos!NC77+U72 -> 103.81575 | W72: =datos!AV77*W$4 -> 380.55952 | X72: =W72*X$4 -> 30.444762 | Y72: =Y73/(1+(datos!G78/datos!G77-1)) -> 22.692319 | AC72: =datos!MJ77 -> 50.19 | AD72: =datos!BB77*AD$4 -> 638.36904 | AE72: =AD72*AE$4 -> 51.069523 | AF72: =Y72 -> 22.692319 | AI72: =AVERAGE(datos!ML77,datos!MM77,datos!MN77,datos!MO77) -> 84.99 | AK72: =A72 -> 44409 | AL72: =B72/C72 -> 0.21438309 | AM72: =D72/E72 -> 0.26836245 | AN72: =F72/G72 -> 0.14702318 | AO72: =H72/I72 -> 0.62406303 | AP72: =J72/K72 -> 0.41735489 | AQ72: =L72/M72 -> 0.5045339 | AR72: =N72/O72 -> 0.16918728 | AS72: =P72/Q72 -> 0.20693865 | AT72: =R72/V72 -> 0.31315094
A73: 44440 | B73: =datos!R78/1000 -> 25.33 | C73: =datos!MA78 -> 115.14 | D73: =datos!AI78 -> 37.142 | E73: =datos!MP78 -> 151.17 | F73: =(datos!AD78/1000)/PP!$F$2 -> 29.325576 | G73: =datos!MH78 -> 190.09 | H73: =datos!BK78/$H$2 -> 427.59982 | I73: =datos!NB78 -> 672.89 | J73: =datos!BR78/$J$2 -> 212.51667 | K73: =datos!NE78 -> 494.21 | L73: =datos!BO78*$L$2 -> 101.542 | M73: =datos!NA78 -> 199.69 | N73: =datos!BS78*$N$2 -> 154.98 | O73: =datos!ND78 -> 919 | P73: =(datos!AG78/1000)/$P$2 -> 87.352941 | Q73: =datos!MY78*$Q$2 -> 423.62 | R73: =datos!BN78 -> 33.03 | S73: 0.0369 | T73: 469.01 | U73: =T73*S73 -> 17.306469 | V73: =datos!NC78+U73 -> 111.03647 | W73: =datos!AV78*W$4 -> 417.16832 | X73: =W73*X$4 -> 33.373465 | Y73: =Y74/(1+(datos!G79/datos!G78-1)) -> 23.497167 | AC73: =datos!MJ78 -> 51.18 | AD73: =datos!BB78*AD$4 -> 729.5207 | AE73: =AD73*AE$4 -> 58.361656 | AF73: =Y73 -> 23.497167 | AI73: =AVERAGE(datos!ML78,datos!MM78,datos!MN78,datos!MO78) -> 99.95 | AK73: =A73 -> 44440 | AL73: =B73/C73 -> 0.21999305 | AM73: =D73/E73 -> 0.2456969 | AN73: =F73/G73 -> 0.15427206 | AO73: =H73/I73 -> 0.63546764 | AP73: =J73/K73 -> 0.43001288 | AQ73: =L73/M73 -> 0.50849817 | AR73: =N73/O73 -> 0.16863983 | AS73: =P73/Q73 -> 0.20620589 | AT73: =R73/V73 -> 0.29746983
A74: 44470 | B74: =datos!R79/1000 -> 25.5 | C74: =datos!MA79 -> 116.74 | D74: =datos!AI79 -> 40.87 | E74: =datos!MP79 -> 151.76 | F74: =(datos!AD79/1000)/PP!$F$2 -> 30.321032 | G74: =datos!MH79 -> 197.99 | H74: =datos!BK79/$H$2 -> 428.06942 | I74: =datos!NB79 -> 676.49 | J74: =datos!BR79/$J$2 -> 224.3 | K74: =datos!NE79 -> 521.54 | L74: =datos!BO79*$L$2 -> 105.749 | M74: =datos!NA79 -> 202.18 | N74: =datos!BS79*$N$2 -> 170.1 | O74: =datos!ND79 -> 989 | P74: =(datos!AG79/1000)/$P$2 -> 87.352941 | Q74: =datos!MY79*$Q$2 -> 434.7 | R74: =datos!BN79 -> 33.27 | S74: 0.0364 | T74: 476.21 | U74: =T74*S74 -> 17.334044 | V74: =datos!NC79+U74 -> 110.61404 | W74: =datos!AV79*W$4 -> 403.09091 | X74: =W74*X$4 -> 32.247273 | Y74: =Y75/(1+(datos!G80/datos!G79-1)) -> 24.324273 | AC74: =datos!MJ79 -> 52.86 | AD74: =datos!BB79*AD$4 -> 914.58131 | AE74: =AD74*AE$4 -> 73.166505 | AF74: =Y74 -> 24.324273 | AI74: =AVERAGE(datos!ML79,datos!MM79,datos!MN79,datos!MO79) -> 121.87 | AK74: =A74 -> 44470 | AL74: =B74/C74 -> 0.21843413 | AM74: =D74/E74 -> 0.2693068 | AN74: =F74/G74 -> 0.15314426 | AO74: =H74/I74 -> 0.63278011 | AP74: =J74/K74 -> 0.43007248 | AQ74: =L74/M74 -> 0.52304382 | AR74: =N74/O74 -> 0.17199191 | AS74: =P74/Q74 -> 0.20094995 | AT74: =R74/V74 -> 0.30077555
A75: 44501 | B75: =datos!R80/1000 -> 25.375 | C75: =datos!MA80 -> 114.43 | D75: =datos!AI80 -> 39.24 | E75: =datos!MP80 -> 156.12 | F75: =(datos!AD80/1000)/PP!$F$2 -> 31.304396 | G75: =datos!MH80 -> 204.32 | H75: =datos!BK80/$H$2 -> 512.14383 | I75: =datos!NB80 -> 786.63 | J75: =datos!BR80/$J$2 -> 237.7 | K75: =datos!NE80 -> 568.08 | L75: =datos!BO80*$L$2 -> 108.57 | M75: =datos!NA80 -> 210.04 | N75: =datos!BS80*$N$2 -> 170.1 | O75: =datos!ND80 -> 1019 | P75: =(datos!AG80/1000)/$P$2 -> 108.32353 | Q75: =datos!MY80*$Q$2 -> 433.2 | R75: =datos!BN80 -> 33.7 | S75: 0.0362 | T75: 486.41 | U75: =T75*S75 -> 17.608042 | V75: =datos!NC80+U75 -> 107.06804 | W75: =datos!AV80*W$4 -> 438.15385 | X75: =W75*X$4 -> 35.052308 | Y75: =Y76/(1+(datos!G81/datos!G80-1)) -> 24.937826 | AC75: =datos!MJ80 -> 55.84 | AD75: =datos!BB80*AD$4 -> 713.1631 | AE75: =AD75*AE$4 -> 57.053048 | AF75: =Y75 -> 24.937826 | AI75: =AVERAGE(datos!ML80,datos!MM80,datos!MN80,datos!MO80) -> 98.84 | AK75: =A75 -> 44501 | AL75: =B75/C75 -> 0.22175129 | AM75: =D75/E75 -> 0.25134512 | AN75: =F75/G75 -> 0.15321259 | AO75: =H75/I75 -> 0.65106064 | AP75: =J75/K75 -> 0.41842698 | AQ75: =L75/M75 -> 0.51690154 | AR75: =N75/O75 -> 0.16692836 | AS75: =P75/Q75 -> 0.25005432 | AT75: =R75/V75 -> 0.31475312
A76: 44531 | B76: =datos!R81/1000 -> 25 | C76: =datos!MA81 -> 114.82 | D76: =datos!AI81 -> 34.8327 | E76: =datos!MP81 -> 163.25 | F76: =(datos!AD81/1000)/PP!$F$2 -> 31.102984 | G76: =datos!MH81 -> 207.97 | H76: =datos!BK81/$H$2 -> 537.44555 | I76: =datos!NB81 -> 870.68 | J76: =datos!BR81/$J$2 -> 248.05 | K76: =datos!NE81 -> 593.57 | L76: =datos!BO81*$L$2 -> 116.41 | M76: =datos!NA81 -> 215.43 | N76: =datos!BS81*$N$2 -> 173.88 | O76: =datos!ND81 -> 1019 | P76: =(datos!AG81/1000)/$P$2 -> 108.32353 | Q76: =datos!MY81*$Q$2 -> 433.56 | R76: =datos!BN81 -> 34.35 | S76: 0.0359 | T76: 500.69 | U76: =T76*S76 -> 17.974771 | V76: =datos!NC81+U76 -> 108.26477 | W76: =datos!AV81*W$4 -> 371.81356 | X76: =W76*X$4 -> 29.745085 | Y76: =Y77/(1+(datos!G82/datos!G81-1)) -> 25.89817 | AC76: =datos!MJ81 -> 53.71 | AD76: =datos!BB81*AD$4 -> 589.80628 | AE76: =AD76*AE$4 -> 47.184502 | AF76: =Y76 -> 25.89817 | AI76: =AVERAGE(datos!ML81,datos!MM81,datos!MN81,datos!MO81) -> 88.523333 | AK76: =A76 -> 44531 | AL76: =B76/C76 -> 0.2177321 | AM76: =D76/E76 -> 0.21337029 | AN76: =F76/G76 -> 0.14955515 | AO76: =H76/I76 -> 0.61727105 | AP76: =J76/K76 -> 0.41789511 | AQ76: =L76/M76 -> 0.54036114 | AR76: =N76/O76 -> 0.17063788 | AS76: =P76/Q76 -> 0.24984669 | AT76: =R76/V76 -> 0.31727772
A77: 44562 | B77: =datos!R82/1000 -> 24 | C77: =datos!MA82 -> 120.6 | D77: =datos!AI82 -> 44.58 | E77: =datos!MP82 -> 167.31 | F77: =(datos!AD82/1000)/PP!$F$2 -> 31.985758 | G77: =datos!MH82 -> 209.92 | H77: =datos!BK82/$H$2 -> 533.17377 | I77: =datos!NB82 -> 898.19 | J77: =datos!BR82/$J$2 -> 258.33333 | K77: =datos!NE82 -> 611 | L77: =datos!BO82*$L$2 -> 108.92 | M77: =datos!NA82 -> 225.9 | N77: =datos!BS82*$N$2 -> 173.88 | O77: =datos!ND82 -> 1019 | P77: =(datos!AG82/1000)/$P$2 -> 108.32353 | Q77: =datos!MY82*$Q$2 -> 450.36 | R77: =datos!BN82 -> 35.82 | S77: 0.0359 | T77: 522.73 | U77: =T77*S77 -> 18.766007 | V77: =datos!NC82+U77 -> 109.98601 | W77: =datos!AV82*W$4 -> 478.10959 | X77: =W77*X$4 -> 38.248767 | Y77: =Y78/(1+(datos!G83/datos!G82-1)) -> 26.898529 | AC77: =datos!MJ82 -> 61.33 | AD77: =datos!BB82*AD$4 -> 933.65465 | AE77: =AD77*AE$4 -> 74.692372 | AF77: =Y77 -> 26.898529 | AI77: =AVERAGE(datos!ML82,datos!MM82,datos!MN82,datos!MO82) -> 120.29667 | AK77: =A77 -> 44562 | AL77: =B77/C77 -> 0.19900498 | AM77: =D77/E77 -> 0.2664515 | AN77: =F77/G77 -> 0.15237118 | AO77: =H77/I77 -> 0.59360912 | AP77: =J77/K77 -> 0.42280415 | AQ77: =L77/M77 -> 0.48216025 | AR77: =N77/O77 -> 0.17063788 | AS77: =P77/Q77 -> 0.24052653 | AT77: =R77/V77 -> 0.32567779
A78: 44593 | B78: =datos!R83/1000 -> 23.5 | C78: =datos!MA83 -> 120.62 | D78: =datos!AI83 -> 46.28 | E78: =datos!MP83 -> 173.7 | F78: =(datos!AD83/1000)/PP!$F$2 -> 33.437943 | G78: =datos!MH83 -> 225.82 | H78: =datos!BK83/$H$2 -> 605.61025 | I78: =datos!NB83 -> 907.24 | J78: =datos!BR83/$J$2 -> 254 | K78: =datos!NE83 -> 612.61 | L78: =datos!BO83*$L$2 -> 122.43 | M78: =datos!NA83 -> 230.59 | N78: =datos!BS83*$N$2 -> 173.88 | O78: =datos!ND83 -> 1019 | P78: =(datos!AG83/1000)/$P$2 -> 108.32353 | Q78: =datos!MY83*$Q$2 -> 478.42 | R78: =datos!BN83 -> 37.69 | S78: 0.0365 | T78: 538.46 | U78: =T78*S78 -> 19.65379 | V78: =datos!NC83+U78 -> 115.09379 | W78: =datos!AV83*W$4 -> 517.23188 | X78: =W78*X$4 -> 41.378551 | Y78: =Y79/(1+(datos!G84/datos!G83-1)) -> 28.161203 | AC78: =datos!MJ83 -> 71.35 | AD78: =datos!BB83*AD$4 -> 1348.6202 | AE78: =AD78*AE$4 -> 107.88961 | AF78: =Y78 -> 28.161203 | AI78: =AVERAGE(datos!ML83,datos!MM83,datos!MN83,datos!MO83) -> 154.03667 | AK78: =A78 -> 44593 | AL78: =B78/C78 -> 0.19482673 | AM78: =D78/E78 -> 0.26643638 | AN78: =F78/G78 -> 0.14807344 | AO78: =H78/I78 -> 0.66753037 | AP78: =J78/K78 -> 0.41461942 | AQ78: =L78/M78 -> 0.53094237 | AR78: =N78/O78 -> 0.17063788 | AS78: =P78/Q78 -> 0.22641932 | AT78: =R78/V78 -> 0.32747206
A79: 44621 | B79: =datos!R84/1000 -> 24.95 | C79: =datos!MA84 -> 124.5 | D79: =datos!AI84 -> 51.574 | E79: =datos!MP84 -> 185.68 | F79: =(datos!AD84/1000)/PP!$F$2 -> 39.231537 | G79: =datos!MH84 -> 265.71 | H79: =datos!BK84/$H$2 -> 643.03539 | I79: =datos!NB84 -> 978.01 | J79: =datos!BR84/$J$2 -> 255.4 | K79: =datos!NE84 -> 641.21 | L79: =datos!BO84*$L$2 -> 139.58 | M79: =datos!NA84 -> 265.5 | N79: =datos!BS84*$N$2 -> 189 | O79: =datos!ND84 -> 1069 | P79: =(datos!AG84/1000)/$P$2 -> 108.32353 | Q79: =datos!MY84*$Q$2 -> 498.48 | R79: =datos!BN84 -> 40.42 | S79: 0.038 | T79: 561.17 | U79: =T79*S79 -> 21.32446 | V79: =datos!NC84+U79 -> 130.07446 | W79: =datos!AV84*W$4 -> 557.15517 | X79: =W79*X$4 -> 44.572414 | Y79: =Y80/(1+(datos!G85/datos!G84-1)) -> 30.059661 | AC79: =datos!MJ84 -> 67.24 | AD79: =datos!BB84*AD$4 -> 1249.3175 | AE79: =AD79*AE$4 -> 99.945401 | AF79: =Y79 -> 30.059661 | AI79: =AVERAGE(datos!ML84,datos!MM84,datos!MN84,datos!MO84) -> 141.20667 | AK79: =A79 -> 44621 | AL79: =B79/C79 -> 0.20040161 | AM79: =D79/E79 -> 0.27775743 | AN79: =F79/G79 -> 0.14764795 | AO79: =H79/I79 -> 0.65749368 | AP79: =J79/K79 -> 0.39830945 | AQ79: =L79/M79 -> 0.52572505 | AR79: =N79/O79 -> 0.17680075 | AS79: =P79/Q79 -> 0.21730767 | AT79: =R79/V79 -> 0.31074509
A80: 44652 | B80: =datos!R85/1000 -> 26.75 | C80: =datos!MA85 -> 127.08 | D80: =datos!AI85 -> 66.1185 | E80: =datos!MP85 -> 206.89 | F80: =(datos!AD85/1000)/PP!$F$2 -> 44.724589 | G80: =datos!MH85 -> 295.24 | H80: =datos!BK85/$H$2 -> 693.80445 | I80: =datos!NB85 -> 1049.47 | J80: =datos!BR85/$J$2 -> 265.43333 | K80: =datos!NE85 -> 689.83 | L80: =datos!BO85*$L$2 -> 157.22 | M80: =datos!NA85 -> 293.89 | N80: =datos!BS85*$N$2 -> 189 | O80: =datos!ND85 -> 1069 | P80: =(datos!AG85/1000)/$P$2 -> 137.91176 | Q80: =datos!MY85*$Q$2 -> 548.26 | R80: =datos!BN85 -> 43.38 | S80: 0.0388 | T80: 591.1 | U80: =T80*S80 -> 22.93468 | V80: =datos!NC85+U80 -> 140.43468 | W80: =datos!AV85*W$4 -> 548.5 | X80: =W80*X$4 -> 43.88 | Y80: =Y81/(1+(datos!G86/datos!G85-1)) -> 31.873645 | Z80: =AZ6 -> 0.2 | AA80: =AA$82/(1+Z$80) -> 88.130058 | AB80: =(W80-X80-Y80-AA80)/AB$3 -> 19.230815 | AC80: =datos!MJ85 -> 68.2 | AD80: =datos!BB85*AD$4 -> 839.79546 | AE80: =AD80*AE$4 -> 67.183637 | AF80: =Y80 -> 31.873645 | AG80: =AA80 -> 88.130058 | AH80: =(AD80-AE80-AF80-AG80)/AH$3 -> 36.256007 | AI80: =AVERAGE(datos!ML85,datos!MM85,datos!MN85,datos!MO85) -> 121.93 | AK80: =A80 -> 44652 | AL80: =B80/C80 -> 0.21049732 | AM80: =D80/E80 -> 0.31958287 | AN80: =F80/G80 -> 0.15148553 | AO80: =H80/I80 -> 0.66109984 | AP80: =J80/K80 -> 0.38478079 | AQ80: =L80/M80 -> 0.53496206 | AR80: =N80/O80 -> 0.17680075 | AS80: =P80/Q80 -> 0.25154446 | AT80: =R80/V80 -> 0.30889806 | AU80: =AB80/AC80 -> 0.28197676 | AV80: =AH80/AI80 -> 0.297351
A81: 44682 | B81: =datos!R86/1000 -> 26.5 | C81: =datos!MA86 -> 131.18 | D81: =datos!AI86 -> 63.398 | E81: =datos!MP86 -> 223.37 | F81: =(datos!AD86/1000)/PP!$F$2 -> 52.466649 | G81: =datos!MH86 -> 301.62 | H81: =datos!BK86/$H$2 -> 715.41742 | I81: =datos!NB86 -> 1095.95 | J81: =datos!BR86/$J$2 -> 264.26667 | K81: =datos!NE86 -> 701.15 | L81: =datos!BO86*$L$2 -> 170.59 | M81: =datos!NA86 -> 312.37 | N81: =datos!BS86*$N$2 -> 192.78 | O81: =datos!ND86 -> 1130 | P81: =(datos!AG86/1000)/$P$2 -> 137.91176 | Q81: =datos!MY86*$Q$2 -> 588.24 | R81: =datos!BN86 -> 45.52 | S81: 0.0388 | T81: 616.33 | U81: =T81*S81 -> 23.913604 | V81: =datos!NC86+U81 -> 149.6036 | W81: =datos!AV86*W$4 -> 634.85965 | X81: =W81*X$4 -> 50.788772 | Y81: =Y82/(1+(datos!G87/datos!G86-1)) -> 33.48311 | AA81: =AA$82/(1+Z$80) -> 88.130058 | AB81: =(W81-X81-Y81-AA81)/AB$3 -> 23.122885 | AC81: =datos!MJ86 -> 71.28 | AD81: =datos!BB86*AD$4 -> 986.99118 | AE81: =AD81*AE$4 -> 78.959295 | AF81: =Y81 -> 33.48311 | AG81: =AA81 -> 88.130058 | AH81: =(AD81-AE81-AF81-AG81)/AH$3 -> 43.689929 | AI81: =AVERAGE(datos!ML86,datos!MM86,datos!MN86,datos!MO86) -> 122.97667 | AK81: =A81 -> 44682 | AL81: =B81/C81 -> 0.2020125 | AM81: =D81/E81 -> 0.28382504 | AN81: =F81/G81 -> 0.1739495 | AO81: =H81/I81 -> 0.6527829 | AP81: =J81/K81 -> 0.37690461 | AQ81: =L81/M81 -> 0.54611518 | AR81: =N81/O81 -> 0.17060177 | AS81: =P81/Q81 -> 0.23444812 | AT81: =R81/V81 -> 0.30427074 | AU81: =AB81/AC81 -> 0.32439514 | AV81: =AH81/AI81 -> 0.35527007
A82: 44713 | B82: =datos!R87/1000 -> 27.75 | C82: =datos!MA87 -> 136.95 | D82: =datos!AI87 -> 71.96 | E82: =datos!MP87 -> 245.18 | F82: =(datos!AD87/1000)/PP!$F$2 -> 50.182913 | G82: =datos!MH87 -> 311.8 | H82: =datos!BK87/$H$2 -> 704.50544 | I82: =datos!NB87 -> 1108.84 | J82: =datos!BR87/$J$2 -> 258.71667 | K82: =datos!NE87 -> 699.51 | L82: =datos!BO87*$L$2 -> 178.15 | M82: =datos!NA87 -> 338.59 | N82: =datos!BS87*$N$2 -> 234.36 | O82: =datos!ND87 -> 1210 | P82: =(datos!AG87/1000)/$P$2 -> 137.91176 | Q82: =datos!MY87*$Q$2 -> 609.82 | R82: =datos!BN87 -> 47.81 | S82: 0.0389 | T82: 6473.56 | U82: =T82*S82 -> 251.82148 | V82: =datos!NC87+U82 -> 384.33148 | W82: =datos!AV87*W$4 -> 762.38462 | X82: =W82*X$4 -> 60.990769 | Y82: =Y83/(1+(datos!G88/datos!G87-1)) -> 35.25708 | Z82: =AZ7 -> 0.15711198 | AA82: =AA$87/(1+Z$82) -> 105.75607 | AB82: =(W82-X82-Y82-AA82)/AB$3 -> 28.019035 | AC82: =datos!MJ87 -> 86.64 | AD82: =datos!BB87*AD$4 -> 1125.2084 | AE82: =AD82*AE$4 -> 90.016673 | AF82: =Y82 -> 35.25708 | AG82: =AA82 -> 105.75607 | AH82: =(AD82-AE82-AF82-AG82)/AH$3 -> 49.676588 | AI82: =AVERAGE(datos!ML87,datos!MM87,datos!MN87,datos!MO87) -> 137.74 | AK82: =A82 -> 44713 | AL82: =B82/C82 -> 0.2026287 | AM82: =D82/E82 -> 0.29349865 | AN82: =F82/G82 -> 0.16094584 | AO82: =H82/I82 -> 0.63535356 | AP82: =J82/K82 -> 0.36985414 | AQ82: =L82/M82 -> 0.52615257 | AR82: =N82/O82 -> 0.19368595 | AS82: =P82/Q82 -> 0.22615159 | AT82: =R82/V82 -> 0.12439782 | AU82: =AB82/AC82 -> 0.32339606 | AV82: =AH82/AI82 -> 0.36065477
A83: 44743 | B83: =datos!R88/1000 -> 32 | C83: =datos!MA88 -> 137.75 | D83: =datos!AI88 -> 73.6065 | E83: =datos!MP88 -> 265.85 | F83: =(datos!AD88/1000)/PP!$F$2 -> 47.693674 | G83: =datos!MH88 -> 327.39 | H83: =datos!BK88/$H$2 -> 692.46824 | I83: =datos!NB88 -> 1108.17 | J83: =datos!BR88/$J$2 -> 349.225 | K83: =datos!NE88 -> 755.06 | L83: =datos!BO88*$L$2 -> 173.81 | M83: =datos!NA88 -> 353.12 | N83: =datos!BS88*$N$2 -> 257.04 | O83: =datos!ND88 -> 1400 | P83: =(datos!AG88/1000)/$P$2 -> 137.91176 | Q83: =datos!MY88*$Q$2 -> 636.02 | R83: =datos!BN88 -> 50.51 | S83: 0.0387 | T83: 689.9 | U83: =T83*S83 -> 26.69913 | V83: =datos!NC88+U83 -> 169.11913 | W83: =datos!AV88*W$4 -> 851.41026 | X83: =W83*X$4 -> 68.112821 | Y83: =Y84/(1+(datos!G89/datos!G88-1)) -> 37.87135 | AA83: =AA$87/(1+Z$82) -> 105.75607 | AB83: =(W83-X83-Y83-AA83)/AB$3 -> 31.983501 | AC83: =datos!MJ88 -> 91.32 | AD83: =datos!BB88*AD$4 -> 1167.4958 | AE83: =AD83*AE$4 -> 93.399665 | AF83: =Y83 -> 37.87135 | AG83: =AA83 -> 105.75607 | AH83: =(AD83-AE83-AF83-AG83)/AH$3 -> 51.692707 | AI83: =AVERAGE(datos!ML88,datos!MM88,datos!MN88,datos!MO88) -> 149.83667 | AK83: =A83 -> 44743 | AL83: =B83/C83 -> 0.2323049 | AM83: =D83/E83 -> 0.2768723 | AN83: =F83/G83 -> 0.14567847 | AO83: =H83/I83 -> 0.62487546 | AP83: =J83/K83 -> 0.46251291 | AQ83: =L83/M83 -> 0.49221228 | AR83: =N83/O83 -> 0.1836 | AS83: =P83/Q83 -> 0.21683558 | AT83: =R83/V83 -> 0.29866521 | AU83: =AB83/AC83 -> 0.35023544 | AV83: =AH83/AI83 -> 0.34499371
A84: 44774 | B84: =datos!R89/1000 -> 34 | C84: =datos!MA89 -> 143.83 | D84: =datos!AI89 -> 78.4221 | E84: =datos!MP89 -> 280.89 | F84: =(datos!AD89/1000)/PP!$F$2 -> 49.050333 | G84: =datos!MH89 -> 343.1 | H84: =datos!BK89/$H$2 -> 719.99093 | I84: =datos!NB89 -> 1113.06 | J84: =datos!BR89/$J$2 -> 350.16667 | K84: =datos!NE89 -> 821.93 | L84: =datos!BO89*$L$2 -> 186.41 | M84: =datos!NA89 -> 365.8 | N84: =datos!BS89*$N$2 -> 264.6 | O84: =datos!ND89 -> 1390 | P84: =(datos!AG89/1000)/$P$2 -> 137.91176 | Q84: =datos!MY89*$Q$2 -> 663.68 | R84: =datos!BN89 -> 52.58 | S84: 0.038 | T84: 731.98 | U84: =T84*S84 -> 27.81524 | V84: =datos!NC89+U84 -> 181.70524 | W84: =datos!AV89*W$4 -> 1230.907 | X84: =W84*X$4 -> 98.472558 | Y84: =Y85/(1+(datos!G90/datos!G89-1)) -> 40.50785 | AA84: =AA$87/(1+Z$82) -> 105.75607 | AB84: =(W84-X84-Y84-AA84)/AB$3 -> 49.308525 | AC84: =datos!MJ89 -> 120.84 | AD84: =datos!BB89*AD$4 -> 1715.9065 | AE84: =AD84*AE$4 -> 137.27252 | AF84: =Y84 -> 40.50785 | AG84: =AA84 -> 105.75607 | AH84: =(AD84-AE84-AF84-AG84)/AH$3 -> 79.576113 | AI84: =AVERAGE(datos!ML89,datos!MM89,datos!MN89,datos!MO89) -> 200.32 | AK84: =A84 -> 44774 | AL84: =B84/C84 -> 0.23639018 | AM84: =D84/E84 -> 0.2791915 | AN84: =F84/G84 -> 0.14296221 | AO84: =H84/I84 -> 0.64685725 | AP84: =J84/K84 -> 0.42602979 | AQ84: =L84/M84 -> 0.50959541 | AR84: =N84/O84 -> 0.19035971 | AS84: =P84/Q84 -> 0.20779858 | AT84: =R84/V84 -> 0.28936975 | AU84: =AB84/AC84 -> 0.40804804 | AV84: =AH84/AI84 -> 0.39724497
A85: 44805 | B85: =datos!R90/1000 -> 36 | C85: =datos!MA90 -> 154.33 | D85: =datos!AI90 -> 79.05 | E85: =datos!MP90 -> 300.58 | F85: =(datos!AD90/1000)/PP!$F$2 -> 56.320916 | G85: =datos!MH90 -> 366.54 | H85: =datos!BK90/$H$2 -> 707.62704 | I85: =datos!NB90 -> 1158.68 | J85: =datos!BR90/$J$2 -> 384.9 | K85: =datos!NE90 -> 873.33 | L85: =datos!BO90*$L$2 -> 193.06 | M85: =datos!NA90 -> 376.6 | N85: =datos!BS90*$N$2 -> 283.5 | O85: =datos!ND90 -> 1490 | P85: =(datos!AG90/1000)/$P$2 -> 137.91176 | Q85: =datos!MY90*$Q$2 -> 678.96 | R85: =datos!BN90 -> 55.5 | S85: 0.0377 | T85: 771.17 | U85: =T85*S85 -> 29.073109 | V85: =datos!NC90+U85 -> 200.13311 | W85: =datos!AV90*W$4 -> 1521.0341 | X85: =W85*X$4 -> 121.68273 | Y85: =Y86/(1+(datos!G91/datos!G90-1)) -> 43.006523 | AA85: =AA$87/(1+Z$82) -> 105.75607 | AB85: =(W85-X85-Y85-AA85)/AB$3 -> 62.529439 | AC85: =datos!MJ90 -> 142.16 | AD85: =datos!BB90*AD$4 -> 2057.485 | AE85: =AD85*AE$4 -> 164.5988 | AF85: =Y85 -> 43.006523 | AG85: =AA85 -> 105.75607 | AH85: =(AD85-AE85-AF85-AG85)/AH$3 -> 96.895758 | AI85: =AVERAGE(datos!ML90,datos!MM90,datos!MN90,datos!MO90) -> 264.05333 | AK85: =A85 -> 44805 | AL85: =B85/C85 -> 0.23326638 | AM85: =D85/E85 -> 0.26299155 | AN85: =F85/G85 -> 0.15365558 | AO85: =H85/I85 -> 0.61071827 | AP85: =J85/K85 -> 0.44072687 | AQ85: =L85/M85 -> 0.51263941 | AR85: =N85/O85 -> 0.19026846 | AS85: =P85/Q85 -> 0.20312208 | AT85: =R85/V85 -> 0.27731543 | AU85: =AB85/AC85 -> 0.43985255 | AV85: =AH85/AI85 -> 0.36695526
A86: 44835 | B86: =datos!R91/1000 -> 40 | C86: =datos!MA91 -> 167.76 | D86: =datos!AI91 -> 77.85 | E86: =datos!MP91 -> 317.44 | F86: =(datos!AD91/1000)/PP!$F$2 -> 67.713609 | G86: =datos!MH91 -> 385.2 | H86: =datos!BK91/$H$2 -> 669.63475 | I86: =datos!NB91 -> 1203.51 | J86: =datos!BR91/$J$2 -> 425.38333 | K86: =datos!NE91 -> 929.54 | L86: =datos!BO91*$L$2 -> 200.83 | M86: =datos!NA91 -> 401.64 | N86: =datos!BS91*$N$2 -> 323.946 | O86: =datos!ND91 -> 1490 | P86: =(datos!AG91/1000)/$P$2 -> 206.11765 | Q86: =datos!MY91*$Q$2 -> 702.4 | R86: =datos!BN91 -> 58.39 | S86: 0.0373 | T86: 818.44 | U86: =T86*S86 -> 30.527812 | V86: =datos!NC91+U86 -> 231.13781 | W86: =datos!AV91*W$4 -> 1961.1275 | X86: =W86*X$4 -> 156.8902 | Y86: =Y87/(1+(datos!G92/datos!G91-1)) -> 45.736391 | AA86: =AA$87/(1+Z$82) -> 105.75607 | AB86: =(W86-X86-Y86-AA86)/AB$3 -> 82.63724 | AC86: =datos!MJ91 -> 224.06 | AD86: =datos!BB91*AD$4 -> 1973.5769 | AE86: =AD86*AE$4 -> 157.88615 | AF86: =Y86 -> 45.736391 | AG86: =AA86 -> 105.75607 | AH86: =(AD86-AE86-AF86-AG86)/AH$3 -> 92.455459 | AI86: =AVERAGE(datos!ML91,datos!MM91,datos!MN91,datos!MO91) -> 276.59333 | AK86: =A86 -> 44835 | AL86: =B86/C86 -> 0.23843586 | AM86: =D86/E86 -> 0.2452432 | AN86: =F86/G86 -> 0.17578819 | AO86: =H86/I86 -> 0.55640149 | AP86: =J86/K86 -> 0.45762779 | AQ86: =L86/M86 -> 0.5000249 | AR86: =N86/O86 -> 0.21741342 | AS86: =P86/Q86 -> 0.29344768 | AT86: =R86/V86 -> 0.25261985 | AU86: =AB86/AC86 -> 0.36881746 | AV86: =AH86/AI86 -> 0.33426496
A87: 44866 | B87: =datos!R92/1000 -> 44 | C87: =datos!MA92 -> 173.27 | D87: =datos!AI92 -> 87.6671 | E87: =datos!MP92 -> 336.02 | F87: =(datos!AD92/1000)/PP!$F$2 -> 71.698289 | G87: =datos!MH92 -> 407.77 | H87: =datos!BK92/$H$2 -> 680.36298 | I87: =datos!NB92 -> 1208.9 | J87: =datos!BR92/$J$2 -> 417.06667 | K87: =datos!NE92 -> 946.84 | L87: =datos!BO92*$L$2 -> 188.72 | M87: =datos!NA92 -> 412.71 | N87: =datos!BS92*$N$2 -> 302.4 | O87: =datos!ND92 -> 1690 | P87: =(datos!AG92/1000)/$P$2 -> 206.11765 | Q87: =datos!MY92*$Q$2 -> 738.56 | R87: =datos!BN92 -> 61.59 | S87: 0.0366 | T87: 877.24 | U87: =T87*S87 -> 32.106984 | V87: =datos!NC92+U87 -> 242.31698 | W87: =datos!AV92*W$4 -> 1720.0595 | X87: =W87*X$4 -> 137.60476 | Y87: =Y88/(1+(datos!G93/datos!G92-1)) -> 47.986086 | Z87: =AZ8 -> 0.35337269 | AA87: =AA$90/(1+Z$87) -> 122.37161 | AB87: =(W87-X87-Y87-AA87)/AB$3 -> 70.604853 | AC87: =datos!MJ92 -> 206.65 | AD87: =datos!BB92*AD$4 -> 1697.5056 | AE87: =AD87*AE$4 -> 135.80045 | AF87: =Y87 -> 47.986086 | AG87: =AA87 -> 122.37161 | AH87: =(AD87-AE87-AF87-AG87)/AH$3 -> 77.297081 | AI87: =AVERAGE(datos!ML92,datos!MM92,datos!MN92,datos!MO92) -> 256.61667 | AK87: =A87 -> 44866 | AL87: =B87/C87 -> 0.25393894 | AM87: =D87/E87 -> 0.26089846 | AN87: =F87/G87 -> 0.17583022 | AO87: =H87/I87 -> 0.56279508 | AP87: =J87/K87 -> 0.44048273 | AQ87: =L87/M87 -> 0.45727024 | AR87: =N87/O87 -> 0.17893491 | AS87: =P87/Q87 -> 0.27908044 | AT87: =R87/V87 -> 0.25417121 | AU87: =AB87/AC87 -> 0.34166394 | AV87: =AH87/AI87 -> 0.30121614
A88: 44896 | B88: =datos!R93/1000 -> 44 | C88: =datos!MA93 -> 183.52 | D88: =datos!AI93 -> 104.8064 | E88: =datos!MP93 -> 358.15 | F88: =(datos!AD93/1000)/PP!$F$2 -> 71.881583 | G88: =datos!MH93 -> 428.42 | H88: =datos!BK93/$H$2 -> 694.68693 | I88: =datos!NB93 -> 1239.2 | J88: =datos!BR93/$J$2 -> 431.46667 | K88: =datos!NE93 -> 957.8 | L88: =datos!BO93*$L$2 -> 204.12 | M88: =datos!NA93 -> 426.32 | N88: =datos!BS93*$N$2 -> 321.3 | O88: =datos!ND93 -> 1690 | P88: =(datos!AG93/1000)/$P$2 -> 206.11765 | Q88: =datos!MY93*$Q$2 -> 754.26 | R88: =datos!BN93 -> 66.24 | S88: 0.0361 | T88: 956.31 | U88: =T88*S88 -> 34.522791 | V88: =datos!NC93+U88 -> 250.83279 | W88: =datos!AV93*W$4 -> 1882.6984 | X88: =W88*X$4 -> 150.61587 | Y88: =Y89/(1+(datos!G94/datos!G93-1)) -> 50.444745 | AA88: =AA$90/(1+Z$87) -> 122.37161 | AB88: =(W88-X88-Y88-AA88)/AB$3 -> 77.963309 | AC88: =datos!MJ93 -> 210.94 | AD88: =datos!BB93*AD$4 -> 1781.9228 | AE88: =AD88*AE$4 -> 142.55382 | AF88: =Y88 -> 50.444745 | AG88: =AA88 -> 122.37161 | AH88: =(AD88-AE88-AF88-AG88)/AH$3 -> 81.475145 | AI88: =AVERAGE(datos!ML93,datos!MM93,datos!MN93,datos!MO93) -> 249.36667 | AK88: =A88 -> 44896 | AL88: =B88/C88 -> 0.23975588 | AM88: =D88/E88 -> 0.2926327 | AN88: =F88/G88 -> 0.16778298 | AO88: =H88/I88 -> 0.56059307 | AP88: =J88/K88 -> 0.45047679 | AQ88: =L88/M88 -> 0.47879527 | AR88: =N88/O88 -> 0.19011834 | AS88: =P88/Q88 -> 0.27327135 | AT88: =R88/V88 -> 0.26408031 | AU88: =AB88/AC88 -> 0.36959945 | AV88: =AH88/AI88 -> 0.32672829
A89: 44927 | B89: =datos!R94/1000 -> 51.5 | C89: =datos!MA94 -> 198.02 | D89: =datos!AI94 -> 112.5087 | E89: =datos!MP94 -> 386.94 | F89: =(datos!AD94/1000)/PP!$F$2 -> 71.56306 | G89: =datos!MH94 -> 435.66 | H89: =datos!BK94/$H$2 -> 787.15971 | I89: =datos!NB94 -> 1276.95 | J89: =datos!BR94/$J$2 -> 445 | K89: =datos!NE94 -> 992.29 | L89: =datos!BO94*$L$2 -> 190.96 | M89: =datos!NA94 -> 444.98 | N89: =datos!BS94*$N$2 -> 359.1 | O89: =datos!ND94 -> 1770 | P89: =(datos!AG94/1000)/$P$2 -> 206.11765 | Q89: =datos!MY94*$Q$2 -> 786.2 | R89: =datos!BN94 -> 69.98 | S89: 0.0362 | T89: 1007.88 | U89: =T89*S89 -> 36.485256 | V89: =datos!NC94+U89 -> 261.75526 | W89: =datos!AV94*W$4 -> 2344.0217 | X89: =W89*X$4 -> 187.52174 | Y89: =Y90/(1+(datos!G95/datos!G94-1)) -> 53.485834 | AA89: =AA$90/(1+Z$87) -> 122.37161 | AB89: =(W89-X89-Y89-AA89)/AB$3 -> 99.032128 | AC89: =datos!MJ94 -> 263.02 | AD89: =datos!BB94*AD$4 -> 2470.2052 | AE89: =AD89*AE$4 -> 197.61641 | AF89: =Y89 -> 53.485834 | AG89: =AA89 -> 122.37161 | AH89: =(AD89-AE89-AF89-AG89)/AH$3 -> 116.48507 | AI89: =AVERAGE(datos!ML94,datos!MM94,datos!MN94,datos!MO94) -> 309.10667 | AK89: =A89 -> 44927 | AL89: =B89/C89 -> 0.26007474 | AM89: =D89/E89 -> 0.29076523 | AN89: =F89/G89 -> 0.16426356 | AO89: =H89/I89 -> 0.61643738 | AP89: =J89/K89 -> 0.44845761 | AQ89: =L89/M89 -> 0.42914288 | AR89: =N89/O89 -> 0.20288136 | AS89: =P89/Q89 -> 0.26216948 | AT89: =R89/V89 -> 0.26734898 | AU89: =AB89/AC89 -> 0.37651938 | AV89: =AH89/AI89 -> 0.37684426
A90: 44958 | B90: =datos!R95/1000 -> 55 | C90: =datos!MA95 -> 226.87 | D90: =datos!AI95 -> 137 | E90: =datos!MP95 -> 414.26 | F90: =(datos!AD95/1000)/PP!$F$2 -> 73.522811 | G90: =datos!MH95 -> 459.15 | H90: =datos!BK95/$H$2 -> 1048.1329 | I90: =datos!NB95 -> 1587.5 | J90: =datos!BR95/$J$2 -> 468.52 | K90: =datos!NE95 -> 1105.4 | L90: =datos!BO95*$L$2 -> 219.73 | M90: =datos!NA95 -> 444.2 | N90: =datos!BS95*$N$2 -> 378 | O90: =datos!ND95 -> 1890 | P90: =(datos!AG95/1000)/$P$2 -> 206.11765 | Q90: =datos!MY95*$Q$2 -> 827.66 | R90: =datos!BN95 -> 74.04 | S90: 0.0365 | T90: 1057.26 | U90: =T90*S90 -> 38.58999 | V90: =datos!NC95+U90 -> 274.62999 | W90: =datos!AV95*W$4 -> 2093.4694 | X90: =W90*X$4 -> 167.47755 | Y90: =Y91/(1+(datos!G96/datos!G95-1)) -> 57.251628 | Z90: =AZ9 -> 0.21999724 | AA90: =AA$94/(1+Z$90) -> 165.6144 | AB90: =(W90-X90-Y90-AA90)/AB$3 -> 85.15629 | AC90: =datos!MJ95 -> 256.7 | AD90: =datos!BB95*AD$4 -> 2089.792 | AE90: =AD90*AE$4 -> 167.18336 | AF90: =Y90 -> 57.251628 | AG90: =AA90 -> 165.6144 | AH90: =(AD90-AE90-AF90-AG90)/AH$3 -> 94.430143 | AI90: =AVERAGE(datos!ML95,datos!MM95,datos!MN95,datos!MO95) -> 285.02 | AK90: =A90 -> 44958 | AL90: =B90/C90 -> 0.24242959 | AM90: =D90/E90 -> 0.33071018 | AN90: =F90/G90 -> 0.16012809 | AO90: =H90/I90 -> 0.66024122 | AP90: =J90/K90 -> 0.42384657 | AQ90: =L90/M90 -> 0.49466457 | AR90: =N90/O90 -> 0.2 | AS90: =P90/Q90 -> 0.24903662 | AT90: =R90/V90 -> 0.26959911 | AU90: =AB90/AC90 -> 0.33173467 | AV90: =AH90/AI90 -> 0.33131058
A91: 44986 | B91: =datos!R96/1000 -> 64 | C91: =datos!MA96 -> 242.47 | D91: =datos!AI96 -> 139.81788 | E91: =datos!MP96 -> 433.03 | F91: =(datos!AD96/1000)/PP!$F$2 -> 74.05676 | G91: =datos!MH96 -> 505.58 | H91: =datos!BK96/$H$2 -> 1075.8825 | I91: =datos!NB96 -> 1801.2 | J91: =datos!BR96/$J$2 -> 497.4 | K91: =datos!NE96 -> 1202.6 | L91: =datos!BO96*$L$2 -> 294.56 | M91: =datos!NA96 -> 582.3 | N91: =datos!BS96*$N$2 -> 378 | O91: =datos!ND96 -> 1950 | P91: =(datos!AG96/1000)/$P$2 -> 206.11765 | Q91: =datos!MY96*$Q$2 -> 878.74 | R91: =datos!BN96 -> 81.53 | S91: 0.0373 | T91: 1149.67 | U91: =T91*S91 -> 42.882691 | V91: =datos!NC96+U91 -> 294.75269 | W91: =datos!AV96*W$4 -> 1888.8889 | X91: =W91*X$4 -> 151.11111 | Y91: =Y92/(1+(datos!G97/datos!G96-1)) -> 61.408674 | AA91: =AA$94/(1+Z$90) -> 165.6144 | AB91: =(W91-X91-Y91-AA91)/AB$3 -> 75.537735 | AC91: =datos!MJ96 -> 246.9 | AD91: =datos!BB96*AD$4 -> 2333.7156 | AE91: =AD91*AE$4 -> 186.69725 | AF91: =Y91 -> 61.408674 | AG91: =AA91 -> 165.6144 | AH91: =(AD91-AE91-AF91-AG91)/AH$3 -> 106.66641 | AI91: =AVERAGE(datos!ML96,datos!MM96,datos!MN96,datos!MO96) -> 302.46333 | AK91: =A91 -> 44986 | AL91: =B91/C91 -> 0.26395018 | AM91: =D91/E91 -> 0.32288266 | AN91: =F91/G91 -> 0.14647882 | AO91: =H91/I91 -> 0.59731428 | AP91: =J91/K91 -> 0.41360386 | AQ91: =L91/M91 -> 0.50585609 | AR91: =N91/O91 -> 0.19384615 | AS91: =P91/Q91 -> 0.23456045 | AT91: =R91/V91 -> 0.27660477 | AU91: =AB91/AC91 -> 0.30594465 | AV91: =AH91/AI91 -> 0.35265897
A92: 45017 | B92: =datos!R97/1000 -> 64 | C92: =datos!MA97 -> 269.86 | D92: =datos!AI97 -> 183.5764 | E92: =datos!MP97 -> 465.77 | F92: =(datos!AD97/1000)/PP!$F$2 -> 63.449256 | G92: =datos!MH97 -> 545.94 | H92: =datos!BK97/$H$2 -> 1107.4728 | I92: =datos!NB97 -> 1860.7 | J92: =datos!BR97/$J$2 -> 518.35833 | K92: =datos!NE97 -> 1259.12 | L92: =datos!BO97*$L$2 -> 329.14 | M92: =datos!NA97 -> 739.07 | N92: =datos!BS97*$N$2 -> 415.8 | O92: =datos!ND97 -> 1979 | P92: =(datos!AG97/1000)/$P$2 -> 314.70588 | Q92: =datos!MY97*$Q$2 -> 948.22 | R92: =datos!BN97 -> 89.36 | S92: 0.0385 | T92: 1224.16 | U92: =T92*S92 -> 47.13016 | V92: =datos!NC97+U92 -> 318.42016 | W92: =datos!AV97*W$4 -> 1724.8611 | X92: =W92*X$4 -> 137.98889 | Y92: =Y93/(1+(datos!G98/datos!G97-1)) -> 66.566078 | AA92: =AA$94/(1+Z$90) -> 165.6144 | AB92: =(W92-X92-Y92-AA92)/AB$3 -> 67.734587 | AC92: =datos!MJ97 -> 240.82 | AD92: =datos!BB97*AD$4 -> 2786.0427 | AE92: =AD92*AE$4 -> 222.88341 | AF92: =Y92 -> 66.566078 | AG92: =AA92 -> 165.6144 | AH92: =(AD92-AE92-AF92-AG92)/AH$3 -> 129.49882 | AI92: =AVERAGE(datos!ML97,datos!MM97,datos!MN97,datos!MO97) -> 379.20667 | AK92: =A92 -> 45017 | AL92: =B92/C92 -> 0.23716001 | AM92: =D92/E92 -> 0.3941353 | AN92: =F92/G92 -> 0.1162202 | AO92: =H92/I92 -> 0.59519147 | AP92: =J92/K92 -> 0.41168303 | AQ92: =L92/M92 -> 0.44534347 | AR92: =N92/O92 -> 0.21010611 | AS92: =P92/Q92 -> 0.33189121 | AT92: =R92/V92 -> 0.2806355 | AU92: =AB92/AC92 -> 0.28126645 | AV92: =AH92/AI92 -> 0.34149933
A93: 45047 | B93: =datos!R98/1000 -> 85 | C93: =datos!MA98 -> 318.44 | D93: =datos!AI98 -> 164.2237 | E93: =datos!MP98 -> 506.03 | F93: =(datos!AD98/1000)/PP!$F$2 -> 70.102055 | G93: =datos!MH98 -> 617.19 | H93: =datos!BK98/$H$2 -> 1111.3317 | I93: =datos!NB98 -> 1873.54 | J93: =datos!BR98/$J$2 -> 545.27083 | K93: =datos!NE98 -> 1333.52 | L93: =datos!BO98*$L$2 -> 273.98 | M93: =datos!NA98 -> 727.32 | N93: =datos!BS98*$N$2 -> 453.6 | O93: =datos!ND98 -> 1980 | P93: =(datos!AG98/1000)/$P$2 -> 329.41176 | Q93: =datos!MY98*$Q$2 -> 1080.78 | R93: =datos!BN98 -> 96.58 | S93: 0.039 | T93: 1309.27 | U93: =T93*S93 -> 51.06153 | V93: =datos!NC98+U93 -> 344.36153 | W93: =datos!AV98*W$4 -> 2066.2791 | X93: =W93*X$4 -> 165.30233 | Y93: =Y94/(1+(datos!G99/datos!G98-1)) -> 71.741265 | AA93: =AA$94/(1+Z$90) -> 165.6144 | AB93: =(W93-X93-Y93-AA93)/AB$3 -> 83.181054 | AC93: =datos!MJ98 -> 251.59 | AD93: =datos!BB98*AD$4 -> 3460.6505 | AE93: =AD93*AE$4 -> 276.85204 | AF93: =Y93 -> 71.741265 | AG93: =AA93 -> 165.6144 | AH93: =(AD93-AE93-AF93-AG93)/AH$3 -> 163.69127 | AI93: =AVERAGE(datos!ML98,datos!MM98,datos!MN98,datos!MO98) -> 465.50667 | AK93: =A93 -> 45047 | AL93: =B93/C93 -> 0.26692627 | AM93: =D93/E93 -> 0.32453353 | AN93: =F93/G93 -> 0.11358262 | AO93: =H93/I93 -> 0.59317211 | AP93: =J93/K93 -> 0.40889588 | AQ93: =L93/M93 -> 0.37669801 | AR93: =N93/O93 -> 0.22909091 | AS93: =P93/Q93 -> 0.30479077 | AT93: =R93/V93 -> 0.28046106 | AU93: =AB93/AC93 -> 0.33062146 | AV93: =AH93/AI93 -> 0.35164108
A94: 45078 | B94: =datos!R99/1000 -> 95 | C94: =datos!MA99 -> 358.85 | D94: =datos!AI99 -> 152.512 | E94: =datos!MP99 -> 570.53 | F94: =(datos!AD99/1000)/PP!$F$2 -> 73.110889 | G94: =datos!MH99 -> 698.16 | H94: =datos!BK99/$H$2 -> 1098.7273 | I94: =datos!NB99 -> 1907.21 | J94: =datos!BR99/$J$2 -> 558.425 | K94: =datos!NE99 -> 1372.65 | L94: =datos!BO99*$L$2 -> 262.08 | M94: =datos!NA99 -> 678.86 | N94: =datos!BS99*$N$2 -> 453.6 | O94: =datos!ND99 -> 2100 | P94: =(datos!AG99/1000)/$P$2 -> 329.41176 | Q94: =datos!MY99*$Q$2 -> 1260.36 | R94: =datos!BN99 -> 102.2 | S94: 0.0388 | T94: 1391.72 | U94: =T94*S94 -> 53.998736 | V94: =datos!NC99+U94 -> 363.62874 | W94: =datos!AV99*W$4 -> 3133.871 | X94: =W94*X$4 -> 250.70968 | Y94: =Y95/(1+(datos!G100/datos!G99-1)) -> 76.009462 | Z94: =AZ10 -> 0.29999774 | AA94: =AA$97/(1+Z$94) -> 202.04911 | AB94: =(W94-X94-Y94-AA94)/AB$3 -> 130.25514 | AC94: =datos!MJ99 -> 313.8 | AD94: =datos!BB99*AD$4 -> 2694.5402 | AE94: =AD94*AE$4 -> 215.56321 | AF94: =Y94 -> 76.009462 | AG94: =AA94 -> 202.04911 | AH94: =(AD94-AE94-AF94-AG94)/AH$3 -> 122.27324 | AI94: =AVERAGE(datos!ML99,datos!MM99,datos!MN99,datos!MO99) -> 383.07 | AK94: =A94 -> 45078 | AL94: =B94/C94 -> 0.26473457 | AM94: =D94/E94 -> 0.26731635 | AN94: =F94/G94 -> 0.10471939 | AO94: =H94/I94 -> 0.57609142 | AP94: =J94/K94 -> 0.40682257 | AQ94: =L94/M94 -> 0.38605898 | AR94: =N94/O94 -> 0.216 | AS94: =P94/Q94 -> 0.26136323 | AT94: =R94/V94 -> 0.2810559 | AU94: =AB94/AC94 -> 0.41508966 | AV94: =AH94/AI94 -> 0.31919295
A95: 45108 | B95: =datos!R100/1000 -> 115 | C95: =datos!MA100 -> 403.18 | D95: =datos!AI100 -> 188.4509 | E95: =datos!MP100 -> 614.51 | F95: =(datos!AD100/1000)/PP!$F$2 -> 79.249851 | G95: =datos!MH100 -> 756.05 | H95: =datos!BK100/$H$2 -> 1149.8412 | I95: =datos!NB100 -> 1906.5 | J95: =datos!BR100/$J$2 -> 594.72083 | K95: =datos!NE100 -> 1411.2 | L95: =datos!BO100*$L$2 -> 306.18 | M95: =datos!NA100 -> 687.3 | N95: =datos!BS100*$N$2 -> 453.6 | O95: =datos!ND100 -> 2229 | P95: =(datos!AG100/1000)/$P$2 -> 352.94118 | Q95: =datos!MY100*$Q$2 -> 1363.64 | R95: =datos!BN100 -> 106.74 | S95: 0.0385 | T95: 1465.1 | U95: =T95*S95 -> 56.40635 | V95: =datos!NC100+U95 -> 386.97635 | W95: =datos!AV100*W$4 -> 4818.125 | X95: =W95*X$4 -> 385.45 | Y95: =Y96/(1+(datos!G101/datos!G100-1)) -> 80.833413 | AA95: =AA$97/(1+Z$94) -> 202.04911 | AB95: =(W95-X95-Y95-AA95)/AB$3 -> 207.48962 | AC95: =datos!MJ100 -> 420.69 | AD95: =datos!BB100*AD$4 -> 2111.1866 | AE95: =AD95*AE$4 -> 168.89493 | AF95: =Y95 -> 80.833413 | AG95: =AA95 -> 202.04911 | AH95: =(AD95-AE95-AF95-AG95)/AH$3 -> 92.189396 | AI95: =AVERAGE(datos!ML100,datos!MM100,datos!MN100,datos!MO100) -> 342.51333 | AK95: =A95 -> 45108 | AL95: =B95/C95 -> 0.2852324 | AM95: =D95/E95 -> 0.30666857 | AN95: =F95/G95 -> 0.10482091 | AO95: =H95/I95 -> 0.60311629 | AP95: =J95/K95 -> 0.42142916 | AQ95: =L95/M95 -> 0.44548232 | AR95: =N95/O95 -> 0.20349933 | AS95: =P95/Q95 -> 0.25882284 | AT95: =R95/V95 -> 0.27583081 | AU95: =AB95/AC95 -> 0.49321264 | AV95: =AH95/AI95 -> 0.26915564
A96: 45139 | B96: =datos!R101/1000 -> 102.77 | C96: =datos!MA101 -> 460.4 | D96: =datos!AI101 -> 178.9191 | E96: =datos!MP101 -> 671.9 | F96: =(datos!AD101/1000)/PP!$F$2 -> 102.47021 | G96: =datos!MH101 -> 861.81 | H96: =datos!BK101/$H$2 -> 1687.0395 | I96: =datos!NB101 -> 2509.5 | J96: =datos!BR101/$J$2 -> 680.12917 | K96: =datos!NE101 -> 1688 | L96: =datos!BO101*$L$2 -> 538.3 | M96: =datos!NA101 -> 798.1 | N96: =datos!BS101*$N$2 -> 529.2 | O96: =datos!ND101 -> 2750 | P96: =(datos!AG101/1000)/$P$2 -> 352.94118 | Q96: =datos!MY101*$Q$2 -> 1530.04 | R96: =datos!BN101 -> 111.1 | S96: 0.038 | T96: 1539.08 | U96: =T96*S96 -> 58.48504 | V96: =datos!NC101+U96 -> 415.69504 | W96: =datos!AV101*W$4 -> 5458.4848 | X96: =W96*X$4 -> 436.67879 | Y96: =Y97/(1+(datos!G102/datos!G101-1)) -> 90.89035 | AA96: =AA$97/(1+Z$94) -> 202.04911 | AB96: =(W96-X96-Y96-AA96)/AB$3 -> 236.44333 | AC96: =datos!MJ101 -> 539.83 | AD96: =datos!BB101*AD$4 -> 2565.2584 | AE96: =AD96*AE$4 -> 205.22067 | AF96: =Y96 -> 90.89035 | AG96: =AA96 -> 202.04911 | AH96: =(AD96-AE96-AF96-AG96)/AH$3 -> 114.83879 | AI96: =AVERAGE(datos!ML101,datos!MM101,datos!MN101,datos!MO101) -> 409.08 | AK96: =A96 -> 45139 | AL96: =B96/C96 -> 0.22321894 | AM96: =D96/E96 -> 0.26628829 | AN96: =F96/G96 -> 0.11890116 | AO96: =H96/I96 -> 0.6722612 | AP96: =J96/K96 -> 0.40292012 | AQ96: =L96/M96 -> 0.67447688 | AR96: =N96/O96 -> 0.19243636 | AS96: =P96/Q96 -> 0.23067448 | AT96: =R96/V96 -> 0.26726323 | AU96: =AB96/AC96 -> 0.43799591 | AV96: =AH96/AI96 -> 0.28072454
A97: 45170 | B97: =datos!R102/1000 -> 160 | C97: =datos!MA102 -> 582.04 | D97: =datos!AI102 -> 197.5374 | E97: =datos!MP102 -> 734.03 | F97: =(datos!AD102/1000)/PP!$F$2 -> 103.52161 | G97: =datos!MH102 -> 980.2 | H97: =datos!BK102/$H$2 -> 1661.9306 | I97: =datos!NB102 -> 2953.9 | J97: =datos!BR102/$J$2 -> 796.66667 | K97: =datos!NE102 -> 1868.5 | L97: =datos!BO102*$L$2 -> 538.3 | M97: =datos!NA102 -> 945 | N97: =datos!BS102*$N$2 -> 529.2 | O97: =datos!ND102 -> 3000 | P97: =(datos!AG102/1000)/$P$2 -> 352.94118 | Q97: =datos!MY102*$Q$2 -> 1711.84 | R97: =datos!BN102 -> 118.36 | S97: 0.0376 | T97: 1649.26 | U97: =T97*S97 -> 62.012176 | V97: =datos!NC102+U97 -> 443.94218 | W97: =datos!AV102*W$4 -> 4980 | X97: =W97*X$4 -> 398.4 | Y97: =Y98/(1+(datos!G103/datos!G102-1)) -> 102.47672 | Z97: =AZ11 -> 0.37000267 | AA97: =AA$101/(1+Z$97) -> 262.66339 | AB97: =(W97-X97-Y97-AA97)/AB$3 -> 210.82299 | AC97: =datos!MJ102 -> 616.42 | AD97: =datos!BB102*AD$4 -> 2654.0574 | AE97: =AD97*AE$4 -> 212.32459 | AF97: =Y97 -> 102.47672 | AG97: =AA97 -> 262.66339 | AH97: =(AD97-AE97-AF97-AG97)/AH$3 -> 115.36626 | AI97: =AVERAGE(datos!ML102,datos!MM102,datos!MN102,datos!MO102) -> 415.08 | AK97: =A97 -> 45170 | AL97: =B97/C97 -> 0.2748952 | AM97: =D97/E97 -> 0.26911352 | AN97: =F97/G97 -> 0.10561274 | AO97: =H97/I97 -> 0.56262249 | AP97: =J97/K97 -> 0.42636696 | AQ97: =L97/M97 -> 0.56962963 | AR97: =N97/O97 -> 0.1764 | AS97: =P97/Q97 -> 0.2061765 | AT97: =R97/V97 -> 0.2666113 | AU97: =AB97/AC97 -> 0.34201193 | AV97: =AH97/AI97 -> 0.27793741
A98: 45200 | B98: =datos!R103/1000 -> 210 | C98: =datos!MA103 -> 789.18 | D98: =datos!AI103 -> 188.7512 | E98: =datos!MP103 -> 799.13 | F98: =(datos!AD103/1000)/PP!$F$2 -> 106.86907 | G98: =datos!MH103 -> 1076.98 | H98: =datos!BK103/$H$2 -> 1990.4583 | I98: =datos!NB103 -> 3028 | J98: =datos!BR103/$J$2 -> 1133.3333 | K98: =datos!NE103 -> 2083 | L98: =datos!BO103*$L$2 -> 573.93 | M98: =datos!NA103 -> 1039 | N98: =datos!BS103*$N$2 -> 642.6 | O98: =datos!ND103 -> 3800 | P98: =(datos!AG103/1000)/$P$2 -> 498.11765 | Q98: =datos!MY103*$Q$2 -> 1834.4 | R98: =datos!BN103 -> 130.17 | S98: 0.037 | T98: 1834.52 | U98: =T98*S98 -> 67.87724 | V98: =datos!NC103+U98 -> 481.17724 | W98: =datos!AV103*W$4 -> 4310.0962 | X98: =W98*X$4 -> 344.80769 | Y98: =Y99/(1+(datos!G104/datos!G103-1)) -> 110.98644 | AA98: =AA$101/(1+Z$97) -> 262.66339 | AB98: =(W98-X98-Y98-AA98)/AB$3 -> 179.58193 | AC98: =datos!MJ103 -> 604.95 | AD98: =datos!BB103*AD$4 -> 3362.906 | AE98: =AD98*AE$4 -> 269.03248 | AF98: =Y98 -> 110.98644 | AG98: =AA98 -> 262.66339 | AH98: =(AD98-AE98-AF98-AG98)/AH$3 -> 151.12354 | AI98: =AVERAGE(datos!ML103,datos!MM103,datos!MN103,datos!MO103) -> 476.20333 | AK98: =A98 -> 45200 | AL98: =B98/C98 -> 0.26609899 | AM98: =D98/E98 -> 0.23619586 | AN98: =F98/G98 -> 0.09923032 | AO98: =H98/I98 -> 0.65735081 | AP98: =J98/K98 -> 0.54408705 | AQ98: =L98/M98 -> 0.55238691 | AR98: =N98/O98 -> 0.16910526 | AS98: =P98/Q98 -> 0.27154255 | AT98: =R98/V98 -> 0.27052402 | AU98: =AB98/AC98 -> 0.29685417 | AV98: =AH98/AI98 -> 0.31735086
A99: 45231 | B99: =datos!R104/1000 -> 280 | C99: =datos!MA104 -> 1020.69 | D99: =datos!AI104 -> 216.46 | E99: =datos!MP104 -> 906.93 | F99: =(datos!AD104/1000)/PP!$F$2 -> 105.42092 | G99: =datos!MH104 -> 1244.72 | H99: =datos!BK104/$H$2 -> 2225.6534 | I99: =datos!NB104 -> 3475 | J99: =datos!BR104/$J$2 -> 1125.0967 | K99: =datos!NE104 -> 2442 | L99: =datos!BO104*$L$2 -> 640.64 | M99: =datos!NA104 -> 1190 | N99: =datos!BS104*$N$2 -> 793.8 | O99: =datos!ND104 -> 5250 | P99: =(datos!AG104/1000)/$P$2 -> 498.11765 | Q99: =datos!MY104*$Q$2 -> 2138.54 | R99: =datos!BN104 -> 150.01 | S99: 0.0369 | T99: 2127.93 | U99: =T99*S99 -> 78.520617 | V99: =datos!NC104+U99 -> 535.62062 | W99: =datos!AV104*W$4 -> 4627.7273 | X99: =W99*X$4 -> 370.21818 | Y99: =Y100/(1+(datos!G105/datos!G104-1)) -> 125.20322 | AA99: =AA$101/(1+Z$97) -> 262.66339 | AB99: =(W99-X99-Y99-AA99)/AB$3 -> 193.48212 | AC99: =datos!MJ104 -> 621.43 | AD99: =datos!BB104*AD$4 -> 4048.0092 | AE99: =AD99*AE$4 -> 323.84074 | AF99: =Y99 -> 125.20322 | AG99: =AA99 -> 262.66339 | AH99: =(AD99-AE99-AF99-AG99)/AH$3 -> 185.3501 | AI99: =AVERAGE(datos!ML104,datos!MM104,datos!MN104,datos!MO104) -> 605.72 | AK99: =A99 -> 45231 | AL99: =B99/C99 -> 0.27432423 | AM99: =D99/E99 -> 0.23867333 | AN99: =F99/G99 -> 0.084694486 | AO99: =H99/I99 -> 0.64047579 | AP99: =J99/K99 -> 0.46072755 | AQ99: =L99/M99 -> 0.53835294 | AR99: =N99/O99 -> 0.1512 | AS99: =P99/Q99 -> 0.23292417 | AT99: =R99/V99 -> 0.28006764 | AU99: =AB99/AC99 -> 0.31134983 | AV99: =AH99/AI99 -> 0.30599964
A100: 45261 | B100: =datos!R105/1000 -> 360 | C100: =datos!MA105 -> 1557.53 | D100: =datos!AI105 -> 247.58 | E100: =datos!MP105 -> 1189.79 | F100: =(datos!AD105/1000)/PP!$F$2 -> 220.96233 | G100: =datos!MH105 -> 1534.79 | H100: =datos!BK105/$H$2 -> 3235.5445 | I100: =datos!NB105 -> 5052 | J100: =datos!BR105/$J$2 -> 1553.9167 | K100: =datos!NE105 -> 3395 | L100: =datos!BO105*$L$2 -> 713.3 | M100: =datos!NA105 -> 1448 | N100: =datos!BS105*$N$2 -> 1134 | O100: =datos!ND105 -> 6240 | P100: =(datos!AG105/1000)/$P$2 -> 617.64706 | Q100: =datos!MY105*$Q$2 -> 2794.38 | R100: =datos!BN105 -> 193.65 | S100: 0.0367 | T100: 2775.22 | U100: =T100*S100 -> 101.85057 | V100: =datos!NC105+U100 -> 716.51057 | W100: =datos!AV105*W$4 -> 6385.8974 | X100: =W100*X$4 -> 510.87179 | Y100: =Y101/(1+(datos!G106/datos!G105-1)) -> 157.08706 | AA100: =AA$101/(1+Z$97) -> 262.66339 | AB100: =(W100-X100-Y100-AA100)/AB$3 -> 272.76376 | AC100: =datos!MJ105 -> 715.39 | AD100: =datos!BB105*AD$4 -> 4469.7099 | AE100: =AD100*AE$4 -> 357.57679 | AF100: =Y100 -> 157.08706 | AG100: =AA100 -> 262.66339 | AH100: =(AD100-AE100-AF100-AG100)/AH$3 -> 205.13237 | AI100: =AVERAGE(datos!ML105,datos!MM105,datos!MN105,datos!MO105) -> 556.70667 | AK100: =A100 -> 45261 | AL100: =B100/C100 -> 0.23113519 | AM100: =D100/E100 -> 0.20808714 | AN100: =F100/G100 -> 0.1439691 | AO100: =H100/I100 -> 0.64044823 | AP100: =J100/K100 -> 0.45770741 | AQ100: =L100/M100 -> 0.4926105 | AR100: =N100/O100 -> 0.18173077 | AS100: =P100/Q100 -> 0.22103188 | AT100: =R100/V100 -> 0.27026817 | AU100: =AB100/AC100 -> 0.3812798 | AV100: =AH100/AI100 -> 0.36847479
A101: 45292 | B101: =datos!R106/1000 -> 430 | C101: =datos!MA106 -> 2046.61 | D101: =datos!AI106 -> 325.15 | E101: =datos!MP106 -> 1442.1 | F101: =(datos!AD106/1000)/PP!$F$2 -> 222.32971 | G101: =datos!MH106 -> 1790.62 | H101: =datos!BK106/$H$2 -> 3355.9347 | I101: =datos!NB106 -> 5864 | J101: =datos!BR106/$J$2 -> 1887.8958 | K101: =datos!NE106 -> 4429 | L101: =datos!BO106*$L$2 -> 778.81288 | M101: =datos!NA106 -> 1835 | N101: =datos!BS106*$N$2 -> 1209.6 | O101: =datos!ND106 -> 7000 | P101: =(datos!AG106/1000)/$P$2 -> 735.29412 | Q101: =datos!MY106*$Q$2 -> 3398.44 | R101: =datos!BN106 -> 243.92 | S101: 0.0364 | T101: 3515.24 | U101: =T101*S101 -> 127.95474 | V101: =datos!NC106+U101 -> 970.19474 | W101: =datos!AV106*W$4 -> 5064.486 | X101: =W101*X$4 -> 405.15888 | Y101: =Y102/(1+(datos!G107/datos!G106-1)) -> 189.46934 | Z101: =AZ12 -> 0.81249762 | AA101: =AA$103/(1+Z$101) -> 359.84954 | AB101: =(W101-X101-Y101-AA101)/AB$3 -> 205.50041 | AC101: =datos!MJ106 -> 721.76 | AD101: =datos!BB106*AD$4 -> 5632.3004 | AE101: =AD101*AE$4 -> 450.58403 | AF101: =Y101 -> 189.46934 | AG101: =AA101 -> 359.84954 | AH101: =(AD101-AE101-AF101-AG101)/AH$3 -> 257.35542 | AI101: =AVERAGE(datos!ML106,datos!MM106,datos!MN106,datos!MO106) -> 579.64667 | AK101: =A101 -> 45292 | AL101: =B101/C101 -> 0.21010354 | AM101: =D101/E101 -> 0.2254698 | AN101: =F101/G101 -> 0.12416354 | AO101: =H101/I101 -> 0.57229445 | AP101: =J101/K101 -> 0.42625781 | AQ101: =L101/M101 -> 0.42442119 | AR101: =N101/O101 -> 0.1728 | AS101: =P101/Q101 -> 0.21636225 | AT101: =R101/V101 -> 0.25141344 | AU101: =AB101/AC101 -> 0.28472125 | AV101: =AH101/AI101 -> 0.44398671
A102: 45323 | B102: =datos!R107/1000 -> 430 | C102: =datos!MA107 -> 2355.31 | D102: =datos!AI107 -> 362.46 | E102: =datos!MP107 -> 1674.35 | F102: =(datos!AD107/1000)/PP!$F$2 -> 216.49818 | G102: =datos!MH107 -> 1942.55 | H102: =datos!BK107/$H$2 -> 3943.2781 | I102: =datos!NB107 -> 6058 | J102: =datos!BR107/$J$2 -> 1741.3208 | K102: =datos!NE107 -> 4331 | L102: =datos!BO107*$L$2 -> 1016.904 | M102: =datos!NA107 -> 1934 | N102: =datos!BS107*$N$2 -> 1209.6 | O102: =datos!ND107 -> 7350 | P102: =(datos!AG107/1000)/$P$2 -> 882.35294 | Q102: =datos!MY107*$Q$2 -> 3667.5 | R102: =datos!BN107 -> 291.69 | S102: 0.0367 | T102: 4172.76 | U102: =T102*S102 -> 153.14029 | V102: =datos!NC107+U102 -> 1172.0103 | W102: =datos!AV107*W$4 -> 6744.186 | X102: =W102*X$4 -> 539.53488 | Y102: =Y103/(1+(datos!G108/datos!G107-1)) -> 214.55636 | AA102: =AA$103/(1+Z$101) -> 359.84954 | AB102: =(W102-X102-Y102-AA102)/AB$3 -> 281.51226 | AC102: =datos!MJ107 -> 749.73 | AD102: =datos!BB107*AD$4 -> 6890.8514 | AE102: =AD102*AE$4 -> 551.26811 | AF102: =Y102 -> 214.55636 | AG102: =AA102 -> 359.84954 | AH102: =(AD102-AE102-AF102-AG102)/AH$3 -> 320.28763 | AI102: =AVERAGE(datos!ML107,datos!MM107,datos!MN107,datos!MO107) -> 707.54667 | AK102: =A102 -> 45323 | AL102: =B102/C102 -> 0.1825662 | AM102: =D102/E102 -> 0.21647804 | AN102: =F102/G102 -> 0.1114505 | AO102: =H102/I102 -> 0.65092079 | AP102: =J102/K102 -> 0.40205976 | AQ102: =L102/M102 -> 0.52580352 | AR102: =N102/O102 -> 0.16457143 | AS102: =P102/Q102 -> 0.24058703 | AT102: =R102/V102 -> 0.24888007 | AU102: =AB102/AC102 -> 0.37548486 | AV102: =AH102/AI102 -> 0.45267351
A103: 45352 | B103: =datos!R108/1000 -> 350 | C103: =datos!MA108 -> 2445.35 | D103: =datos!AI108 -> 417.6 | E103: =datos!MP108 -> 1771.02 | F103: =(datos!AD108/1000)/PP!$F$2 -> 215.1446 | G103: =datos!MH108 -> 2214.07 | H103: =datos!BK108/$H$2 -> 4163.4188 | I103: =datos!NB108 -> 6572 | J103: =datos!BR108/$J$2 -> 1833.3333 | K103: =datos!NE108 -> 4469 | L103: =datos!BO108*$L$2 -> 1127.553 | M103: =datos!NA108 -> 2234 | N103: =datos!BS108*$N$2 -> 1209.6 | O103: =datos!ND108 -> 7350 | P103: =(datos!AG108/1000)/$P$2 -> 1088.2353 | Q103: =datos!MY108*$Q$2 -> 3960.6 | R103: =datos!BN108 -> 331.68 | S103: 0.0374 | T103: 4661.86 | U103: =T103*S103 -> 174.35356 | V103: =datos!NC108+U103 -> 1385.0736 | W103: =datos!AV108*W$4 -> 6830.8333 | X103: =W103*X$4 -> 546.46667 | Y103: =Y104/(1+(datos!G109/datos!G108-1)) -> 238.17824 | Z103: =AZ13 -> 0.24620105 | AA103: =AA$107/(1+Z$103) -> 652.22644 | AB103: =(W103-X103-Y103-AA103)/AB$3 -> 269.6981 | AC103: =datos!MJ108 -> 748.7 | AD103: =datos!BB108*AD$4 -> 8543.7713 | AE103: =AD103*AE$4 -> 683.5017 | AF103: =Y103 -> 238.17824 | AG103: =AA103 -> 652.22644 | AH103: =(AD103-AE103-AF103-AG103)/AH$3 -> 387.21471 | AI103: =AVERAGE(datos!ML108,datos!MM108,datos!MN108,datos!MO108) -> 913.71667 | AK103: =A103 -> 45352 | AL103: =B103/C103 -> 0.1431288 | AM103: =D103/E103 -> 0.23579632 | AN103: =F103/G103 -> 0.097171542 | AO103: =H103/I103 -> 0.63350864 | AP103: =J103/K103 -> 0.41023346 | AQ103: =L103/M103 -> 0.50472381 | AR103: =N103/O103 -> 0.16457143 | AS103: =P103/Q103 -> 0.27476526 | AT103: =R103/V103 -> 0.23946743 | AU103: =AB103/AC103 -> 0.36022185 | AV103: =AH103/AI103 -> 0.42377985
A104: 45383 | B104: =datos!R109/1000 -> 306.57872 | C104: =datos!MA109 -> 2422.83 | D104: =datos!AI109 -> 410.59 | E104: =datos!MP109 -> 1957.46 | F104: =(datos!AD109/1000)/PP!$F$2 -> 232.50969 | G104: =datos!MH109 -> 2376.84 | H104: =datos!BK109/$H$2 -> 4435.9528 | I104: =datos!NB109 -> 6795 | J104: =datos!BR109/$J$2 -> 1604.05 | K104: =datos!NE109 -> 4462 | L104: =datos!BO109*$L$2 -> 1252.727 | M104: =datos!NA109 -> 2425 | N104: =datos!BS109*$N$2 -> 1323 | O104: =datos!ND109 -> 7000 | P104: =(datos!AG109/1000)/$P$2 -> 1102.9412 | Q104: =datos!MY109*$Q$2 -> 3976.9 | R104: =datos!BN109 -> 354.87 | S104: 0.0385 | T104: 4847.89 | U104: =T104*S104 -> 186.64377 | V104: =datos!NC109+U104 -> 1462.9238 | W104: =datos!AV109*W$4 -> 6228.9062 | X104: =W104*X$4 -> 498.3125 | Y104: =Y105/(1+(datos!G110/datos!G109-1)) -> 259.2141 | AA104: =AA$107/(1+Z$103) -> 652.22644 | AB104: =(W104-X104-Y104-AA104)/AB$3 -> 240.95766 | AC104: =datos!MJ109 -> 734.05 | AD104: =datos!BB109*AD$4 -> 10288.408 | AE104: =AD104*AE$4 -> 823.07266 | AF104: =Y104 -> 259.2141 | AG104: =AA104 -> 652.22644 | AH104: =(AD104-AE104-AF104-AG104)/AH$3 -> 475.21639 | AI104: =AVERAGE(datos!ML109,datos!MM109,datos!MN109,datos!MO109) -> 1254.3267 | AK104: =A104 -> 45383 | AL104: =B104/C104 -> 0.12653744 | AM104: =D104/E104 -> 0.20975652 | AN104: =F104/G104 -> 0.097823029 | AO104: =H104/I104 -> 0.65282602 | AP104: =J104/K104 -> 0.35949126 | AQ104: =L104/M104 -> 0.51658845 | AR104: =N104/O104 -> 0.189 | AS104: =P104/Q104 -> 0.27733691 | AT104: =R104/V104 -> 0.24257587 | AU104: =AB104/AC104 -> 0.32825783 | AV104: =AH104/AI104 -> 0.37886175
A105: 45413 | B105: =datos!R110/1000 -> 320.37612 | C105: =datos!MA110 -> 2351.11 | D105: =datos!AI110 -> 420.76 | E105: =datos!MP110 -> 2005.07 | F105: =(datos!AD110/1000)/PP!$F$2 -> 263.25743 | G105: =datos!MH110 -> 2501.86 | H105: =datos!BK110/$H$2 -> 4499.5962 | I105: =datos!NB110 -> 6833 | J105: =datos!BR110/$J$2 -> 1545.5833 | K105: =datos!NE110 -> 4420 | L105: =datos!BO110*$L$2 -> 1181.376 | M105: =datos!NA110 -> 2539 | N105: =datos!BS110*$N$2 -> 1323 | O105: =datos!ND110 -> 7400 | P105: =(datos!AG110/1000)/$P$2 -> 970.58824 | Q105: =datos!MY110*$Q$2 -> 4241.68 | R105: =datos!BN110 -> 389.33 | S105: 0.039 | T105: 5230.35 | U105: =T105*S105 -> 203.98365 | V105: =datos!NC110+U105 -> 1524.0336 | W105: =datos!AV110*W$4 -> 6452.2727 | X105: =W105*X$4 -> 516.18182 | Y105: =Y106/(1+(datos!G111/datos!G110-1)) -> 270.03973 | AA105: =AA$107/(1+Z$103) -> 652.22644 | AB105: =(W105-X105-Y105-AA105)/AB$3 -> 250.69124 | AC105: =datos!MJ110 -> 714.83 | AD105: =datos!BB110*AD$4 -> 15516.242 | AE105: =AD105*AE$4 -> 1241.2994 | AF105: =Y105 -> 270.03973 | AG105: =AA105 -> 652.22644 | AH105: =(AD105-AE105-AF105-AG105)/AH$3 -> 741.81538 | AI105: =AVERAGE(datos!ML110,datos!MM110,datos!MN110,datos!MO110) -> 1814.29 | AK105: =A105 -> 45413 | AL105: =B105/C105 -> 0.1362659 | AM105: =D105/E105 -> 0.20984804 | AN105: =F105/G105 -> 0.10522469 | AO105: =H105/I105 -> 0.65850961 | AP105: =J105/K105 -> 0.34967949 | AQ105: =L105/M105 -> 0.46529185 | AR105: =N105/O105 -> 0.17878378 | AS105: =P105/Q105 -> 0.22882165 | AT105: =R105/V105 -> 0.25546024 | AU105: =AB105/AC105 -> 0.3507005 | AV105: =AH105/AI105 -> 0.40887365
A106: 45444 | B106: =datos!R111/1000 -> 381.84458 | C106: =datos!MA111 -> 2336.91 | D106: =datos!AI111 -> 467.16 | E106: =datos!MP111 -> 2008 | F106: =(datos!AD111/1000)/PP!$F$2 -> 252.8104 | G106: =datos!MH111 -> 2597.5 | H106: =datos!BK111/$H$2 -> 4554.6665 | I106: =datos!NB111 -> 7062 | J106: =datos!BR111/$J$2 -> 1540.05 | K106: =datos!NE111 -> 4495 | L106: =datos!BO111*$L$2 -> 1176.595 | M106: =datos!NA111 -> 2504 | N106: =datos!BS111*$N$2 -> 1474.2 | O106: =datos!ND111 -> 7400 | P106: =(datos!AG111/1000)/$P$2 -> 882.35294 | Q106: =datos!MY111*$Q$2 -> 4460.6 | R106: =datos!BN111 -> 403.38 | S106: 0.0383 | T106: 5512.23 | U106: =T106*S106 -> 211.11841 | V106: =datos!NC111+U106 -> 1566.5484 | W106: =datos!AV111*W$4 -> 7119.2982 | X106: =W106*X$4 -> 569.54386 | Y106: =Y107/(1+(datos!G112/datos!G111-1)) -> 282.39898 | AA106: =AA$107/(1+Z$103) -> 652.22644 | AB106: =(W106-X106-Y106-AA106)/AB$3 -> 280.75645 | AC106: =datos!MJ111 -> 708.8 | AD106: =datos!BB111*AD$4 -> 13650.522 | AE106: =AD106*AE$4 -> 1092.0417 | AF106: =Y106 -> 282.39898 | AG106: =AA106 -> 652.22644 | AH106: =(AD106-AE106-AF106-AG106)/AH$3 -> 645.76969 | AI106: =AVERAGE(datos!ML111,datos!MM111,datos!MN111,datos!MO111) -> 1733.3467 | AK106: =A106 -> 45444 | AL106: =B106/C106 -> 0.16339721 | AM106: =D106/E106 -> 0.2326494 | AN106: =F106/G106 -> 0.097328353 | AO106: =H106/I106 -> 0.64495419 | AP106: =J106/K106 -> 0.34261402 | AQ106: =L106/M106 -> 0.46988618 | AR106: =N106/O106 -> 0.19921622 | AS106: =P106/Q106 -> 0.19781037 | AT106: =R106/V106 -> 0.25749603 | AU106: =AB106/AC106 -> 0.39610108 | AV106: =AH106/AI106 -> 0.37255657
A107: 45474 | B107: =datos!R112/1000 -> 387.04 | C107: =datos!MA112 -> 2301.88 | D107: =datos!AI112 -> 444.93 | E107: =datos!MP112 -> 2047.63 | F107: =(datos!AD112/1000)/PP!$F$2 -> 249.18798 | G107: =datos!MH112 -> 2663.51 | H107: =datos!BK112/$H$2 -> 4691.0413 | I107: =datos!NB112 -> 7106 | J107: =datos!BR112/$J$2 -> 1683.3583 | K107: =datos!NE112 -> 4593 | L107: =datos!BO112*$L$2 -> 1201.466 | M107: =datos!NA112 -> 2553 | N107: =datos!BS112*$N$2 -> 1701 | O107: =datos!ND112 -> 8690 | P107: =(datos!AG112/1000)/$P$2 -> 823.52941 | Q107: =datos!MY112*$Q$2 -> 4512.16 | R107: =datos!BN112 -> 411.7 | S107: 0.0382 | T107: 5628.08 | U107: =T107*S107 -> 214.99266 | V107: =datos!NC112+U107 -> 1520.0627 | W107: =datos!AV112*W$4 -> 9727.9661 | X107: =W107*X$4 -> 778.23729 | Y107: =Y108/(1+(datos!G113/datos!G112-1)) -> 293.78297 | Z107: =AZ14 -> 0.16999932 | AA107: =AA$113/(1+Z$107) -> 812.80527 | AB107: =(W107-X107-Y107-AA107)/AB$3 -> 392.15703 | AC107: =datos!MJ112 -> 913.17 | AD107: =datos!BB112*AD$4 -> 19145.754 | AE107: =AD107*AE$4 -> 1531.6603 | AF107: =Y107 -> 293.78297 | AG107: =AA107 -> 812.80527 | AH107: =(AD107-AE107-AF107-AG107)/AH$3 -> 917.08362 | AI107: =AVERAGE(datos!ML112,datos!MM112,datos!MN112,datos!MO112) -> 2016.4567 | AK107: =A107 -> 45474 | AL107: =B107/C107 -> 0.16814082 | AM107: =D107/E107 -> 0.21729023 | AN107: =F107/G107 -> 0.093556238 | AO107: =H107/I107 -> 0.66015217 | AP107: =J107/K107 -> 0.36650519 | AQ107: =L107/M107 -> 0.47060948 | AR107: =N107/O107 -> 0.19574223 | AS107: =P107/Q107 -> 0.18251334 | AT107: =R107/V107 -> 0.2708441 | AU107: =AB107/AC107 -> 0.42944581 | AV107: =AH107/AI107 -> 0.45479957
A108: 45505 | B108: =datos!R113/1000 -> 400 | C108: =datos!MA113 -> 2288.26 | D108: =datos!AI113 -> 464.92 | E108: =datos!MP113 -> 2061.98 | F108: =(datos!AD113/1000)/PP!$F$2 -> 286.53428 | G108: =datos!MH113 -> 2774.95 | H108: =datos!BK113/$H$2 -> 4658.0944 | I108: =datos!NB113 -> 7233 | J108: =datos!BR113/$J$2 -> 2051.15 | K108: =datos!NE113 -> 4961 | L108: =datos!BO113*$L$2 -> 1423.597 | M108: =datos!NA113 -> 2717 | N108: =datos!BS113*$N$2 -> 1738.8 | O108: =datos!ND113 -> 8700 | P108: =(datos!AG113/1000)/$P$2 -> 617.64706 | Q108: =datos!MY113*$Q$2 -> 4480.84 | R108: =datos!BN113 -> 418.74 | S108: 0.038 | T108: 5762.74 | U108: =T108*S108 -> 218.98412 | V108: =datos!NC113+U108 -> 1572.4241 | W108: =datos!AV113*W$4 -> 13529.268 | X108: =W108*X$4 -> 1082.3415 | Y108: =Y109/(1+(datos!G114/datos!G113-1)) -> 306.03856 | AA108: =AA$113/(1+Z$107) -> 812.80527 | AB108: =(W108-X108-Y108-AA108)/AB$3 -> 566.40415 | AC108: =datos!MJ113 -> 1274.15 | AD108: =datos!BB113*AD$4 -> 15363.557 | AE108: =AD108*AE$4 -> 1229.0845 | AF108: =Y108 -> 306.03856 | AG108: =AA108 -> 812.80527 | AH108: =(AD108-AE108-AF108-AG108)/AH$3 -> 723.09047 | AI108: =AVERAGE(datos!ML113,datos!MM113,datos!MN113,datos!MO113) -> 1763.4267 | AK108: =A108 -> 45505 | AL108: =B108/C108 -> 0.17480531 | AM108: =D108/E108 -> 0.2254726 | AN108: =F108/G108 -> 0.10325746 | AO108: =H108/I108 -> 0.64400586 | AP108: =J108/K108 -> 0.41345495 | AQ108: =L108/M108 -> 0.52395915 | AR108: =N108/O108 -> 0.19986207 | AS108: =P108/Q108 -> 0.1378418 | AT108: =R108/V108 -> 0.2663022 | AU108: =AB108/AC108 -> 0.44453491 | AV108: =AH108/AI108 -> 0.4100485
A109: 45536 | B109: =datos!R114/1000 -> 400 | C109: =datos!MA114 -> 2262 | D109: =datos!AI114 -> 410.52 | E109: =datos!MP114 -> 2122.36 | F109: =(datos!AD114/1000)/PP!$F$2 -> 265.69859 | G109: =datos!MH114 -> 2878.01 | H109: =datos!BK114/$H$2 -> 4526.0413 | I109: =datos!NB114 -> 7271 | J109: =datos!BR114/$J$2 -> 2250.5833 | K109: =datos!NE114 -> 5368 | L109: =datos!BO114*$L$2 -> 1383.116 | M109: =datos!NA114 -> 2834 | N109: =datos!BS114*$N$2 -> 1701 | O109: =datos!ND114 -> 8700 | P109: =(datos!AG114/1000)/$P$2 -> 617.64706 | Q109: =datos!MY114*$Q$2 -> 4391.7 | R109: =datos!BN114 -> 426.18 | S109: 0.0375 | T109: 5937.24 | U109: =T109*S109 -> 222.6465 | V109: =datos!NC114+U109 -> 1580.7465 | W109: =datos!AV114*W$4 -> 12272.65 | X109: =W109*X$4 -> 981.81197 | Y109: =Y110/(1+(datos!G115/datos!G114-1)) -> 316.6557 | AA109: =AA$113/(1+Z$107) -> 812.80527 | AB109: =(W109-X109-Y109-AA109)/AB$3 -> 508.06883 | AC109: =datos!MJ114 -> 1326.9 | AD109: =datos!BB114*AD$4 -> 15126.974 | AE109: =AD109*AE$4 -> 1210.1579 | AF109: =Y109 -> 316.6557 | AG109: =AA109 -> 812.80527 | AH109: =(AD109-AE109-AF109-AG109)/AH$3 -> 710.40863 | AI109: =AVERAGE(datos!ML114,datos!MM114,datos!MN114,datos!MO114) -> 1843.7833 | AK109: =A109 -> 45536 | AL109: =B109/C109 -> 0.17683466 | AM109: =D109/E109 -> 0.19342619 | AN109: =F109/G109 -> 0.092320247 | AO109: =H109/I109 -> 0.62247852 | AP109: =J109/K109 -> 0.41925919 | AQ109: =L109/M109 -> 0.48804375 | AR109: =N109/O109 -> 0.19551724 | AS109: =P109/Q109 -> 0.14063963 | AT109: =R109/V109 -> 0.2696068 | AU109: =AB109/AC109 -> 0.38289911 | AV109: =AH109/AI109 -> 0.38529941
A110: 45566 | B110: =datos!R115/1000 -> 380 | C110: =datos!MA115 -> 2285.88 | D110: =datos!AI115 -> 458.45 | E110: =datos!MP115 -> 2162.88 | F110: =(datos!AD115/1000)/PP!$F$2 -> 260.4 | G110: =datos!MH115 -> 2948.01 | H110: =datos!BK115/$H$2 -> 4437.4841 | I110: =datos!NB115 -> 7585 | J110: =datos!BR115/$J$2 -> 2380.3667 | K110: =datos!NE115 -> 5682 | L110: =datos!BO115*$L$2 -> 1381.282 | M110: =datos!NA115 -> 2862 | N110: =datos!BS115*$N$2 -> 1833.3 | O110: =datos!ND115 -> 9800 | P110: =(datos!AG115/1000)/$P$2 -> 617.64706 | Q110: =datos!MY115*$Q$2 -> 4399.58 | R110: =datos!BN115 -> 434.86 | S110: 0.0369 | T110: 6142.43 | U110: =T110*S110 -> 226.65567 | V110: =datos!NC115+U110 -> 1617.2857 | W110: =datos!AV115*W$4 -> 15237 | X110: =W110*X$4 -> 1218.96 | Y110: =Y111/(1+(datos!G116/datos!G115-1)) -> 325.1832 | AA110: =AA$113/(1+Z$107) -> 812.80527 | AB110: =(W110-X110-Y110-AA110)/AB$3 -> 644.00258 | AC110: =datos!MJ115 -> 1393.92 | AD110: =datos!BB115*AD$4 -> 13480.329 | AE110: =AD110*AE$4 -> 1078.4263 | AF110: =Y110 -> 325.1832 | AG110: =AA110 -> 812.80527 | AH110: =(AD110-AE110-AF110-AG110)/AH$3 -> 625.77299 | AI110: =AVERAGE(datos!ML115,datos!MM115,datos!MN115,datos!MO115) -> 1804.6167 | AK110: =A110 -> 45566 | AL110: =B110/C110 -> 0.16623795 | AM110: =D110/E110 -> 0.21196275 | AN110: =F110/G110 -> 0.088330772 | AO110: =H110/I110 -> 0.58503416 | AP110: =J110/K110 -> 0.41893113 | AQ110: =L110/M110 -> 0.48262823 | AR110: =N110/O110 -> 0.18707143 | AS110: =P110/Q110 -> 0.14038773 | AT110: =R110/V110 -> 0.26888262 | AU110: =AB110/AC110 -> 0.46200828 | AV110: =AH110/AI110 -> 0.34676228
A111: 45597 | B111: =datos!R116/1000 -> 350 | C111: =datos!MA116 -> 2273.69 | D111: =datos!AI116 -> 422.87 | E111: =datos!MP116 -> 2153.78 | F111: =(datos!AD116/1000)/PP!$F$2 -> 238.82908 | G111: =datos!MH116 -> 3040.97 | H111: =datos!BK116/$H$2 -> 4834.2332 | I111: =datos!NB116 -> 7696 | J111: =datos!BR116/$J$2 -> 2440.05 | K111: =datos!NE116 -> 5803 | L111: =datos!BO116*$L$2 -> 1496.432 | M111: =datos!NA116 -> 2889 | N111: =datos!BS116*$N$2 -> 1833.3 | O111: =datos!ND116 -> 9800 | P111: =(datos!AG116/1000)/$P$2 -> 485.29412 | Q111: =datos!MY116*$Q$2 -> 4471.48 | R111: =datos!BN116 -> 439.73 | S111: 0.0364 | T111: 6274.27 | U111: =T111*S111 -> 228.38343 | V111: =datos!NC116+U111 -> 1657.1234 | W111: =datos!AV116*W$4 -> 13858.4 | X111: =W111*X$4 -> 1108.672 | Y111: =Y112/(1+(datos!G117/datos!G116-1)) -> 333.07047 | AA111: =AA$113/(1+Z$107) -> 812.80527 | AB111: =(W111-X111-Y111-AA111)/AB$3 -> 580.19261 | AC111: =datos!MJ116 -> 1197.23 | AD111: =datos!BB116*AD$4 -> 11145.5 | AE111: =AD111*AE$4 -> 891.64 | AF111: =Y111 -> 333.07047 | AG111: =AA111 -> 812.80527 | AH111: =(AD111-AE111-AF111-AG111)/AH$3 -> 505.99913 | AI111: =AVERAGE(datos!ML116,datos!MM116,datos!MN116,datos!MO116) -> 1492.6267 | AK111: =A111 -> 45597 | AL111: =B111/C111 -> 0.15393479 | AM111: =D111/E111 -> 0.19633853 | AN111: =F111/G111 -> 0.078537139 | AO111: =H111/I111 -> 0.62814881 | AP111: =J111/K111 -> 0.42048079 | AQ111: =L111/M111 -> 0.51797577 | AR111: =N111/O111 -> 0.18707143 | AS111: =P111/Q111 -> 0.10853098 | AT111: =R111/V111 -> 0.26535742 | AU111: =AB111/AC111 -> 0.48461249 | AV111: =AH111/AI111 -> 0.33899912
A112: 45627 | B112: =datos!R117/1000 -> 300 | C112: =datos!MA117 -> 2190.58 | D112: =datos!AI117 -> 425.56 | E112: =datos!MP117 -> 2166.11 | F112: =(datos!AD117/1000)/PP!$F$2 -> 244.64396 | G112: =datos!MH117 -> 3095.49 | H112: =datos!BK117/$H$2 -> 5358.8634 | I112: =datos!NB117 -> 8995 | J112: =datos!BR117/$J$2 -> 2583.1333 | K112: =datos!NE117 -> 6416 | L112: =datos!BO117*$L$2 -> 1508.353 | M112: =datos!NA117 -> 3071 | N112: =datos!BS117*$N$2 -> 2268 | O112: =datos!ND117 -> 10990 | P112: =(datos!AG117/1000)/$P$2 -> 485.29412 | Q112: =datos!MY117*$Q$2 -> 4476.1 | R112: =datos!BN117 -> 441.1 | S112: 0.0364 | T112: 6296.65 | U112: =T112*S112 -> 229.19806 | V112: =datos!NC117+U112 -> 1683.7681 | W112: =datos!AV117*W$4 -> 5439.3617 | X112: =W112*X$4 -> 435.14894 | Y112: =Y113/(1+(datos!G118/datos!G117-1)) -> 342.07815 | AA112: =AA$113/(1+Z$107) -> 812.80527 | AB112: =(W112-X112-Y112-AA112)/AB$3 -> 192.46647 | AC112: =datos!MJ117 -> 1046.62 | AD112: =datos!BB117*AD$4 -> 10655.95 | AE112: =AD112*AE$4 -> 852.47603 | AF112: =Y112 -> 342.07815 | AG112: =AA112 -> 812.80527 | AH112: =(AD112-AE112-AF112-AG112)/AH$3 -> 480.47727 | AI112: =AVERAGE(datos!ML117,datos!MM117,datos!MN117,datos!MO117) -> 1219.9033 | AK112: =A112 -> 45627 | AL112: =B112/C112 -> 0.13695003 | AM112: =D112/E112 -> 0.19646278 | AN112: =F112/G112 -> 0.079032387 | AO112: =H112/I112 -> 0.59576025 | AP112: =J112/K112 -> 0.40260806 | AQ112: =L112/M112 -> 0.49116021 | AR112: =N112/O112 -> 0.20636943 | AS112: =P112/Q112 -> 0.10841896 | AT112: =R112/V112 -> 0.26197195 | AU112: =AB112/AC112 -> 0.18389336 | AV112: =AH112/AI112 -> 0.39386504
A113: 45658 | B113: =datos!R118/1000 -> 250 | C113: =datos!MA118 -> 2110.76 | D113: =datos!AI118 -> 416.9 | E113: =datos!MP118 -> 2189.77 | F113: =(datos!AD118/1000)/PP!$F$2 -> 249.83126 | G113: =datos!MH118 -> 3154.17 | H113: =datos!BK118/$H$2 -> 5625.4719 | I113: =datos!NB118 -> 9609 | J113: =datos!BR118/$J$2 -> 2670.51 | K113: =datos!NE118 -> 6714 | L113: =datos!BO118*$L$2 -> 1235.71 | M113: =datos!NA118 -> 3097 | N113: =datos!BS118*$N$2 -> 1965.6 | O113: =datos!ND118 -> 11490 | P113: =(datos!AG118/1000)/$P$2 -> 705.88235 | Q113: =datos!MY118*$Q$2 -> 4523.3 | R113: =datos!BN118 -> 444.11 | S113: 0.0364 | T113: 6355.69 | U113: =T113*S113 -> 231.34712 | V113: =datos!NC118+U113 -> 1714.4071 | W113: =datos!AV118*W$4 -> 3901.3333 | X113: =W113*X$4 -> 312.10667 | Y113: =Y114/(1+(datos!G119/datos!G118-1)) -> 349.64086 | Z113: =AZ15 -> 0.12000096 | AA113: =AA$121/(1+Z$121) -> 950.98162 | AB113: =(W113-X113-Y113-AA113)/AB$3 -> 114.43021 | AC113: =datos!MJ118 -> 842.73 | AD113: =datos!BB118*AD$4 -> 10262.768 | AE113: =AD113*AE$4 -> 821.0214 | AF113: =Y113 -> 349.64086 | AG113: =AA113 -> 950.98162 | AH113: =(AD113-AE113-AF113-AG113)/AH$3 -> 452.28465 | AI113: =AVERAGE(datos!ML118,datos!MM118,datos!MN118,datos!MO118) -> 1252.1367 | AK113: =A113 -> 45658 | AL113: =B113/C113 -> 0.11844075 | AM113: =D113/E113 -> 0.19038529 | AN113: =F113/G113 -> 0.079206656 | AO113: =H113/I113 -> 0.58543781 | AP113: =J113/K113 -> 0.39775246 | AQ113: =L113/M113 -> 0.39900226 | AR113: =N113/O113 -> 0.1710705 | AS113: =P113/Q113 -> 0.15605473 | AT113: =R113/V113 -> 0.25904582 | AU113: =AB113/AC113 -> 0.13578514 | AV113: =AH113/AI113 -> 0.36121029
A114: 45689 | B114: =datos!R119/1000 -> 240 | C114: =datos!MA119 -> 1937.98 | D114: =datos!AI119 -> 432.619 | E114: =datos!MP119 -> 2176.3 | F114: =(datos!AD119/1000)/PP!$F$2 -> 272.7924 | G114: =datos!MH119 -> 3212.93 | H114: =datos!BK119/$H$2 -> 6357.8403 | I114: =datos!NB119 -> 9866 | J114: =datos!BR119/$J$2 -> 2758.8722 | K114: =datos!NE119 -> 6734 | L114: =datos!BO119*$L$2 -> 1412.684 | M114: =datos!NA119 -> 3100 | N114: =datos!BS119*$N$2 -> 2192.4 | O114: =datos!ND119 -> 11700 | P114: =(datos!AG119/1000)/$P$2 -> 882.35294 | Q114: =datos!MY119*$Q$2 -> 4501.24 | R114: =datos!BN119 -> 447.42 | S114: 0.0372 | T114: 6287.64 | U114: =T114*S114 -> 233.90021 | V114: =datos!NC119+U114 -> 1730.5202 | W114: =datos!AV119*W$4 -> 5955.7377 | X114: =W114*X$4 -> 476.45902 | Y114: =Y115/(1+(datos!G120/datos!G119-1)) -> 358.03942 | AA114: =AA$121/(1+Z$121) -> 950.98162 | AB114: =(W114-X114-Y114-AA114)/AB$3 -> 208.51288 | AC114: =datos!MJ119 -> 790.79 | AD114: =datos!BB119*AD$4 -> 7712.2544 | AE114: =AD114*AE$4 -> 616.98035 | AF114: =Y114 -> 358.03942 | AG114: =AA114 -> 950.98162 | AH114: =(AD114-AE114-AF114-AG114)/AH$3 -> 321.4585 | AI114: =AVERAGE(datos!ML119,datos!MM119,datos!MN119,datos!MO119) -> 1083.72 | AK114: =A114 -> 45689 | AL114: =B114/C114 -> 0.12384029 | AM114: =D114/E114 -> 0.19878647 | AN114: =F114/G114 -> 0.084904559 | AO114: =H114/I114 -> 0.64441925 | AP114: =J114/K114 -> 0.40969293 | AQ114: =L114/M114 -> 0.45570452 | AR114: =N114/O114 -> 0.18738462 | AS114: =P114/Q114 -> 0.19602442 | AT114: =R114/V114 -> 0.25854653 | AU114: =AB114/AC114 -> 0.26367668 | AV114: =AH114/AI114 -> 0.29662505
A115: 45717 | B115: =datos!R120/1000 -> 250 | C115: =datos!MA120 -> 1920 | D115: =datos!AI120 -> 432.1034 | E115: =datos!MP120 -> 2158.11 | F115: =(datos!AD120/1000)/PP!$F$2 -> 283.52285 | G115: =datos!MH120 -> 3333.96 | H115: =datos!BK120/$H$2 -> 6692.3117 | I115: =datos!NB120 -> 10622 | J115: =datos!BR120/$J$2 -> 2742.5167 | K115: =datos!NE120 -> 6980 | L115: =datos!BO120*$L$2 -> 1673.098 | M115: =datos!NA120 -> 3234 | N115: =datos!BS120*$N$2 -> 2381.4 | O115: =datos!ND120 -> 11790 | P115: =(datos!AG120/1000)/$P$2 -> 838.23529 | Q115: =datos!MY120*$Q$2 -> 4451.64 | R115: =datos!BN120 -> 453.14 | S115: 0.0384 | T115: 6195.5 | U115: =T115*S115 -> 237.9072 | V115: =datos!NC120+U115 -> 1724.0972 | W115: =datos!AV120*W$4 -> 8870.5882 | X115: =W115*X$4 -> 709.64706 | Y115: =Y116/(1+(datos!G121/datos!G120-1)) -> 371.34641 | AA115: =AA$121/(1+Z$121) -> 950.98162 | AB115: =(W115-X115-Y115-AA115)/AB$3 -> 341.93066 | AC115: =datos!MJ120 -> 1013.58 | AD115: =datos!BB120*AD$4 -> 10851.256 | AE115: =AD115*AE$4 -> 868.10045 | AF115: =Y115 -> 371.34641 | AG115: =AA115 -> 950.98162 | AH115: =(AD115-AE115-AF115-AG115)/AH$3 -> 481.15706 | AI115: =AVERAGE(datos!ML120,datos!MM120,datos!MN120,datos!MO120) -> 1478.4233 | AK115: =A115 -> 45717 | AL115: =B115/C115 -> 0.13020833 | AM115: =D115/E115 -> 0.20022307 | AN115: =F115/G115 -> 0.085040868 | AO115: =H115/I115 -> 0.63004253 | AP115: =J115/K115 -> 0.3929107 | AQ115: =L115/M115 -> 0.51734632 | AR115: =N115/O115 -> 0.20198473 | AS115: =P115/Q115 -> 0.18829809 | AT115: =R115/V115 -> 0.26282741 | AU115: =AB115/AC115 -> 0.33734945 | AV115: =AH115/AI115 -> 0.32545283
A116: 45748 | B116: =datos!R121/1000 -> 230 | C116: =datos!MA121 -> 1851.68 | D116: =datos!AI121 -> 418.8491 | E116: =datos!MP121 -> 2220.1 | F116: =(datos!AD121/1000)/PP!$F$2 -> 295.07039 | G116: =datos!MH121 -> 3415.26 | H116: =datos!BK121/$H$2 -> 6678.7659 | I116: =datos!NB121 -> 10980 | J116: =datos!BR121/$J$2 -> 2735.3567 | K116: =datos!NE121 -> 7196 | L116: =datos!BO121*$L$2 -> 1790.418 | M116: =datos!NA121 -> 3580 | N116: =datos!BS121*$N$2 -> 2570.4 | O116: =datos!ND121 -> 11790 | P116: =(datos!AG121/1000)/$P$2 -> 852.94118 | Q116: =datos!MY121*$Q$2 -> 4328.16 | R116: =datos!BN121 -> 461.01 | S116: 0.0396 | T116: 6147.37 | U116: =T116*S116 -> 243.43585 | V116: =datos!NC121+U116 -> 1779.4659 | W116: =datos!AV121*W$4 -> 6483.5938 | X116: =W116*X$4 -> 518.6875 | Y116: =Y117/(1+(datos!G122/datos!G121-1)) -> 381.71902 | AA116: =AA$121/(1+Z$121) -> 950.98162 | AB116: =(W116-X116-Y116-AA116)/AB$3 -> 231.61028 | AC116: =datos!MJ121 -> 897.46 | AD116: =datos!BB121*AD$4 -> 11716.681 | AE116: =AD116*AE$4 -> 937.33447 | AF116: =Y116 -> 381.71902 | AG116: =AA116 -> 950.98162 | AH116: =(AD116-AE116-AF116-AG116)/AH$3 -> 524.81365 | AI116: =AVERAGE(datos!ML121,datos!MM121,datos!MN121,datos!MO121) -> 1577.59 | AK116: =A116 -> 45748 | AL116: =B116/C116 -> 0.12421153 | AM116: =D116/E116 -> 0.18866227 | AN116: =F116/G116 -> 0.086397637 | AO116: =H116/I116 -> 0.60826647 | AP116: =J116/K116 -> 0.38012183 | AQ116: =L116/M116 -> 0.50011676 | AR116: =N116/O116 -> 0.21801527 | AS116: =P116/Q116 -> 0.19706785 | AT116: =R116/V116 -> 0.25907213 | AU116: =AB116/AC116 -> 0.2580731 | AV116: =AH116/AI116 -> 0.33266796
A117: 45778 | B117: =datos!R122/1000 -> 230 | C117: =datos!MA122 -> 1860.08 | D117: =datos!AI122 -> 430.27 | E117: =datos!MP122 -> 2208.55 | F117: =(datos!AD122/1000)/PP!$F$2 -> 281.29372 | G117: =datos!MH122 -> 3491.53 | H117: =datos!BK122/$H$2 -> 6647.0054 | I117: =datos!NB122 -> 11252 | J117: =datos!BR122/$J$2 -> 2726.75 | K117: =datos!NE122 -> 7401 | L117: =datos!BO122*$L$2 -> 1726.2525 | M117: =datos!NA122 -> 3634 | N117: =datos!BS122*$N$2 -> 2532.6 | O117: =datos!ND122 -> 11790 | P117: =(datos!AG122/1000)/$P$2 -> 882.35294 | Q117: =datos!MY122*$Q$2 -> 4451.7 | R117: =datos!BN122 -> 467.92 | S117: 0.039 | T117: 6316.85 | U117: =T117*S117 -> 246.35715 | V117: =datos!NC122+U117 -> 1790.2972 | W117: =datos!AV122*W$4 -> 5990.9091 | X117: =W117*X$4 -> 479.27273 | Y117: =Y118/(1+(datos!G123/datos!G122-1)) -> 387.44939 | AA117: =AA$121/(1+Z$121) -> 950.98162 | AB117: =(W117-X117-Y117-AA117)/AB$3 -> 208.66027 | AC117: =datos!MJ122 -> 824.36 | AD117: =datos!BB122*AD$4 -> 10179.536 | AE117: =AD117*AE$4 -> 814.36287 | AF117: =Y117 -> 387.44939 | AG117: =AA117 -> 950.98162 | AH117: =(AD117-AE117-AF117-AG117)/AH$3 -> 445.93011 | AI117: =AVERAGE(datos!ML122,datos!MM122,datos!MN122,datos!MO122) -> 1469.4567 | AK117: =A117 -> 45778 | AL117: =B117/C117 -> 0.1236506 | AM117: =D117/E117 -> 0.19482013 | AN117: =F117/G117 -> 0.080564599 | AO117: =H117/I117 -> 0.59073991 | AP117: =J117/K117 -> 0.36842994 | AQ117: =L117/M117 -> 0.47502821 | AR117: =N117/O117 -> 0.21480916 | AS117: =P117/Q117 -> 0.19820584 | AT117: =R117/V117 -> 0.26136443 | AU117: =AB117/AC117 -> 0.25311789 | AV117: =AH117/AI117 -> 0.30346598
A118: 45809 | B118: =datos!R123/1000 -> 200 | C118: =datos!MA123 -> 1844.34 | D118: =datos!AI123 -> 350.32 | E118: =datos!MP123 -> 2221.89 | F118: =(datos!AD123/1000)/PP!$F$2 -> 292.57387 | G118: =datos!MH123 -> 3554.08 | H118: =datos!BK123/$H$2 -> 6715.0635 | I118: =datos!NB123 -> 11390 | J118: =datos!BR123/$J$2 -> 2713.8167 | K118: =datos!NE123 -> 7281 | L118: =datos!BO123*$L$2 -> 1763.93 | M118: =datos!NA123 -> 3711 | N118: =datos!BS123*$N$2 -> 2457 | O118: =datos!ND123 -> 11790 | P118: =(datos!AG123/1000)/$P$2 -> 882.35294 | Q118: =datos!MY123*$Q$2 -> 4519.26 | R118: =datos!BN123 -> 472.87 | S118: 0.0394 | T118: 6312.07 | U118: =T118*S118 -> 248.69556 | V118: =datos!NC123+U118 -> 1822.9656 | W118: =datos!AV123*W$4 -> 5715.2778 | X118: =W118*X$4 -> 457.22222 | Y118: =Y119/(1+(datos!G124/datos!G123-1)) -> 393.7219 | AA118: =AA$121/(1+Z$121) -> 950.98162 | AB118: =(W118-X118-Y118-AA118)/AB$3 -> 195.6676 | AC118: =datos!MJ123 -> 828.41 | AD118: =datos!BB123*AD$4 -> 9416.5162 | AE118: =AD118*AE$4 -> 753.32129 | AF118: =Y118 -> 393.7219 | AG118: =AA118 -> 950.98162 | AH118: =(AD118-AE118-AF118-AG118)/AH$3 -> 406.58285 | AI118: =AVERAGE(datos!ML123,datos!MM123,datos!MN123,datos!MO123) -> 1248.51 | AK118: =A118 -> 45809 | AL118: =B118/C118 -> 0.10843988 | AM118: =D118/E118 -> 0.15766757 | AN118: =F118/G118 -> 0.082320565 | AO118: =H118/I118 -> 0.58955782 | AP118: =J118/K118 -> 0.37272582 | AQ118: =L118/M118 -> 0.47532471 | AR118: =N118/O118 -> 0.20839695 | AS118: =P118/Q118 -> 0.19524279 | AT118: =R118/V118 -> 0.25939601 | AU118: =AB118/AC118 -> 0.23619657 | AV118: =AH118/AI118 -> 0.32565446
A119: 45839 | B119: =datos!R124/1000 -> 200 | C119: =datos!MA124 -> 1848.08 | D119: =datos!AI124 -> 393.79 | E119: =datos!MP124 -> 2194.58 | F119: =(datos!AD124/1000)/PP!$F$2 -> 316.32946 | G119: =datos!MH124 -> 3661.28 | H119: =datos!BK124/$H$2 -> 6755.8984 | I119: =datos!NB124 -> 11375 | J119: =datos!BR124/$J$2 -> 2729.2667 | K119: =datos!NE124 -> 7251 | L119: =datos!BO124*$L$2 -> 1768.2 | M119: =datos!NA124 -> 3872 | N119: =datos!BS124*$N$2 -> 2457 | O119: =datos!ND124 -> 11790 | P119: =(datos!AG124/1000)/$P$2 -> 882.35294 | Q119: =datos!MY124*$Q$2 -> 4572.02 | R119: =datos!BN124 -> 473.26 | S119: 0.0393 | T119: 6360.34 | U119: =T119*S119 -> 249.96136 | V119: =datos!NC124+U119 -> 1834.3214 | W119: =datos!AV124*W$4 -> 6823.6842 | X119: =W119*X$4 -> 545.89474 | Y119: =Y120/(1+(datos!G125/datos!G124-1)) -> 401.20925 | AA119: =AA$121/(1+Z$121) -> 950.98162 | AB119: =(W119-X119-Y119-AA119)/AB$3 -> 246.27993 | AC119: =datos!MJ124 -> 870.54 | AD119: =datos!BB124*AD$4 -> 8193.7078 | AE119: =AD119*AE$4 -> 655.49662 | AF119: =Y119 -> 401.20925 | AG119: =AA119 -> 950.98162 | AH119: =(AD119-AE119-AF119-AG119)/AH$3 -> 343.6678 | AI119: =AVERAGE(datos!ML124,datos!MM124,datos!MN124,datos!MO124) -> 1244.89 | AK119: =A119 -> 45839 | AL119: =B119/C119 -> 0.10822042 | AM119: =D119/E119 -> 0.17943752 | AN119: =F119/G119 -> 0.086398598 | AO119: =H119/I119 -> 0.59392513 | AP119: =J119/K119 -> 0.37639866 | AQ119: =L119/M119 -> 0.45666322 | AR119: =N119/O119 -> 0.20839695 | AS119: =P119/Q119 -> 0.19298974 | AT119: =R119/V119 -> 0.25800277 | AU119: =AB119/AC119 -> 0.28290478 | AV119: =AH119/AI119 -> 0.27606278
A120: 45870 | B120: =datos!R125/1000 -> 200 | C120: =datos!MA125 -> 1811.63 | D120: =datos!AI125 -> 389.21 | E120: =datos!MP125 -> 2218.63 | F120: =(datos!AD125/1000)/PP!$F$2 -> 315.2112 | G120: =datos!MH125 -> 3759.76 | H120: =datos!BK125/$H$2 -> 6932.8494 | I120: =datos!NB125 -> 11281 | J120: =datos!BR125/$J$2 -> 2769.1667 | K120: =datos!NE125 -> 7173 | L120: =datos!BO125*$L$2 -> 1583.4 | M120: =datos!NA125 -> 3835 | N120: =datos!BS125*$N$2 -> 2457 | O120: =datos!ND125 -> 12290 | P120: =(datos!AG125/1000)/$P$2 -> 852.94118 | Q120: =datos!MY125*$Q$2 -> 4644.1 | R120: =datos!BN125 -> 473.74 | S120: 0.0388 | T120: 6441.74 | U120: =T120*S120 -> 249.93951 | V120: =datos!NC125+U120 -> 1866.4495 | W120: =datos!AV125*W$4 -> 5161.3208 | X120: =W120*X$4 -> 412.90566 | Y120: =Y121/(1+(datos!G126/datos!G125-1)) -> 408.73314 | AA120: =AA$121/(1+Z$121) -> 950.98162 | AB120: =(W120-X120-Y120-AA120)/AB$3 -> 169.43502 | AC120: =datos!MJ125 -> 855.43 | AD120: =datos!BB125*AD$4 -> 9871.4963 | AE120: =AD120*AE$4 -> 789.71971 | AF120: =Y120 -> 408.73314 | AG120: =AA120 -> 950.98162 | AH120: =(AD120-AE120-AF120-AG120)/AH$3 -> 429.00344 | AI120: =AVERAGE(datos!ML125,datos!MM125,datos!MN125,datos!MO125) -> 1368.7867 | AK120: =A120 -> 45870 | AL120: =B120/C120 -> 0.11039782 | AM120: =D120/E120 -> 0.17542808 | AN120: =F120/G120 -> 0.083838117 | AO120: =H120/I120 -> 0.61455982 | AP120: =J120/K120 -> 0.38605418 | AQ120: =L120/M120 -> 0.41288136 | AR120: =N120/O120 -> 0.19991863 | AS120: =P120/Q120 -> 0.18366124 | AT120: =R120/V120 -> 0.25381881 | AU120: =AB120/AC120 -> 0.19807 | AV120: =AH120/AI120 -> 0.31341877
A121: 45901 | B121: =datos!R126/1000 -> 225 | C121: =datos!MA126 -> 1745.29 | D121: =datos!AI126 -> 372.98 | E121: =datos!MP126 -> 2215.06 | F121: =(datos!AD126/1000)/PP!$F$2 -> 325.45185 | G121: =datos!MH126 -> 3833.99 | H121: =datos!BK126/$H$2 -> 7221.7181 | I121: =datos!NB126 -> 11542 | J121: =datos!BR126/$J$2 -> 2890.8333 | K121: =datos!NE126 -> 7394 | L121: =datos!BO126*$L$2 -> 1393.7 | M121: =datos!NA126 -> 3808 | N121: =datos!BS126*$N$2 -> 2457 | O121: =datos!ND126 -> 12290 | P121: =(datos!AG126/1000)/$P$2 -> 823.52941 | Q121: =datos!MY126*$Q$2 -> 4707.72 | R121: =datos!BN126 -> 474.6 | S121: 0.0383 | T121: 6506.73 | U121: =T121*S121 -> 249.20776 | V121: =datos!NC126+U121 -> 1829.3878 | W121: =datos!AV126*W$4 -> 5137.594 | X121: =W121*X$4 -> 411.00752 | Y121: =Y122/(1+(datos!G127/datos!G126-1)) -> 417.22028 | Z121: =AZ16 -> 0.15669954 | AA121: 1100 | AB121: =(W121-X121-Y121-AA121)/AB$3 -> 160.46831 | AC121: =datos!MJ126 -> 823 | AD121: =datos!BB126*AD$4 -> 11952.68 | AE121: =AD121*AE$4 -> 956.21442 | AF121: =Y121 -> 417.22028 | AG121: =AA121 -> 1100 | AH121: =(AD121-AE121-AF121-AG121)/AH$3 -> 526.62475 | AI121: =AVERAGE(datos!ML126,datos!MM126,datos!MN126,datos!MO126) -> 1661.9233 | AK121: =A121 -> 45901 | AL121: =B121/C121 -> 0.1289184 | AM121: =D121/E121 -> 0.1683837 | AN121: =F121/G121 -> 0.084885942 | AO121: =H121/I121 -> 0.62569036 | AP121: =J121/K121 -> 0.39097016 | AQ121: =L121/M121 -> 0.36599265 | AR121: =N121/O121 -> 0.19991863 | AS121: =P121/Q121 -> 0.17493169 | AT121: =R121/V121 -> 0.25943106 | AU121: =AB121/AC121 -> 0.19497972 | AV121: =AH121/AI121 -> 0.31687668
A122: 45931 | B122: =datos!R127/1000 -> 225.5 | C122: =datos!MA127 -> 1702.33 | D122: =datos!AI127 -> 473.53 | E122: =datos!MP127 -> 2197.14 | F122: =(datos!AD127/1000)/PP!$F$2 -> 329.05867 | G122: =datos!MH127 -> 3908.68 | H122: =datos!BK127/$H$2 -> 7660.1906 | I122: =datos!NB127 -> 12492 | J122: =datos!BR127/$J$2 -> 2966.3167 | K122: =datos!NE127 -> 7565 | L122: =datos!BO127*$L$2 -> 1401.5802 | M122: =datos!NA127 -> 3775 | N122: =datos!BS127*$N$2 -> 2457 | O122: =datos!ND127 -> 13990 | P122: =(datos!AG127/1000)/$P$2 -> 823.52941 | Q122: =datos!MY127*$Q$2 -> 4841.58 | R122: =datos!BN127 -> 475.43 | S122: 0.0376 | T122: 6630.88 | U122: =T122*S122 -> 249.32109 | V122: =datos!NC127+U122 -> 1841.0311 | W122: =datos!AV127*W$4 -> 4957.6642 | X122: =W122*X$4 -> 396.61314 | Y122: =Y123/(1+(datos!G128/datos!G127-1)) -> 426.99135 | AA122: 1100 | AB122: =(W122-X122-Y122-AA122)/AB$3 -> 151.70299 | AC122: =datos!MJ127 -> 829.02 | AD122: =datos!BB127*AD$4 -> 11348.833 | AE122: =AD122*AE$4 -> 907.90665 | AF122: =Y122 -> 426.99135 | AG122: =AA122 -> 1100 | AH122: =(AD122-AE122-AF122-AG122)/AH$3 -> 495.21862 | AI122: =AVERAGE(datos!ML127,datos!MM127,datos!MN127,datos!MO127) -> 1637.3767 | AK122: =A122 -> 45931 | AL122: =B122/C122 -> 0.1324655 | AM122: =D122/E122 -> 0.21552109 | AN122: =F122/G122 -> 0.084186649 | AO122: =H122/I122 -> 0.6132077 | AP122: =J122/K122 -> 0.3921106 | AQ122: =L122/M122 -> 0.37127954 | AR122: =N122/O122 -> 0.17562545 | AS122: =P122/Q122 -> 0.17009518 | AT122: =R122/V122 -> 0.25824116 | AU122: =AB122/AC122 -> 0.18299075 | AV122: =AH122/AI122 -> 0.30244636
A123: 45962 | B123: =datos!R128/1000 -> 225.5 | C123: =datos!MA128 -> 1684.46 | D123: =datos!AI128 -> 499.75 | E123: =datos!MP128 -> 2199.07 | F123: =(datos!AD128/1000)/PP!$F$2 -> 323.94259 | G123: =datos!MH128 -> 3952.81 | H123: =datos!BK128/$H$2 -> 8878.1919 | I123: =datos!NB128 -> 13405 | J123: =datos!BR128/$J$2 -> 3073.3333 | K123: =datos!NE128 -> 7760 | L123: =datos!BO128*$L$2 -> 1460.725 | M123: =datos!NA128 -> 3813 | N123: =datos!BS128*$N$2 -> 2457 | O123: =datos!ND128 -> 13990 | P123: =(datos!AG128/1000)/$P$2 -> 573.52941 | Q123: =datos!MY128*$Q$2 -> 4861.08 | R123: =datos!BN128 -> 475.44 | S123: 0.0374 | T123: 6681.92 | U123: =T123*S123 -> 249.90381 | V123: =datos!NC128+U123 -> 1811.8238 | W123: =datos!AV128*W$4 -> 5844 | X123: =W123*X$4 -> 467.52 | Y123: =Y124/(1+(datos!G129/datos!G128-1)) -> 437.5505 | AA123: 1100 | AB123: =(W123-X123-Y123-AA123)/AB$3 -> 191.94648 | AC123: =datos!MJ128 -> 940.91 | AD123: =datos!BB128*AD$4 -> 12424.66 | AE123: =AD123*AE$4 -> 993.9728 | AF123: =Y123 -> 437.5505 | AG123: =AA123 -> 1100 | AH123: =(AD123-AE123-AF123-AG123)/AH$3 -> 549.61871 | AI123: =AVERAGE(datos!ML128,datos!MM128,datos!MN128,datos!MO128) -> 1460.7533 | AK123: =A123 -> 45962 | AL123: =B123/C123 -> 0.1338708 | AM123: =D123/E123 -> 0.22725516 | AN123: =F123/G123 -> 0.081952481 | AO123: =H123/I123 -> 0.66230451 | AP123: =J123/K123 -> 0.39604811 | AQ123: =L123/M123 -> 0.38309074 | AR123: =N123/O123 -> 0.17562545 | AS123: =P123/Q123 -> 0.11798395 | AT123: =R123/V123 -> 0.26240962 | AU123: =AB123/AC123 -> 0.20400089 | AV123: =AH123/AI123 -> 0.37625703
A124: 45992 | B124: =datos!R129/1000 -> 245 | C124: =datos!MA129 -> 1701.36 | D124: =datos!AI129 -> 463.2 | E124: =datos!MP129 -> 2253.4 | F124: =(datos!AD129/1000)/PP!$F$2 -> 322.27893 | G124: =datos!MH129 -> 4024 | H124: =datos!BK129/$H$2 -> 9712.6044 | I124: =datos!NB129 -> 15340 | J124: =datos!BR129/$J$2 -> 3027.6599 | K124: =datos!NE129 -> 8162 | L124: =datos!BO129*$L$2 -> 1821.274 | M124: =datos!NA129 -> 3858 | N124: =datos!BS129*$N$2 -> 3061.8 | O124: =datos!ND129 -> 14990 | P124: =(datos!AG129/1000)/$P$2 -> 558.82353 | Q124: =datos!MY129*$Q$2 -> 4892.04 | R124: =datos!BN129 -> 476.6 | S124: 0.0371 | T124: 6758.96 | U124: =T124*S124 -> 250.75742 | V124: =datos!NC129+U124 -> 1867.0674 | W124: =datos!AV129*W$4 -> 6472.4138 | X124: =W124*X$4 -> 517.7931 | Y124: 450 | AA124: 1100 | AB124: =(W124-X124-Y124-AA124)/AB$3 -> 220.23103 | AC124: =datos!MJ129 -> 930.53 | AD124: =datos!BB129*AD$4 -> 10426.594 | AE124: =AD124*AE$4 -> 834.12752 | AF124: =Y124 -> 450 | AG124: =AA124 -> 1100 | AH124: =(AD124-AE124-AF124-AG124)/AH$3 -> 446.80369 | AI124: =AVERAGE(datos!ML129,datos!MM129,datos!MN129,datos!MO129) -> 1238.41 | AK124: =A124 -> 45992 | AL124: =B124/C124 -> 0.14400245 | AM124: =D124/E124 -> 0.20555605 | AN124: =F124/G124 -> 0.080089198 | AO124: =H124/I124 -> 0.63315543 | AP124: =J124/K124 -> 0.37094583 | AQ124: =L124/M124 -> 0.47207724 | AR124: =N124/O124 -> 0.20425617 | AS124: =P124/Q124 -> 0.11423119 | AT124: =R124/V124 -> 0.25526663 | AU124: =AB124/AC124 -> 0.23667269 | AV124: =AH124/AI124 -> 0.36078818
A125: 46023 | B125: =datos!R130/1000 -> 250 | C125: =datos!MA130 -> 1711.31 | D125: =datos!AI130 -> 432.44 | E125: =datos!MP130 -> 2263.26 | F125: =(datos!AD130/1000)/PP!$F$2 -> 320.85074 | G125: =datos!MH130 -> 4122.18 | H125: =datos!BK130/$H$2 -> 9797.7155 | I125: =datos!NB130 -> 16322 | J125: =datos!BR130/$J$2 -> 3143.4933 | K125: =datos!NE130 -> 8241 | L125: =datos!BO130*$L$2 -> 1987.5677 | M125: =datos!NA130 -> 4069 | N125: =datos!BS130*$N$2 -> 3024 | O125: =datos!ND130 -> 14990 | P125: =(datos!AG130/1000)/$P$2 -> 558.82353 | Q125: =datos!MY130*$Q$2 -> 4959.12 | R125: =datos!BN130 -> 478.19 | S125: 0.0371 | T125: 6758.96 | U125: =T125*S125 -> 250.75742 | V125: =datos!NC130+U125 -> 1906.0374 | W125: =datos!AV130*W$4 -> 8851.6949 | X125: =W125*X$4 -> 708.13559 | Y125: =Y124*(1+(datos!G130/datos!G129-1)) -> 462.96729 | Z125: =AZ17 -> 0.094900019 | AA125: =AA124*(1+Z125) -> 1204.39 | AB125: =(W125-X125-Y125-AA125)/AB$3 -> 323.8101 | AC125: =datos!MJ130 -> 1205.82 | AD125: =datos!BB130*AD$4 -> 14565.369 | AE125: =AD125*AE$4 -> 1165.2295 | AF125: =Y125 -> 462.96729 | AG125: =AA125 -> 1204.39 | AH125: =(AD125-AE125-AF125-AG125)/AH$3 -> 651.82123 | AI125: =AVERAGE(datos!ML130,datos!MM130,datos!MN131,datos!MO130) -> 1705.4725 | AK125: =A125 -> 46023 | AL125: =B125/C125 -> 0.14608692 | AM125: =D125/E125 -> 0.19106952 | AN125: =F125/G125 -> 0.077835208 | AO125: =H125/I125 -> 0.60027665 | AP125: =J125/K125 -> 0.38144562 | AQ125: =L125/M125 -> 0.4884659 | AR125: =N125/O125 -> 0.20173449 | AS125: =P125/Q125 -> 0.11268603 | AT125: =R125/V125 -> 0.25088175 | AU125: =AB125/AC125 -> 0.26853933 | AV125: =AH125/AI125 -> 0.38219392
A126: 46054 | B126: =datos!R131/1000 -> 270 | C126: =datos!MA131 -> 1739.93 | D126: =datos!AI131 -> 318.93 | E126: =datos!MP131 -> 2266.39 | F126: =(datos!AD131/1000)/PP!$F$2 -> 312.06699 | G126: =datos!MH131 -> 4201.87 | H126: =datos!BK131/$H$2 -> 10764.553 | I126: =datos!NB131 -> 16853 | J126: =datos!BR131/$J$2 -> 3225.1833 | K126: =datos!NE131 -> 8416 | L126: =datos!BO131*$L$2 -> 2042.6 | M126: =datos!NA131 -> 4347 | N126: =datos!BS131*$N$2 -> 3024 | O126: =datos!ND131 -> 14990 | P126: =(datos!AG131/1000)/$P$2 -> 647.05882 | Q126: =datos!MY131*$Q$2 -> 5049.74 | R126: =datos!BN131 -> 481.03 | S126: 0.0378 | T126: 6704.77 | U126: =T126*S126 -> 253.44031 | V126: =datos!NC131+U126 -> 1945.9003 | W126: =datos!AV131*W$4 -> 9822.2222 | X126: =W126*X$4 -> 785.77778 | Y126: =Y125*(1+(datos!G131/datos!G130-1)) -> 476.3763 | AA126: =AA125*(1+Z126) -> 1204.39 | AB126: =(W126-X126-Y126-AA126)/AB$3 -> 367.78391 | AC126: =datos!MJ131 -> 1303.25 | AD126: =datos!BB131*AD$4 -> 10241.67 | AE126: =AD126*AE$4 -> 819.33358 | AF126: =Y126 -> 476.3763 | AG126: =AA126 -> 1204.39 | AH126: =(AD126-AE126-AF126-AG126)/AH$3 -> 430.08722 | AI126: =AVERAGE(datos!ML131,datos!MM131,datos!MN132,datos!MO131) -> 1476.4875 | AK126: =A126 -> 46054 | AL126: =B126/C126 -> 0.15517866 | AM126: =D126/E126 -> 0.14072159 | AN126: =F126/G126 -> 0.074268598 | AO126: =H126/I126 -> 0.63873216 | AP126: =J126/K126 -> 0.38322045 | AQ126: =L126/M126 -> 0.46988728 | AR126: =N126/O126 -> 0.20173449 | AS126: =P126/Q126 -> 0.12813706 | AT126: =R126/V126 -> 0.24720177 | AU126: =AB126/AC126 -> 0.28220518 | AV126: =AH126/AI126 -> 0.29129079
A127: 46082 | B127: =datos!R132/1000 -> 250 | C127: =datos!MA132 -> 1719.46 | D127: =datos!AI132 -> 393.41 | E127: =datos!MP132 -> 2291.75 | F127: =(datos!AD132/1000)/PP!$F$2 -> 372.95031 | G127: =datos!MH132 -> 4268.7 | H127: =datos!BK132/$H$2 -> 10816.804 | I127: =datos!NB132 -> 18617 | J127: =datos!BR132/$J$2 -> 3402.0833 | K127: =datos!NE132 -> 8944 | L127: =datos!BO132*$L$2 -> 1916.299 | M127: =datos!NA132 -> 4822 | N127: =datos!BS132*$N$2 -> 3024 | O127: =datos!ND132 -> 14990 | P127: =(datos!AG132/1000)/$P$2 -> 705.88235 | Q127: =datos!MY132*$Q$2 -> 5023.64 | R127: =datos!BN132 -> 489.16 | S127: 0.0389 | T127: 6633.7 | U127: =T127*S127 -> 258.05093 | V127: =datos!NC132+U127 -> 1993.7809 | W127: =datos!AV132*W$4 -> 8808.6957 | X127: =W127*X$4 -> 704.69565 | Y127: =Y126*(1+(datos!G132/datos!G131-1)) -> 492.49031 | Z127: =AZ18 -> 0.13159991 | AA127: =AA126*(1+Z127) -> 1362.8876 | AB127: =(W127-X127-Y127-AA127)/AB$3 -> 312.4311 | AC127: =datos!MJ132 -> 1270.56 | AD127: =datos!BB132*AD$4 -> 9826.3749 | AE127: =AD127*AE$4 -> 786.10999 | AF127: =Y127 -> 492.49031 | AG127: =AA127 -> 1362.8876 | AH127: =(AD127-AE127-AF127-AG127)/AH$3 -> 399.16039 | AI127: =AVERAGE(datos!ML132,datos!MM132,datos!MN133,datos!MO132) -> 1424.895 | AK127: =A127 -> 46082 | AL127: =B127/C127 -> 0.14539448 | AM127: =D127/E127 -> 0.17166358 | AN127: =F127/G127 -> 0.087368593 | AO127: =H127/I127 -> 0.58101754 | AP127: =J127/K127 -> 0.38037604 | AQ127: =L127/M127 -> 0.39740751 | AR127: =N127/O127 -> 0.20173449 | AS127: =P127/Q127 -> 0.14051213 | AT127: =R127/V127 -> 0.2453429 | AU127: =AB127/AC127 -> 0.24590031 | AV127: =AH127/AI127 -> 0.28013319
A128: 46113 | B128: =datos!R133/1000 -> 250 | C128: =datos!MA133 -> 1713.73 | D128: =datos!AI133 -> 285.66 | E128: =datos!MP133 -> 2285.55 | F128: =(datos!AD133/1000)/PP!$F$2 -> 373.88774 | G128: =datos!MH133 -> 4383.37 | H128: =datos!BK133/$H$2 -> 10605.263 | I128: =datos!NB133 -> 18091 | J128: =datos!BR133/$J$2 -> 3405.6667 | K128: =datos!NE133 -> 8903 | L128: =datos!BO133*$L$2 -> 2017.6394 | M128: =datos!NA133 -> 4936 | N128: =datos!BS133*$N$2 -> 3213 | O128: =datos!ND133 -> 14990 | P128: =(datos!AG133/1000)/$P$2 -> 705.88235 | Q128: =datos!MY133*$Q$2 -> 5136.06 | R128: =datos!BN133 -> 498.18 | S128: 0.0397 | T128: 6654.37 | U128: =T128*S128 -> 264.17849 | V128: =datos!NC133+U128 -> 2083.8585 | W128: =datos!AV133*W$4 -> 9717.4603 | X128: =W128*X$4 -> 777.39683 | Y128: =Y127*(1+(datos!G133/datos!G132-1)) -> 505.20729 | Z128: =AZ19 -> 0 | AA128: =AA127*(1+Z128) -> 1362.8876 | AB128: =(W128-X128-Y128-AA128)/AB$3 -> 353.59843 | AC128: =datos!MJ133 -> 1305.47 | AD128: =datos!BB133*AD$4 -> 9559.4208 | AE128: =AD128*AE$4 -> 764.75366 | AF128: =Y128 -> 505.20729 | AG128: =AA128 -> 1362.8876 | AH128: =(AD128-AE128-AF128-AG128)/AH$3 -> 384.80957 | AI128: =AVERAGE(datos!ML133,datos!MM133,datos!MN134,datos!MO133) -> 1375.6875 | AK128: =A128 -> 46113 | AL128: =B128/C128 -> 0.14588062 | AM128: =D128/E128 -> 0.12498523 | AN128: =F128/G128 -> 0.08529687 | AO128: =H128/I128 -> 0.58621763 | AP128: =J128/K128 -> 0.38253023 | AQ128: =L128/M128 -> 0.40876001 | AR128: =N128/O128 -> 0.2143429 | AS128: =P128/Q128 -> 0.13743655 | AT128: =R128/V128 -> 0.23906614 | AU128: =AB128/AC128 -> 0.2708591 | AV128: =AH128/AI128 -> 0.27972164
A129: 46143 | B129: =datos!R134/1000 -> 280 | C129: =datos!MA134 -> 1750.9 | D129: =datos!AI134 -> 311.85 | E129: =datos!MP134 -> 2317.53 | F129: =(datos!AD134/1000)/PP!$F$2 -> 395.28342 | G129: =datos!MH134 -> 4471.54 | H129: =datos!BK134/$H$2 -> 10463.251 | I129: =datos!NB134 -> 18154 | J129: =datos!BR134/$J$2 -> 3399.6167 | K129: =datos!NE134 -> 9151 | L129: =datos!BO134*$L$2 -> 2042.999 | M129: =datos!NA134 -> 5048 | N129: =datos!BS134*$N$2 -> 3326.4 | O129: =datos!ND134 -> 15990 | P129: =(datos!AG134/1000)/$P$2 -> 735.29412 | Q129: =datos!MY134*$Q$2 -> 5229.46 | R129: =datos!BN134 -> 508.74 | S129: 0.0402 | T129: 6684.54 | U129: =T129*S129 -> 268.71851 | V129: =datos!NC134+U129 -> 2187.3285 | W129: =datos!AV134*W$4 -> 12702.174 | X129: =W129*X$4 -> 1016.1739 | Y129: =Y128*(1+(datos!G134/datos!G133-1)) -> 516.06911 | Z129: =AZ20 -> 0 | AA129: =AA128*(1+Z129) -> 1362.8876 | AB129: =(W129-X129-Y129-AA129)/AB$3 -> 490.35216 | AC129: =datos!MJ134 -> 1473.32 | AD129: =datos!BB134*AD$4 -> 15740.075 | AE129: =AD129*AE$4 -> 1259.206 | AF129: =Y129 -> 516.06911 | AG129: =AA129 -> 1362.8876 | AH129: =(AD129-AE129-AF129-AG129)/AH$3 -> 700.10625 | AI129: =AVERAGE(datos!ML134,datos!MM134,datos!MN135,datos!MO134) -> 1680.365 | AK129: =A129 -> 46143 | AL129: =B129/C129 -> 0.15991776 | AM129: =D129/E129 -> 0.13456136 | AN129: =F129/G129 -> 0.08839984 | AO129: =H129/I129 -> 0.57636063 | AP129: =J129/K129 -> 0.3715022 | AQ129: =L129/M129 -> 0.40471454 | AR129: =N129/O129 -> 0.20803002 | AS129: =P129/Q129 -> 0.14060613 | AT129: =R129/V129 -> 0.23258509 | AU129: =AB129/AC129 -> 0.33282122 | AV129: =AH129/AI129 -> 0.41663939
A130: 46174 | B130: =datos!R135/1000 -> 280 | C130: =datos!MA135 -> 1783.17 | D130: =datos!AI135 -> 303.4 | E130: =datos!MP135 -> 2311.51 | F130: =(datos!AD135/1000)/PP!$F$2 -> 379.08382 | G130: =datos!MH135 -> 4652.79 | H130: =datos!BK135/$H$2 -> 10426.679 | I130: =datos!NB135 -> 17916 | J130: =datos!BR135/$J$2 -> 3376.2833 | K130: =datos!NE135 -> 9143 | L130: =datos!BO135*$L$2 -> 1990.1 | M130: =datos!NA135 -> 4982 | N130: =datos!BS135*$N$2 -> 3402 | O130: =datos!ND135 -> 15990 | P130: =(datos!AG135/1000)/$P$2 -> 764.70588 | Q130: =datos!MY135*$Q$2 -> 5210.58 | R130: =datos!BN135 -> 518.16 | S130: 0.0395 | T130: 6894.36 | U130: =T130*S130 -> 272.32722 | V130: =datos!NC135+U130 -> 2198.7472 | W130: =datos!AV135*W$4 -> 14334.375 | X130: =W130*X$4 -> 1146.75 | Y130: =Y129*(1+(datos!G135/datos!G134-1)) -> 525.80667 | Z130: =AZ21 -> 0 | AA130: =AA129*(1+Z130) -> 1362.8876 | AB130: =(W130-X130-Y130-AA130)/AB$3 -> 564.94653 | AC130: =datos!MJ135 -> 1544.25 | AD130: =datos!BB135*AD$4 -> 17364.435 | AE130: =AD130*AE$4 -> 1389.1548 | AF130: =Y130 -> 525.80667 | AG130: =AA130 -> 1362.8876 | AH130: =(AD130-AE130-AF130-AG130)/AH$3 -> 782.58808 | AI130: =AVERAGE(datos!ML135,datos!MM135,datos!MN136,datos!MO135) -> 1844.145 | AK130: =A130 -> 46174 | AL130: =B130/C130 -> 0.15702373 | AM130: =D130/E130 -> 0.13125619 | AN130: =F130/G130 -> 0.081474517 | AO130: =H130/I130 -> 0.58197582 | AP130: =J130/K130 -> 0.36927522 | AQ130: =L130/M130 -> 0.39945805 | AR130: =N130/O130 -> 0.21275797 | AS130: =P130/Q130 -> 0.14676022 | AT130: =R130/V130 -> 0.23566147 | AU130: =AB130/AC130 -> 0.36583878 | AV130: =AH130/AI130 -> 0.42436364
A131: 46204 | B131: =datos!R136/1000 -> 280 | C131: =datos!MA136 -> 1838.91 | D131: =datos!AI136 -> 397.35 | E131: =datos!MP136 -> 2329 | F131: =(datos!AD136/1000)/PP!$F$2 -> 401.05578 | G131: =datos!MH136 -> 4732.35 | H131: =datos!BK136/$H$2 -> 10618.6 | I131: =datos!NB136 -> 17704 | J131: =datos!BR136/$J$2 -> 3396.8167 | K131: =datos!NE136 -> 9056 | L131: =datos!BO136*$L$2 -> 1947.6333 | M131: =datos!NA136 -> 4982 | N131: =datos!BS136*$N$2 -> 3213 | O131: =datos!ND136 -> 15990 | P131: =(datos!AG136/1000)/$P$2 -> 764.70588 | Q131: =datos!MY136*$Q$2 -> 5179.42 | R131: =datos!BN136 -> 527.47 | S131: 0.0392 | T131: 7064.67 | U131: =T131*S131 -> 276.93506 | V131: =datos!NC136+U131 -> 2275.7451 | W131: =datos!AV136*W$4 -> 18662.89 | X131: =W131*X$4 -> 1493.0312 | Y131: =Y130*(1+(datos!G136/datos!G135-1)) -> 536.92103 | Z131: =AZ22 -> 0 | AA131: =AA130*(1+Z131) -> 1362.8876 | AB131: =(W131-X131-Y131-AA131)/AB$3 -> 763.50251 | AC131: =datos!MJ136 -> 1865.66 | AD131: =datos!BB136*AD$4 -> 18876.667 | AE131: =AD131*AE$4 -> 1510.1334 | AF131: =Y131 -> 536.92103 | AG131: =AA131 -> 1362.8876 | AH131: =(AD131-AE131-AF131-AG131)/AH$3 -> 859.2625 | AI131: =AVERAGE(datos!ML136,datos!MM136,datos!MN137,datos!MO136) -> 2078.4275 | AK131: =A131 -> 46204 | AL131: =B131/C131 -> 0.15226411 | AM131: =D131/E131 -> 0.1706097 | AN131: =F131/G131 -> 0.0847477 | AO131: =H131/I131 -> 0.59978537 | AP131: =J131/K131 -> 0.37509018 | AQ131: =L131/M131 -> 0.39093403 | AR131: =N131/O131 -> 0.20093809 | AS131: =P131/Q131 -> 0.14764315 | AT131: =R131/V131 -> 0.23177904 | AU131: =AB131/AC131 -> 0.4092399 | AV131: =AH131/AI131 -> 0.41341952
A132: 46235 | B132: =datos!R137/1000 -> 300 | C132: =datos!MA137 -> 1858.04 | D132: =datos!AI137 -> 380.74 | E132: =datos!MP137 -> 2316 | F132: =(datos!AD137/1000)/PP!$F$2 -> 418.33828 | G132: =datos!MH137 -> 4909.98 | H132: =datos!BK137/$H$2 -> 10663.512 | I132: =datos!NB137 -> 17650 | J132: =datos!BR137/$J$2 -> 3428.0833 | K132: =datos!NE137 -> 9235 | L132: =datos!BO137*$L$2 -> 1901.2 | M132: =datos!NA137 -> 4934 | N132: =datos!BS137*$N$2 -> 3213 | O132: =datos!ND137 -> 15990 | P132: =(datos!AG137/1000)/$P$2 -> 823.52941 | Q132: =datos!MY137*$Q$2 -> 5238.2 | R132: =datos!BN137 -> 535.12 | S132: 0.0385 | T132: 7269.15 | U132: =T132*S132 -> 279.86227 | V132: =datos!NC137+U132 -> 2288.2623 | W132: =datos!AV137*W$4 -> 22163.04 | X132: =W132*X$4 -> 1773.0432 | Y132: =Y131*(1+(datos!G137/datos!G136-1)) -> 545.82965 | Z132: =AZ23 -> 0 | AA132: =AA131*(1+Z132) -> 1362.8876 | AB132: =(W132-X132-Y132-AA132)/AB$3 -> 924.06398 | AC132: =datos!MJ137 -> 2275.91 | AD132: =datos!BB137*AD$4 -> 18568.697 | AE132: =AD132*AE$4 -> 1485.4958 | AF132: =Y132 -> 545.82965 | AG132: =AA132 -> 1362.8876 | AH132: =(AD132-AE132-AF132-AG132)/AH$3 -> 843.0269 | AI132: =AVERAGE(datos!ML137,datos!MM137,datos!MN138,datos!MO137) -> 2419.955 | AK132: =A132 -> 46235 | AL132: =B132/C132 -> 0.16146046 | AM132: =D132/E132 -> 0.16439551 | AN132: =F132/G132 -> 0.085201625 | AO132: =H132/I132 -> 0.60416497 | AP132: =J132/K132 -> 0.37120556 | AQ132: =L132/M132 -> 0.38532631 | AR132: =N132/O132 -> 0.20093809 | AS132: =P132/Q132 -> 0.15721611 | AT132: =R132/V132 -> 0.23385431 | AU132: =AB132/AC132 -> 0.40601956 | AV132: =AH132/AI132 -> 0.3483647
AK135: 42948 | AL135: =VLOOKUP($AK135,$AK$4:$AV$131,2) -> 0.19058824 | AM135: =VLOOKUP($AK135,$AK$4:$AV$131,3) -> 0.28557852 | AN135: =VLOOKUP($AK135,$AK$4:$AV$131,4) -> 0.091432437 | AO135: =VLOOKUP($AK135,$AK$4:$AV$131,5) -> 0.62695266 | AP135: =VLOOKUP($AK135,$AK$4:$AV$131,6) -> 0.2888828 | AQ135: =VLOOKUP($AK135,$AK$4:$AV$131,7) -> 0.43623112 | AS135: =VLOOKUP($AK135,$AK$4:$AV$131,9) -> 0.28067227 | AZ135: =AK144 -> 46235 | BB135: prom ant
...

Sheet datos
A1: ran_dat | B1: Columna | D1: =+COLUMN() -> 4 | E1: =+COLUMN() -> 5 | F1: =+COLUMN() -> 6 | G1: =+COLUMN() -> 7 | H1: =+COLUMN() -> 8 | I1: =+COLUMN() -> 9 | J1: =+COLUMN() -> 10 | K1: =+COLUMN() -> 11 | L1: =+COLUMN() -> 12 | N1: =+COLUMN() -> 14 | O1: =+COLUMN() -> 15 | P1: =+COLUMN() -> 16 | Q1: =+COLUMN() -> 17 | R1: =+COLUMN() -> 18 | S1: =+COLUMN() -> 19 | T1: =+COLUMN() -> 20 | U1: =+COLUMN() -> 21 | ... DI1: =+COLUMN() -> 113 | DK1: =+COLUMN() -> 115 | DL1: =+COLUMN() -> 116 | DM1: =+COLUMN() -> 117 | DN1: =+COLUMN() -> 118 | DO1: =+COLUMN() -> 119 | DP1: =+COLUMN() -> 120 | DQ1: =+COLUMN() -> 121 | DR1: =+COLUMN() -> 122 | ... FD1: =+COLUMN() -> 160 | FF1: =+COLUMN() -> 162 | FG1: =+COLUMN() -> 163 | FH1: =+COLUMN() -> 164 | FI1: =+COLUMN() -> 165 | FJ1: =+COLUMN() -> 166 | FK1: =+COLUMN() -> 167 | FL1: =+COLUMN() -> 168 | FM1: =+COLUMN() -> 169 | ... HQ1: =+COLUMN() -> 225 | HS1: =+COLUMN() -> 227 | HT1: =+COLUMN() -> 228 | HU1: =+COLUMN() -> 229 | HV1: =+COLUMN() -> 230 | HW1: =+COLUMN() -> 231 | HX1: =+COLUMN() -> 232 | HY1: =+COLUMN() -> 233 | HZ1: =+COLUMN() -> 234 | ... JD1: =+COLUMN() -> 264 | JF1: =+COLUMN() -> 266 | JG1: =+COLUMN() -> 267 | JH1: =+COLUMN() -> 268 | JI1: =+COLUMN() -> 269 | JJ1: =+COLUMN() -> 270 | JK1: =+COLUMN() -> 271 | JL1: =+COLUMN() -> 272 | JM1: =+COLUMN() -> 273 | ... LX1: =+COLUMN() -> 336 | LZ1: =+COLUMN() -> 338 | MA1: =+COLUMN() -> 339 | MB1: =+COLUMN() -> 340 | MC1: =+COLUMN() -> 341 | MD1: =+COLUMN() -> 342 | ME1: =+COLUMN() -> 343 | MF1: =+COLUMN() -> 344 | MG1: =+COLUMN() -> 345 | ... NE1: =+COLUMN() -> 369
F2: Generales | N2: Productos | BY2: Actividad | DK2: Actividad | FF2: Actividad | IJ2: 46466688 | IP2: =IJ2 -> 46466688
